Workbook

Sheet WORKLOAD_TEAMS_OLD1
A1: PRIORYTET | B1: DATE | C1: DATE | D1: TOTALS | E1: =TEXT(DATE(2024,1,1)+(E2-1)*7-WEEKDAY(DATE(2024,1,1),2)+1,"dd.mm")&"-"&TEXT(DATE(2024,1,1)+(E2-1)*7-WEEKDAY(DATE(2024,1,1),2)+7,"dd.mm") -> 11.03-17.03 | F1: =TEXT(DATE(2024,1,1)+(F2-1)*7-WEEKDAY(DATE(2024,1,1),2)+1,"dd.mm")&"-"&TEXT(DATE(2024,1,1)+(F2-1)*7-WEEKDAY(DATE(2024,1,1),2)+7,"dd.mm") -> 18.03-24.03 | G1: =TEXT(DATE(2024,1,1)+(G2-1)*7-WEEKDAY(DATE(2024,1,1),2)+1,"dd.mm")&"-"&TEXT(DATE(2024,1,1)+(G2-1)*7-WEEKDAY(DATE(2024,1,1),2)+7,"dd.mm") -> 25.03-31.03 | H1: =TEXT(DATE(2024,1,1)+(H2-1)*7-WEEKDAY(DATE(2024,1,1),2)+1,"dd.mm")&"-"&TEXT(DATE(2024,1,1)+(H2-1)*7-WEEKDAY(DATE(2024,1,1),2)+7,"dd.mm") -> 01.04-07.04 | I1: =TEXT(DATE(2024,1,1)+(I2-1)*7-WEEKDAY(DATE(2024,1,1),2)+1,"dd.mm")&"-"&TEXT(DATE(2024,1,1)+(I2-1)*7-WEEKDAY(DATE(2024,1,1),2)+7,"dd.mm") -> 08.04-14.04 | J1: =TEXT(DATE(2024,1,1)+(J2-1)*7-WEEKDAY(DATE(2024,1,1),2)+1,"dd.mm")&"-"&TEXT(DATE(2024,1,1)+(J2-1)*7-WEEKDAY(DATE(2024,1,1),2)+7,"dd.mm") -> 15.04-21.04 | K1: =TEXT(DATE(2024,1,1)+(K2-1)*7-WEEKDAY(DATE(2024,1,1),2)+1,"dd.mm")&"-"&TEXT(DATE(2024,1,1)+(K2-1)*7-WEEKDAY(DATE(2024,1,1),2)+7,"dd.mm") -> 22.04-28.04 | L1: =TEXT(DATE(2024,1,1)+(L2-1)*7-WEEKDAY(DATE(2024,1,1),2)+1,"dd.mm")&"-"&TEXT(DATE(2024,1,1)+(L2-1)*7-WEEKDAY(DATE(2024,1,1),2)+7,"dd.mm") -> 29.04-05.05 | ... AT1: =TEXT(DATE(2024,1,1)+(AT2-1)*7-WEEKDAY(DATE(2024,1,1),2)+1,"dd.mm")&"-"&TEXT(DATE(2024,1,1)+(AT2-1)*7-WEEKDAY(DATE(2024,1,1),2)+7,"dd.mm") -> 23.12-29.12 | AU1: =TEXT(DATE(2025,1,1)+(AU2-1)*7-WEEKDAY(DATE(2025,1,1),2)+1,"dd.mm")&"-"&TEXT(DATE(2025,1,1)+(AU2-1)*7-WEEKDAY(DATE(2025,1,1),2)+7,"dd.mm") -> 30.12-05.01 | AV1: =TEXT(DATE(2025,1,1)+(AV2-1)*7-WEEKDAY(DATE(2025,1,1),2)+1,"dd.mm")&"-"&TEXT(DATE(2025,1,1)+(AV2-1)*7-WEEKDAY(DATE(2025,1,1),2)+7,"dd.mm") -> 06.01-12.01 | AW1: =TEXT(DATE(2025,1,1)+(AW2-1)*7-WEEKDAY(DATE(2025,1,1),2)+1,"dd.mm")&"-"&TEXT(DATE(2025,1,1)+(AW2-1)*7-WEEKDAY(DATE(2025,1,1),2)+7,"dd.mm") -> 13.01-19.01 | AX1: =TEXT(DATE(2025,1,1)+(AX2-1)*7-WEEKDAY(DATE(2025,1,1),2)+1,"dd.mm")&"-"&TEXT(DATE(2025,1,1)+(AX2-1)*7-WEEKDAY(DATE(2025,1,1),2)+7,"dd.mm") -> 20.01-26.01 | AY1: =TEXT(DATE(2025,1,1)+(AY2-1)*7-WEEKDAY(DATE(2025,1,1),2)+1,"dd.mm")&"-"&TEXT(DATE(2025,1,1)+(AY2-1)*7-WEEKDAY(DATE(2025,1,1),2)+7,"dd.mm") -> 27.01-02.02 | AZ1: =TEXT(DATE(2025,1,1)+(AZ2-1)*7-WEEKDAY(DATE(2025,1,1),2)+1,"dd.mm")&"-"&TEXT(DATE(2025,1,1)+(AZ2-1)*7-WEEKDAY(DATE(2025,1,1),2)+7,"dd.mm") -> 03.02-09.02 | BA1: =TEXT(DATE(2025,1,1)+(BA2-1)*7-WEEKDAY(DATE(2025,1,1),2)+1,"dd.mm")&"-"&TEXT(DATE(2025,1,1)+(BA2-1)*7-WEEKDAY(DATE(2025,1,1),2)+7,"dd.mm") -> 10.02-16.02 | BB1: =TEXT(DATE(2025,1,1)+(BB2-1)*7-WEEKDAY(DATE(2025,1,1),2)+1,"dd.mm")&"-"&TEXT(DATE(2025,1,1)+(BB2-1)*7-WEEKDAY(DATE(2025,1,1),2)+7,"dd.mm") -> 17.02-23.02 | ... CT1: =TEXT(DATE(2025,1,1)+(CT2-1)*7-WEEKDAY(DATE(2025,1,1),2)+1,"dd.mm")&"-"&TEXT(DATE(2025,1,1)+(CT2-1)*7-WEEKDAY(DATE(2025,1,1),2)+7,"dd.mm") -> 22.12-28.12
C2: WEEK | E2: 11 | F2: 12 | G2: 13 | H2: 14 | I2: 15 | J2: 16 | K2: 17 | L2: 18 | M2: 19 | N2: 20 | O2: 21 | P2: 22 | Q2: 23 | R2: 24 | S2: 25 | T2: 26 | U2: 27 | V2: 28 | W2: 29 | X2: 30 | Y2: 31 | Z2: 32 | AA2: 33 | AB2: 34 | AC2: 35 | AD2: 36 | AE2: 37 | AF2: 38 | AG2: 39 | AH2: 40 | AI2: 41 | AJ2: 42 | AK2: 43 | AL2: 44 | AM2: 45 | AN2: 46 | AO2: 47 | AP2: 48 | AQ2: 49 | AR2: 50 | AS2: 51 | AT2: 52 | AU2: 1 | AV2: 2 | AW2: 3 | AX2: 4 | AY2: 5 | AZ2: 6 | BA2: 7 | BB2: 8 | BC2: 9 | BD2: 10 | BE2: 11 | BF2: 12 | BG2: 13 | BH2: 14 | BI2: 15 | BJ2: 16 | BK2: 17 | BL2: 18 | BM2: 19 | BN2: 20 | BO2: 21 | BP2: 22 | BQ2: 23 | BR2: 24 | BS2: 25 | BT2: 26 | BU2: 27 | BV2: 28 | BW2: 29 | BX2: 30 | BY2: 31 | BZ2: 32 | CA2: 33 | CB2: 34 | CC2: 35 | CD2: 36 | CE2: 37 | CF2: 38 | CG2: 39 | CH2: 40 | CI2: 41 | CJ2: 42 | CK2: 43 | CL2: 44 | CM2: 45 | CN2: 46 | CO2: 47 | CP2: 48 | CQ2: 49 | CR2: 50 | CS2: 51 | CT2: 52
B3: PROJECTS & FUNCTIONALITIES CAPACITY | C3: ALF | E3: =CAPACITY!G2 -> 27.342 | F3: =OFFSET(CAPACITY!$G$2,0,7*(F$2-$E$2)) -> 27.342 | G3: =OFFSET(CAPACITY!$G$2,0,7*(G$2-$E$2)) -> 27.342 | H3: =OFFSET(CAPACITY!$G$2,0,7*(H$2-$E$2)) -> 21.462 | I3: =OFFSET(CAPACITY!$G$2,0,7*(I$2-$E$2)) -> 27.342 | J3: =OFFSET(CAPACITY!$G$2,0,7*(J$2-$E$2)) -> 27.342 | K3: =OFFSET(CAPACITY!$G$2,0,7*(K$2-$E$2)) -> 27.342 | L3: =OFFSET(CAPACITY!$G$2,0,7*(L$2-$E$2)) -> 14.028 | M3: =OFFSET(CAPACITY!$G$2,0,7*(M$2-$E$2)) -> 28.371 | ... AT3: =OFFSET(CAPACITY!$G$2,0,7*(AT$2-$E$2)) -> 12.39 | AU3: =OFFSET(CAPACITY!$G$2,0,7*(AU$2+52-$E$2)) -> 17.346 | AV3: =OFFSET(CAPACITY!$G$2,0,7*(AV$2+52-$E$2)) -> 23.247 | AW3: =OFFSET(CAPACITY!$G$2,0,7*(AW$2+52-$E$2)) -> 28.728 | AX3: =OFFSET(CAPACITY!$G$2,0,7*(AX$2+52-$E$2)) -> 28.728 | AY3: =OFFSET(CAPACITY!$G$2,0,7*(AY$2+52-$E$2)) -> 26.439 | AZ3: =OFFSET(CAPACITY!$G$2,0,7*(AZ$2+52-$E$2)) -> 28.455 | BA3: =OFFSET(CAPACITY!$G$2,0,7*(BA$2+52-$E$2)) -> 27.342 | BB3: =OFFSET(CAPACITY!$G$2,0,7*(BB$2+52-$E$2)) -> 28.581 | ... CT3: =OFFSET(CAPACITY!$G$2,0,7*(CT$2+52-$E$2)) -> 9.66
C4: WAREX | E4: =CAPACITY!G4 -> 10.388559 | F4: =OFFSET(CAPACITY!$G$4,0,7*(F$2-$E$2)) -> 10.388559 | G4: =OFFSET(CAPACITY!$G$4,0,7*(G$2-$E$2)) -> 10.388559 | H4: =OFFSET(CAPACITY!$G$4,0,7*(H$2-$E$2)) -> 8.1544599 | I4: =OFFSET(CAPACITY!$G$4,0,7*(I$2-$E$2)) -> 10.388559 | J4: =OFFSET(CAPACITY!$G$4,0,7*(J$2-$E$2)) -> 10.069402 | K4: =OFFSET(CAPACITY!$G$4,0,7*(K$2-$E$2)) -> 10.388559 | L4: =OFFSET(CAPACITY!$G$4,0,7*(L$2-$E$2)) -> 1.9149417 | M4: =OFFSET(CAPACITY!$G$4,0,7*(M$2-$E$2)) -> 9.4310877 | ... AT4: =OFFSET(CAPACITY!$G$4,0,7*(AT$2-$E$2)) -> 9.4151298 | AU4: =OFFSET(CAPACITY!$G$4,0,7*(AU$2+52-$E$2)) -> 13.181182 | AV4: =OFFSET(CAPACITY!$G$4,0,7*(AV$2+52-$E$2)) -> 17.665337 | AW4: =OFFSET(CAPACITY!$G$4,0,7*(AW$2+52-$E$2)) -> 21.830335 | AX4: =OFFSET(CAPACITY!$G$4,0,7*(AX$2+52-$E$2)) -> 21.830335 | AY4: =OFFSET(CAPACITY!$G$4,0,7*(AY$2+52-$E$2)) -> 20.09093 | AZ4: =OFFSET(CAPACITY!$G$4,0,7*(AZ$2+52-$E$2)) -> 21.622883 | BA4: =OFFSET(CAPACITY!$G$4,0,7*(BA$2+52-$E$2)) -> 20.777117 | BB4: =OFFSET(CAPACITY!$G$4,0,7*(BB$2+52-$E$2)) -> 21.71863 | ... CT4: =OFFSET(CAPACITY!$G$4,0,7*(CT$2+52-$E$2)) -> 7.3406097
C5: OPTIMUS | E5: =CAPACITY!G6 -> 21.241748 | F5: =OFFSET(CAPACITY!$G$6,0,7*(F$2-$E$2)) -> 21.241748 | G5: =OFFSET(CAPACITY!$G$6,0,7*(G$2-$E$2)) -> 21.241748 | H5: =OFFSET(CAPACITY!$G$6,0,7*(H$2-$E$2)) -> 16.67363 | I5: =OFFSET(CAPACITY!$G$6,0,7*(I$2-$E$2)) -> 21.241748 | J5: =OFFSET(CAPACITY!$G$6,0,7*(J$2-$E$2)) -> 21.241748 | K5: =OFFSET(CAPACITY!$G$6,0,7*(K$2-$E$2)) -> 21.241748 | L5: =OFFSET(CAPACITY!$G$6,0,7*(L$2-$E$2)) -> 8.995678 | M5: =OFFSET(CAPACITY!$G$6,0,7*(M$2-$E$2)) -> 18.395459 | ... AT5: =OFFSET(CAPACITY!$G$6,0,7*(AT$2-$E$2)) -> 7.9063577 | AU5: =OFFSET(CAPACITY!$G$6,0,7*(AU$2+52-$E$2)) -> 12.281209 | AV5: =OFFSET(CAPACITY!$G$6,0,7*(AV$2+52-$E$2)) -> 14.705825 | AW5: =OFFSET(CAPACITY!$G$6,0,7*(AW$2+52-$E$2)) -> 20.082148 | AX5: =OFFSET(CAPACITY!$G$6,0,7*(AX$2+52-$E$2)) -> 20.082148 | AY5: =OFFSET(CAPACITY!$G$6,0,7*(AY$2+52-$E$2)) -> 18.852271 | AZ5: =OFFSET(CAPACITY!$G$6,0,7*(AZ$2+52-$E$2)) -> 19.027967 | BA5: =OFFSET(CAPACITY!$G$6,0,7*(BA$2+52-$E$2)) -> 17.270999 | BB5: =OFFSET(CAPACITY!$G$6,0,7*(BB$2+52-$E$2)) -> 15.074789 | ... CT5: =OFFSET(CAPACITY!$G$6,0,7*(CT$2+52-$E$2)) -> 4.9195114
C6: MASH | E6: =CAPACITY!G8 -> 8.1375 | F6: =OFFSET(CAPACITY!$G$8,0,7*(F$2-$E$2)) -> 8.1375 | G6: =OFFSET(CAPACITY!$G$8,0,7*(G$2-$E$2)) -> 8.1375 | H6: =OFFSET(CAPACITY!$G$8,0,7*(H$2-$E$2)) -> 6.3875 | I6: =OFFSET(CAPACITY!$G$8,0,7*(I$2-$E$2)) -> 8.1375 | J6: =OFFSET(CAPACITY!$G$8,0,7*(J$2-$E$2)) -> 8.1375 | K6: =OFFSET(CAPACITY!$G$8,0,7*(K$2-$E$2)) -> 8.1375 | L6: =OFFSET(CAPACITY!$G$8,0,7*(L$2-$E$2)) -> 5.25 | M6: =OFFSET(CAPACITY!$G$8,0,7*(M$2-$E$2)) -> 8.1375 | ... AT6: =OFFSET(CAPACITY!$G$8,0,7*(AT$2-$E$2)) -> 2.205 | AU6: =OFFSET(CAPACITY!$G$8,0,7*(AU$2+52-$E$2)) -> 3.4825 | AV6: =OFFSET(CAPACITY!$G$8,0,7*(AV$2+52-$E$2)) -> 6.0375 | AW6: =OFFSET(CAPACITY!$G$8,0,7*(AW$2+52-$E$2)) -> 7.91 | AX6: =OFFSET(CAPACITY!$G$8,0,7*(AX$2+52-$E$2)) -> 7.21 | AY6: =OFFSET(CAPACITY!$G$8,0,7*(AY$2+52-$E$2)) -> 6.86 | AZ6: =OFFSET(CAPACITY!$G$8,0,7*(AZ$2+52-$E$2)) -> 6.7375 | BA6: =OFFSET(CAPACITY!$G$8,0,7*(BA$2+52-$E$2)) -> 6.16 | BB6: =OFFSET(CAPACITY!$G$8,0,7*(BB$2+52-$E$2)) -> 7.56 | ... CT6: =OFFSET(CAPACITY!$G$8,0,7*(CT$2+52-$E$2)) -> 3.15
C7: MAGENTO | E7: =CAPACITY!G10 -> 23.2875 | F7: =OFFSET(CAPACITY!$G$10,0,7*(F$2-$E$2)) -> 23.2875 | G7: =OFFSET(CAPACITY!$G$10,0,7*(G$2-$E$2)) -> 23.2875 | H7: =OFFSET(CAPACITY!$G$10,0,7*(H$2-$E$2)) -> 22.5375 | I7: =OFFSET(CAPACITY!$G$10,0,7*(I$2-$E$2)) -> 23.2875 | J7: =OFFSET(CAPACITY!$G$10,0,7*(J$2-$E$2)) -> 23.2875 | K7: =OFFSET(CAPACITY!$G$10,0,7*(K$2-$E$2)) -> 23.2875 | L7: =OFFSET(CAPACITY!$G$10,0,7*(L$2-$E$2)) -> 20.25 | M7: =OFFSET(CAPACITY!$G$10,0,7*(M$2-$E$2)) -> 24.1575 | ... AT7: =OFFSET(CAPACITY!$G$10,0,7*(AT$2-$E$2)) -> 12.1125 | AU7: =OFFSET(CAPACITY!$G$10,0,7*(AU$2+52-$E$2)) -> 15.6675 | AV7: =OFFSET(CAPACITY!$G$10,0,7*(AV$2+52-$E$2)) -> 19.18875 | AW7: =OFFSET(CAPACITY!$G$10,0,7*(AW$2+52-$E$2)) -> 24.1575 | AX7: =OFFSET(CAPACITY!$G$10,0,7*(AX$2+52-$E$2)) -> 24.1575 | AY7: =OFFSET(CAPACITY!$G$10,0,7*(AY$2+52-$E$2)) -> 24.1575 | AZ7: =OFFSET(CAPACITY!$G$10,0,7*(AZ$2+52-$E$2)) -> 24.1575 | BA7: =OFFSET(CAPACITY!$G$10,0,7*(BA$2+52-$E$2)) -> 24.1575 | BB7: =OFFSET(CAPACITY!$G$10,0,7*(BB$2+52-$E$2)) -> 24.1575 | ... CT7: =OFFSET(CAPACITY!$G$10,0,7*(CT$2+52-$E$2)) -> 7.5
B8: PROJECTS & FUNCTIONALITIES CAPACITY UTILISATION | C8: ALF | E8: =E3-SUMIF($C$13:$C$506,$C8,E13:E506) -> 15.342 | F8: =F3-SUMIF($C$13:$C$506,$C8,F13:F506) -> 15.342 | G8: =G3-SUMIF($C$13:$C$506,$C8,G13:G506) -> 15.342 | H8: =H3-SUMIF($C$13:$C$506,$C8,H13:H506) -> 9.462 | I8: =I3-SUMIF($C$13:$C$506,$C8,I13:I506) -> 15.342 | J8: =J3-SUMIF($C$13:$C$506,$C8,J13:J506) -> 15.342 | K8: =K3-SUMIF($C$13:$C$506,$C8,K13:K506) -> 5.342 | L8: =L3-SUMIF($C$13:$C$506,$C8,L13:L506) -> -3.972 | ... BI8: =BI3-SUMIF($C$13:$C$506,$C8,BI13:BI506) -> 30.702
C9: WAREX | E9: =E4-SUMIF($C$13:$C$506,$C9,E13:E506) -> 10.388559 | F9: =F4-SUMIF($C$13:$C$506,$C9,F13:F506) -> 10.388559 | G9: =G4-SUMIF($C$13:$C$506,$C9,G13:G506) -> 10.388559 | H9: =H4-SUMIF($C$13:$C$506,$C9,H13:H506) -> 0.15445992 | I9: =I4-SUMIF($C$13:$C$506,$C9,I13:I506) -> 2.3885585 | J9: =J4-SUMIF($C$13:$C$506,$C9,J13:J506) -> 2.0694016 | K9: =K4-SUMIF($C$13:$C$506,$C9,K13:K506) -> -3.6114415 | L9: =L4-SUMIF($C$13:$C$506,$C9,L13:L506) -> -4.0850583 | ... BI9: =BI4-SUMIF($C$13:$C$506,$C9,BI13:BI506) -> 23.330373
C10: OPTIMUS | E10: =E5-SUMIF($C$13:$C$506,$C10,E13:E506) -> 21.241748 | F10: =F5-SUMIF($C$13:$C$506,$C10,F13:F506) -> 21.241748 | G10: =G5-SUMIF($C$13:$C$506,$C10,G13:G506) -> 21.241748 | H10: =H5-SUMIF($C$13:$C$506,$C10,H13:H506) -> 16.67363 | I10: =I5-SUMIF($C$13:$C$506,$C10,I13:I506) -> 21.241748 | J10: =J5-SUMIF($C$13:$C$506,$C10,J13:J506) -> 21.241748 | K10: =K5-SUMIF($C$13:$C$506,$C10,K13:K506) -> 21.241748 | L10: =L5-SUMIF($C$13:$C$506,$C10,L13:L506) -> 8.995678 | ... BI10: =BI5-SUMIF($C$13:$C$506,$C10,BI13:BI506) -> 17.868368
C11: MASH | E11: =E6-SUMIF($C$13:$C$506,$C11,E13:E506) -> 7.6375 | F11: =F6-SUMIF($C$13:$C$506,$C11,F13:F506) -> 7.6375 | G11: =G6-SUMIF($C$13:$C$506,$C11,G13:G506) -> 7.6375 | H11: =H6-SUMIF($C$13:$C$506,$C11,H13:H506) -> 4.8875 | I11: =I6-SUMIF($C$13:$C$506,$C11,I13:I506) -> 5.6375 | J11: =J6-SUMIF($C$13:$C$506,$C11,J13:J506) -> 3.6375 | K11: =K6-SUMIF($C$13:$C$506,$C11,K13:K506) -> 0.6375 | L11: =L6-SUMIF($C$13:$C$506,$C11,L13:L506) -> -2.25 | ... BI11: =BI6-SUMIF($C$13:$C$506,$C11,BI13:BI506) -> 8.1375
C12: MAGENTO | E12: =E7-SUMIF($C$13:$C$506,$C12,E13:E506) -> 23.2875 | F12: =F7-SUMIF($C$13:$C$506,$C12,F13:F506) -> 23.2875 | G12: =G7-SUMIF($C$13:$C$506,$C12,G13:G506) -> 23.2875 | H12: =H7-SUMIF($C$13:$C$506,$C12,H13:H506) -> 22.5375 | I12: =I7-SUMIF($C$13:$C$506,$C12,I13:I506) -> 23.2875 | J12: =J7-SUMIF($C$13:$C$506,$C12,J13:J506) -> 11.2875 | K12: =K7-SUMIF($C$13:$C$506,$C12,K13:K506) -> 0.2875 | L12: =L7-SUMIF($C$13:$C$506,$C12,L13:L506) -> 2.25 | ... BI12: =BI7-SUMIF($C$13:$C$506,$C12,BI13:BI506) -> 24.4125
B13: DŁUG FUNKCJONALNY ALF | C13: ALF | D13: =SUM(E13:CT13) -> 504 | E13: 12 | F13: 12 | G13: 12 | H13: 12 | I13: 12 | J13: 12 | K13: 12 | L13: 12 | M13: 12 | N13: 12 | O13: 12 | P13: 12 | Q13: 12 | R13: 12 | S13: 12 | T13: 12 | U13: 12 | V13: 12 | W13: 12 | X13: 12 | Y13: 12 | Z13: 12 | AA13: 12 | AB13: 12 | AC13: 12 | AD13: 12 | AE13: 12 | AF13: 12 | AG13: 12 | AH13: 12 | AI13: 12 | AJ13: 12 | AK13: 12 | AL13: 12 | AM13: 12 | AN13: 12 | AO13: 12 | AP13: 12 | AQ13: 12 | AR13: 12 | AS13: 12 | AT13: 12
C14: WAREX | D14: =SUM(E14:CT14) -> 0
C15: OPTIMUS | D15: =SUM(E15:CT15) -> 0
C16: MASH | D16: =SUM(E16:CT16) -> 21 | E16: 0.5 | F16: 0.5 | G16: 0.5 | H16: 0.5 | I16: 0.5 | J16: 0.5 | K16: 0.5 | L16: 0.5 | M16: 0.5 | N16: 0.5 | O16: 0.5 | P16: 0.5 | Q16: 0.5 | R16: 0.5 | S16: 0.5 | T16: 0.5 | U16: 0.5 | V16: 0.5 | W16: 0.5 | X16: 0.5 | Y16: 0.5 | Z16: 0.5 | AA16: 0.5 | AB16: 0.5 | AC16: 0.5 | AD16: 0.5 | AE16: 0.5 | AF16: 0.5 | AG16: 0.5 | AH16: 0.5 | AI16: 0.5 | AJ16: 0.5 | AK16: 0.5 | AL16: 0.5 | AM16: 0.5 | AN16: 0.5 | AO16: 0.5 | AP16: 0.5 | AQ16: 0.5 | AR16: 0.5 | AS16: 0.5 | AT16: 0.5
C17: MAGENTO | D17: =SUM(E17:CT17) -> 0
A18: 0 | B18: Project - Portal B2B 1(1.5) | C18: ALF | D18: =SUM(E18:CT18) -> 2 | K18: 2
C19: WAREX | D19: =SUM(E19:CT19) -> 0
C20: OPTIMUS | D20: =SUM(E20:CT20) -> 0
C21: MASH | D21: =SUM(E21:CT21) -> 2 | J21: 1 | M21: 1
C22: MAGENTO | D22: =SUM(E22:CT22) -> 27 | J22: 6 | K22: 3 | L22: 3 | M22: 3 | N22: 2 | R22: 5 | S22: 5
A23: 0 | B23: Project - Multibrand for iMad | C23: ALF | D23: =SUM(E23:CT23) -> 2 | K23: 2
C24: WAREX | D24: =SUM(E24:CT24) -> 0
C25: OPTIMUS | D25: =SUM(E25:CT25) -> 0
C26: MASH | D26: =SUM(E26:CT26) -> 1 | K26: 1
C27: MAGENTO | D27: =SUM(E27:CT27) -> 35 | K27: 5 | L27: 5 | M27: 5 | Q27: 5 | R27: 5 | S27: 5 | T27: 5
A28: 0 | B28: Project - Malezja Faza 1A | C28: ALF | D28: =SUM(E28:CT28) -> 8.5 | K28: 1 | L28: 1 | M28: 0.5 | O28: 1 | P28: 3 | Q28: 2
C29: WAREX | D29: =SUM(E29:CT29) -> 1 | M29: 0.5 | N29: 0.5
C30: OPTIMUS | D30: =SUM(E30:CT30) -> 8 | P30: 0.5 | Q30: 0.5 | R30: 5 | S30: 2
C31: MASH | D31: =SUM(E31:CT31) -> 20 | H31: 1 | I31: 2 | J31: 3 | K31: 3 | L31: 2 | M31: 3 | N31: 1 | P31: 0.5 | Q31: 1 | R31: 0.5 | S31: 1 | T31: 2
C32: MAGENTO | D32: =SUM(E32:CT32) -> 92 | J32: 6 | K32: 15 | L32: 10 | M32: 5 | N32: 15 | O32: 15 | P32: 10 | Q32: 5 | R32: 4 | S32: 4 | T32: 3
A33: 0 | B33: MM Open Days: Faza1 - 22/05 | C33: ALF | D33: =SUM(E33:CT33) -> 25 | K33: 5 | L33: 5 | M33: 5 | N33: 5 | O33: 5
C34: WAREX | D34: =SUM(E34:CT34) -> 2 | N34: 2
C35: OPTIMUS | D35: =SUM(E35:CT35) -> 0
C36: MASH | D36: =SUM(E36:CT36) -> 15 | K36: 3 | L36: 5 | M36: 3 | N36: 2 | O36: 2
C37: MAGENTO | D37: =SUM(E37:CT37) -> 10 | N37: 5 | O37: 5
A38: 0 | B38: MM Open Days: Faza2 - 03/06 | C38: ALF | D38: =SUM(E38:CT38) -> 0
C39: WAREX | D39: =SUM(E39:CT39) -> 0
C40: OPTIMUS | D40: =SUM(E40:CT40) -> 0
C41: MASH | D41: =SUM(E41:CT41) -> 0
C42: MAGENTO | D42: =SUM(E42:CT42) -> 4 | P42: 4
A43: 0 | B43: Open Days tMobile - 23/06 + Genetal Open Days Tasks | C43: ALF | D43: =SUM(E43:CT43) -> 0
C44: WAREX | D44: =SUM(E44:CT44) -> 0
C45: OPTIMUS | D45: =SUM(E45:CT45) -> 0
C46: MASH | D46: =SUM(E46:CT46) -> 0
C47: MAGENTO | D47: =SUM(E47:CT47) -> 12 | Q47: 4 | R47: 3 | S47: 5
A48: 0 | B48: PLAY New Assortment Groups | C48: ALF | D48: =SUM(E48:CT48) -> 0
C49: WAREX | D49: =SUM(E49:CT49) -> 44 | H49: 3 | I49: 3 | J49: 3 | K49: 8 | L49: 3 | M49: 12 | N49: 8 | O49: 2 | Q49: 1 | R49: 1
C50: OPTIMUS | D50: =SUM(E50:CT50) -> 29 | P50: 5 | Q50: 10 | R50: 10 | S50: 3 | T50: 1
C51: MASH | D51: =SUM(E51:CT51) -> 0
C52: MAGENTO | D52: =SUM(E52:CT52) -> 0
A53: 0 | B53: Inicjatywa PLK karta usług (B2B Enterprise + Frontend) | C53: ALF | D53: =SUM(E53:CT53) -> 0
C54: WAREX | D54: =SUM(E54:CT54) -> 94 | H54: 5 | I54: 5 | J54: 5 | K54: 6 | L54: 3 | M54: 8 | N54: 8 | O54: 9 | P54: 9 | Q54: 4 | R54: 4 | S54: 8 | T54: 4 | U54: 4 | V54: 2 | W54: 2 | X54: 2 | Y54: 2 | Z54: 2 | AA54: 1 | AB54: 1
C55: OPTIMUS | D55: =SUM(E55:CT55) -> 25 | U55: 5 | V55: 7 | W55: 5 | X55: 5 | Y55: 3
C56: MASH | D56: =SUM(E56:CT56) -> 0
C57: MAGENTO | D57: =SUM(E57:CT57) -> 0
A58: 0 | B58: JET (zmiana leasingu na najem do 27 maja) | C58: ALF | D58: =SUM(E58:CT58) -> 10 | N58: 2 | O58: 5 | Q58: 3
C59: WAREX | D59: =SUM(E59:CT59) -> 0
C60: OPTIMUS | D60: =SUM(E60:CT60) -> 0
C61: MASH | D61: =SUM(E61:CT61) -> 0
C62: MAGENTO | D62: =SUM(E62:CT62) -> 0
A63: 0 | B63: ALLPSI | C63: ALF | D63: =SUM(E63:CT63) -> 28 | N63: 2 | O63: 5 | P63: 5 | Q63: 6 | R63: 5 | S63: 4 | T63: 1
C64: WAREX | D64: =SUM(E64:CT64) -> 0
C65: OPTIMUS | D65: =SUM(E65:CT65) -> 0
C66: MASH | D66: =SUM(E66:CT66) -> 10 | M66: 1 | N66: 3 | O66: 1 | P66: 1 | Q66: 1 | R66: 1 | S66: 1 | T66: 1
C67: MAGENTO | D67: =SUM(E67:CT67) -> 0
A68: 0 | B68: PHOX | C68: ALF | D68: =SUM(E68:CT68) -> 30 | U68: 5 | V68: 5 | W68: 5 | X68: 5 | Y68: 5 | Z68: 5
C69: WAREX | D69: =SUM(E69:CT69) -> 25 | W69: 5 | X69: 5 | Y69: 5 | Z69: 5 | AA69: 5
C70: OPTIMUS | D70: =SUM(E70:CT70) -> 20 | Y70: 5 | Z70: 5 | AA70: 5 | AB70: 5
C71: MASH | D71: =SUM(E71:CT71) -> 5 | U71: 1 | V71: 1 | W71: 1 | X71: 1 | Y71: 1
C72: MAGENTO | D72: =SUM(E72:CT72) -> 0
A73: 0 | B73: (BIK) Antyfraud CFD | C73: ALF | D73: =SUM(E73:CT73) -> 0
C74: WAREX | D74: =SUM(E74:CT74) -> 0
C75: OPTIMUS | D75: =SUM(E75:CT75) -> 0
C76: MASH | D76: =SUM(E76:CT76) -> 22.5 | M76: 1 | N76: 1 | O76: 1 | P76: 0.5 | Q76: 1 | R76: 1 | S76: 3 | T76: 3 | U76: 2 | V76: 2 | W76: 2 | X76: 2 | Y76: 1 | Z76: 1 | AA76: 1
C77: MAGENTO | D77: =SUM(E77:CT77) -> 39 | R77: 2 | S77: 5 | T77: 3 | U77: 3 | V77: 3 | W77: 3 | X77: 5 | Y77: 5 | Z77: 5 | AA77: 5
A78: 0 | B78: Inicjatywa API PLAY | C78: ALF | D78: =SUM(E78:CT78) -> 0
C79: WAREX | D79: =SUM(E79:CT79) -> 0
C80: OPTIMUS | D80: =SUM(E80:CT80) -> 3 | T80: 3
C81: MASH | D81: =SUM(E81:CT81) -> 0
C82: MAGENTO | D82: =SUM(E82:CT82) -> 0
A83: 1 | B83: Rebranding | C83: ALF | D83: =SUM(E83:CT83) -> 91 | Q83: 6 | R83: 10 | S83: 8 | T83: 8 | U83: 8 | V83: 8 | W83: 5 | X83: 5 | Y83: 5 | Z83: 5 | AA83: 5 | AB83: 5 | AC83: 5 | AD83: 5 | AE83: 3
C84: WAREX | D84: =SUM(E84:CT84) -> 62 | Q84: 5 | R84: 3 | S84: 5 | T84: 2 | U84: 2 | V84: 2 | W84: 2 | X84: 2 | Y84: 2 | Z84: 5 | AA84: 5 | AB84: 5 | AC84: 5 | AD84: 5 | AE84: 5 | AF84: 5 | AG84: 2
C85: OPTIMUS | D85: =SUM(E85:CT85) -> 266 | M85: 2 | N85: 6 | O85: 10 | P85: 15 | Q85: 15 | R85: 15 | S85: 5 | T85: 5 | U85: 10 | V85: 10 | W85: 10 | X85: 10 | Y85: 10 | Z85: 10 | AA85: 10 | AB85: 10 | AC85: 10 | AD85: 10 | AE85: 10 | AF85: 10 | AG85: 10 | AH85: 10 | AI85: 10 | AJ85: 10 | AK85: 10 | AL85: 10 | AM85: 10 | AN85: 3
C86: MASH | D86: =SUM(E86:CT86) -> 3.5 | P86: 1 | Q86: 1 | R86: 1 | T86: 0.5
C87: MAGENTO | D87: =SUM(E87:CT87) -> 21 | P87: 1 | U87: 5 | V87: 5 | W87: 5 | X87: 5
A88: 2 | B88: Project - HT Rental | C88: ALF | D88: =SUM(E88:CT88) -> 40 | Q88: 5 | R88: 5 | T88: 5 | U88: 5 | V88: 7 | W88: 8 | X88: 5
C89: WAREX | D89: =SUM(E89:CT89) -> 20 | P89: 1 | S89: 2 | T89: 1 | U89: 4 | V89: 3 | W89: 5 | X89: 3 | Y89: 1
C90: OPTIMUS | D90: =SUM(E90:CT90) -> 30 | V90: 10 | W90: 8 | X90: 10 | Y90: 2
C91: MASH | D91: =SUM(E91:CT91) -> 0
C92: MAGENTO | D92: =SUM(E92:CT92) -> 0
A93: 3 | B93: Project - iStyle HU | C93: ALF | D93: =SUM(E93:CT93) -> 37 | N93: 5 | O93: 10 | P93: 11 | Q93: 5 | R93: 4 | S93: 2
C94: WAREX | D94: =SUM(E94:CT94) -> 17 | O94: 2 | P94: 3 | Q94: 6 | R94: 4 | S94: 2
C95: OPTIMUS | D95: =SUM(E95:CT95) -> 24 | S95: 1 | T95: 9 | U95: 5 | V95: 5 | W95: 2 | X95: 2
C96: MASH | D96: 8 | N96: 2 | O96: 4 | P96: 1 | Q96: 1 | R96: 0.5
C97: MAGENTO | D97: =SUM(E97:CT97) -> 0
A98: 4 | B98: Orange B2B (insurance exchange) | C98: ALF
C99: WAREX
C100: OPTIMUS
...

Sheet WORKLOAD_PEOPLE
A1: NAME | B1: SURNAME | C1: FULL NAME | D1: SKILLSET | E1: TEAM | F1: PROJECT | G1: TOTAL PROJECT MD | H1: 45362 | I1: 45363 | J1: 45364 | K1: 45365 | L1: 45366 | M1: 45367 | N1: 45368 | O1: 45369 | P1: 45370 | Q1: 45371 | R1: 45372 | S1: 45373 | T1: 45374 | U1: 45375 | V1: 45376 | W1: 45377 | X1: 45378 | Y1: 45379 | Z1: 45380 | AA1: 45381 | AB1: 45382 | AC1: 45383 | AD1: 45384 | AE1: 45385 | AF1: 45386 | AG1: 45387 | AH1: 45388 | AI1: 45389 | AJ1: 45390 | AK1: 45391 | AL1: 45392 | AM1: 45393 | AN1: 45394 | AO1: 45395 | AP1: 45396 | AQ1: 45397 | AR1: 45398 | AS1: 45399 | AT1: 45400 | AU1: 45401 | AV1: 45402 | AW1: 45403 | AX1: 45404 | AY1: 45405 | AZ1: 45406 | BA1: 45407 | BB1: 45408 | BC1: 45409 | BD1: 45410 | BE1: 45411 | BF1: 45412 | BG1: 45413 | BH1: 45414 | BI1: 45415 | BJ1: 45416 | BK1: 45417 | BL1: 45418 | BM1: 45419 | BN1: 45420 | BO1: 45421 | BP1: 45422 | BQ1: 45423 | BR1: 45424 | BS1: 45425 | BT1: 45426 | BU1: 45427 | BV1: 45428 | BW1: 45429 | BX1: 45430 | BY1: 45431 | BZ1: 45432 | CA1: 45433 | CB1: 45434 | CC1: 45435 | CD1: 45436 | CE1: 45437 | CF1: 45438 | CG1: 45439 | CH1: 45440 | CI1: 45441 | CJ1: 45442 | CK1: 45443 | CL1: 45444 | CM1: 45445 | CN1: 45446 | CO1: 45447 | CP1: 45448 | CQ1: 45449 | CR1: 45450 | CS1: 45451 | CT1: 45452 | CU1: 45453 | CV1: 45454 | CW1: 45455 | CX1: 45456 | CY1: 45457 | CZ1: 45458 | DA1: 45459 | DB1: 45460 | DC1: 45461 | DD1: 45462 | DE1: 45463 | DF1: 45464 | DG1: 45465 | DH1: 45466 | DI1: 45467 | DJ1: 45468 | DK1: 45469 | DL1: 45470 | DM1: 45471 | DN1: 45472 | DO1: 45473 | DP1: 45474 | DQ1: 45475 | DR1: 45476 | DS1: 45477 | DT1: 45478 | DU1: 45479 | DV1: 45480 | DW1: 45481 | DX1: 45482 | DY1: 45483 | DZ1: 45484 | EA1: 45485 | EB1: 45486 | EC1: 45487 | ED1: 45488 | EE1: 45489 | EF1: 45490 | EG1: 45491 | EH1: 45492 | EI1: 45493 | EJ1: 45494 | EK1: 45495 | EL1: 45496 | EM1: 45497 | EN1: 45498 | EO1: 45499 | EP1: 45500 | EQ1: 45501 | ER1: 45502 | ES1: 45503 | ET1: 45504 | EU1: 45505 | EV1: 45506 | EW1: 45507 | EX1: 45508 | EY1: 45509 | EZ1: 45510 | FA1: 45511 | FB1: 45512 | FC1: 45513 | FD1: 45514 | FE1: 45515 | FF1: 45516 | FG1: 45517 | FH1: 45518 | FI1: 45519 | FJ1: 45520 | FK1: 45521 | FL1: 45522 | FM1: 45523 | FN1: 45524 | FO1: 45525 | FP1: 45526 | FQ1: 45527 | FR1: 45528 | FS1: 45529 | FT1: 45530 | FU1: 45531 | FV1: 45532 | FW1: 45533 | FX1: 45534 | FY1: 45535 | FZ1: 45536 | GA1: 45537 | GB1: 45538 | GC1: 45539 | GD1: 45540 | GE1: 45541 | GF1: 45542 | GG1: 45543 | GH1: 45544 | GI1: 45545 | GJ1: 45546 | GK1: 45547 | GL1: 45548 | GM1: 45549 | GN1: 45550 | GO1: 45551 | GP1: 45552 | GQ1: 45553 | GR1: 45554 | GS1: 45555 | GT1: 45556 | GU1: 45557 | GV1: 45558 | GW1: 45559 | GX1: 45560 | GY1: 45561 | GZ1: 45562 | HA1: 45563 | HB1: 45564 | HC1: 45565 | HD1: 45566 | HE1: 45567 | HF1: 45568 | HG1: 45569 | HH1: 45570 | HI1: 45571 | HJ1: 45572 | HK1: 45573 | HL1: 45574 | HM1: 45575 | HN1: 45576 | HO1: 45577 | HP1: 45578 | HQ1: 45579 | HR1: 45580 | HS1: 45581 | HT1: 45582 | HU1: 45583 | HV1: 45584 | HW1: 45585 | HX1: 45586 | HY1: 45587 | HZ1: 45588 | IA1: 45589 | IB1: 45590 | IC1: 45591 | ID1: 45592 | IE1: 45593 | IF1: 45594 | IG1: 45595 | IH1: 45596 | II1: 45597 | IJ1: 45598 | IK1: 45599 | IL1: 45600 | IM1: 45601 | IN1: 45602 | IO1: 45603 | IP1: 45604 | IQ1: 45605 | IR1: 45606 | IS1: 45607 | IT1: 45608 | IU1: 45609 | IV1: 45610 | IW1: 45611 | IX1: 45612 | IY1: 45613 | IZ1: 45614 | JA1: 45615 | JB1: 45616 | JC1: 45617 | JD1: 45618 | JE1: 45619 | JF1: 45620 | JG1: 45621 | JH1: 45622 | JI1: 45623 | JJ1: 45624 | JK1: 45625 | JL1: 45626 | JM1: 45627 | JN1: 45628 | JO1: 45629 | JP1: 45630 | JQ1: 45631 | JR1: 45632 | JS1: 45633 | JT1: 45634 | JU1: 45635 | JV1: 45636 | JW1: 45637 | JX1: 45638 | JY1: 45639 | JZ1: 45640 | KA1: 45641 | KB1: 45642 | KC1: 45643 | KD1: 45644 | KE1: 45645 | KF1: 45646 | KG1: 45647 | KH1: 45648 | KI1: 45649 | KJ1: 45650 | KK1: 45651 | KL1: 45652 | KM1: 45653 | KN1: 45654 | KO1: 45655 | KP1: 45656 | KQ1: 45657 | KR1: 45658 | KS1: 45659 | KT1: 45660 | KU1: 45661 | KV1: 45662 | KW1: 45663 | KX1: 45664 | KY1: 45665 | KZ1: 45666 | LA1: 45667 | LB1: 45668
A2: Andrzej | B2: Dyśko | C2: =A2&" "&B2 -> Andrzej Dyśko | D2: =VLOOKUP(C2,CAPACITY!$C$12:$E$69,2,0) -> #N/A | E2: =VLOOKUP(C2,CAPACITY!$C$12:$E$69,3,0) -> #N/A | F2: SUMA | G2: =SUM(H2:L2) -> 0.65 | H2: =SUM(H3:H5) -> 0.35 | I2: =SUM(I3:I5) -> 0.1 | J2: =SUM(J3:J5) -> 0.1 | K2: =SUM(K3:K5) -> 0.1 | L2: =SUM(L3:L5) -> 0 | M2: =SUM(M3:M5) -> 0 | N2: =SUM(N3:N5) -> 0 | O2: =SUM(O3:O5) -> 0 | ... LB2: =SUM(LB3:LB5) -> 0
A3: Andrzej | B3: Dyśko | C3: =A3&" "&B3 -> Andrzej Dyśko | D3: =VLOOKUP(C3,CAPACITY!$C$12:$E$69,2,0) -> #N/A | E3: =VLOOKUP(C3,CAPACITY!$C$12:$E$69,3,0) -> #N/A | F3: Malezja | G3: =SUM(H3:L3) -> 0.35 | H3: 0.05 | I3: 0.1 | J3: 0.1 | K3: 0.1 | L3: 0 | M3: 0 | N3: 0 | O3: 0 | P3: 0 | Q3: 0 | R3: 0 | S3: 0 | T3: 0 | U3: 0 | V3: 0 | W3: 0 | X3: 0 | Y3: 0 | Z3: 0 | AA3: 0 | AB3: 0 | AC3: 0 | AD3: 0 | AE3: 0 | AF3: 0 | AG3: 0 | AH3: 0 | AI3: 0 | AJ3: 0 | AK3: 0 | AL3: 0 | AM3: 0 | AN3: 0 | AO3: 0 | AP3: 0 | AQ3: 0 | AR3: 0 | AS3: 0 | AT3: 0 | AU3: 0 | AV3: 0 | AW3: 0 | AX3: 0 | AY3: 0 | AZ3: 0 | BA3: 0 | BB3: 0 | BC3: 0 | BD3: 0 | BE3: 0 | BF3: 0 | BG3: 0 | BH3: 0 | BI3: 0 | BJ3: 0 | BK3: 0 | BL3: 0 | BM3: 0 | BN3: 0 | BO3: 0 | BP3: 0 | BQ3: 0 | BR3: 0 | BS3: 0 | BT3: 0 | BU3: 0 | BV3: 0 | BW3: 0 | BX3: =SUM(BX4:BX6) -> 0 | BY3: =SUM(BY4:BY6) -> 0 | BZ3: 0 | CA3: 0 | CB3: 0 | CC3: 0 | CD3: 0 | CE3: 0 | CF3: 0 | CG3: 0 | CH3: 0 | CI3: 0 | CJ3: 0 | CK3: 0 | CL3: 0 | CM3: 0 | CN3: 0 | CO3: 0 | CP3: 0 | CQ3: 0 | CR3: 0 | CS3: 0 | CT3: 0 | CU3: 0 | CV3: 0 | CW3: 0 | CX3: 0 | CY3: 0 | CZ3: 0 | DA3: 0 | DB3: 0 | DC3: 0 | DD3: 0 | DE3: 0 | DF3: 0 | DG3: 0 | DH3: 0 | DI3: 0 | DJ3: 0 | DK3: 0 | DL3: 0 | DM3: 0 | DN3: 0 | DO3: 0 | DP3: 0 | DQ3: 0 | DR3: 0 | DS3: 0 | DT3: 0 | DU3: 0 | DV3: 0 | DW3: 0 | DX3: 0 | DY3: 0 | DZ3: 0 | EA3: 0 | EB3: 0 | EC3: 0 | ED3: 0 | EE3: 0 | EF3: 0 | EG3: 0 | EH3: 0 | EI3: 0 | EJ3: 0 | EK3: 0 | EL3: 0 | EM3: 0 | EN3: 0 | EO3: 0 | EP3: 0 | EQ3: 0 | ER3: 0 | ES3: 0 | ET3: 0 | EU3: 0 | EV3: 0 | EW3: 0 | EX3: 0 | EY3: 0 | EZ3: 0 | FA3: 0 | FB3: 0 | FC3: 0 | FD3: 0 | FE3: 0 | FF3: 0 | FG3: 0 | FH3: 0 | FI3: 0 | FJ3: 0 | FK3: 0 | FL3: 0 | FM3: 0 | FN3: 0 | FO3: 0 | FP3: 0 | FQ3: 0 | FR3: 0 | FS3: 0 | FT3: 0 | FU3: 0 | FV3: 0 | FW3: 0 | FX3: 0 | FY3: 0 | FZ3: 0 | GA3: 0 | GB3: 0 | GC3: 0 | GD3: 0 | GE3: 0 | GF3: 0 | GG3: 0 | GH3: 0 | GI3: 0 | GJ3: 0 | GK3: 0 | GL3: 0 | GM3: 0 | GN3: 0 | GO3: 0 | GP3: 0 | GQ3: 0 | GR3: 0 | GS3: 0 | GT3: 0 | GU3: 0 | GV3: 0 | GW3: 0 | GX3: 0 | GY3: 0 | GZ3: 0 | HA3: 0 | HB3: 0 | HC3: 0 | HD3: 0 | HE3: 0 | HF3: 0 | HG3: 0 | HH3: 0 | HI3: 0 | HJ3: 0 | HK3: 0 | HL3: 0 | HM3: 0 | HN3: 0 | HO3: 0 | HP3: 0 | HQ3: 0 | HR3: 0 | HS3: 0 | HT3: 0 | HU3: 0 | HV3: 0 | HW3: 0 | HX3: 0 | HY3: 0 | HZ3: 0 | IA3: 0 | IB3: 0 | IC3: 0 | ID3: 0 | IE3: 0 | IF3: 0 | IG3: 0 | IH3: 0 | II3: 0 | IJ3: 0 | IK3: 0 | IL3: 0 | IM3: 0 | IN3: 0 | IO3: 0 | IP3: 0 | IQ3: 0 | IR3: 0 | IS3: 0 | IT3: 0 | IU3: 0 | IV3: 0 | IW3: 0 | IX3: 0 | IY3: 0 | IZ3: 0 | JA3: 0 | JB3: 0 | JC3: 0 | JD3: 0 | JE3: 0 | JF3: 0 | JG3: 0 | JH3: 0 | JI3: 0 | JJ3: 0 | JK3: 0 | JL3: 0 | JM3: 0 | JN3: 0 | JO3: 0 | JP3: 0 | JQ3: 0 | JR3: 0 | JS3: 0 | JT3: 0 | JU3: 0 | JV3: 0 | JW3: 0 | JX3: 0 | JY3: 0 | JZ3: 0 | KA3: 0 | KB3: 0 | KC3: 0 | KD3: 0 | KE3: 0 | KF3: 0 | KG3: 0 | KH3: 0 | KI3: 0 | KJ3: 0 | KK3: 0 | KL3: 0 | KM3: 0 | KN3: 0 | KO3: 0 | KP3: 0 | KQ3: 0 | KR3: 0 | KS3: 0 | KT3: 0 | KU3: 0 | KV3: 0 | KW3: 0 | KX3: 0 | KY3: 0 | KZ3: 0 | LA3: 0 | LB3: 0
A4: Andrzej | B4: Dyśko | C4: =A4&" "&B4 -> Andrzej Dyśko | D4: =VLOOKUP(C4,CAPACITY!$C$12:$E$69,2,0) -> #N/A | E4: =VLOOKUP(C4,CAPACITY!$C$12:$E$69,3,0) -> #N/A | F4: KYC | G4: =SUM(H4:L4) -> 0.1 | H4: 0.1 | I4: 0 | J4: 0 | K4: 0 | L4: 0 | M4: 0 | N4: 0 | O4: 0 | P4: 0 | Q4: 0 | R4: 0 | S4: 0 | T4: 0 | U4: 0 | V4: 0 | W4: 0 | X4: 0 | Y4: 0 | Z4: 0 | AA4: 0 | AB4: 0 | AC4: 0 | AD4: 0 | AE4: 0 | AF4: 0 | AG4: 0 | AH4: 0 | AI4: 0 | AJ4: 0 | AK4: 0 | AL4: 0 | AM4: 0 | AN4: 0 | AO4: 0 | AP4: 0 | AQ4: 0 | AR4: 0 | AS4: 0 | AT4: 0 | AU4: 0 | AV4: 0 | AW4: 0 | AX4: 0 | AY4: 0 | AZ4: 0 | BA4: 0 | BB4: 0 | BC4: 0 | BD4: 0 | BE4: 0 | BF4: 0 | BG4: 0 | BH4: 0 | BI4: 0 | BJ4: 0 | BK4: 0 | BL4: 0 | BM4: 0 | BN4: 0 | BO4: 0 | BP4: 0 | BQ4: 0 | BR4: 0 | BS4: 0 | BT4: 0 | BU4: 0 | BV4: 0 | BW4: 0 | BX4: =SUM(BX5:BX7) -> 0 | BY4: =SUM(BY5:BY7) -> 0 | BZ4: 0 | CA4: 0 | CB4: 0 | CC4: 0 | CD4: 0 | CE4: 0 | CF4: 0 | CG4: 0 | CH4: 0 | CI4: 0 | CJ4: 0 | CK4: 0 | CL4: 0 | CM4: 0 | CN4: 0 | CO4: 0 | CP4: 0 | CQ4: 0 | CR4: 0 | CS4: 0 | CT4: 0 | CU4: 0 | CV4: 0 | CW4: 0 | CX4: 0 | CY4: 0 | CZ4: 0 | DA4: 0 | DB4: 0 | DC4: 0 | DD4: 0 | DE4: 0 | DF4: 0 | DG4: 0 | DH4: 0 | DI4: 0 | DJ4: 0 | DK4: 0 | DL4: 0 | DM4: 0 | DN4: 0 | DO4: 0 | DP4: 0 | DQ4: 0 | DR4: 0 | DS4: 0 | DT4: 0 | DU4: 0 | DV4: 0 | DW4: 0 | DX4: 0 | DY4: 0 | DZ4: 0 | EA4: 0 | EB4: 0 | EC4: 0 | ED4: 0 | EE4: 0 | EF4: 0 | EG4: 0 | EH4: 0 | EI4: 0 | EJ4: 0 | EK4: 0 | EL4: 0 | EM4: 0 | EN4: 0 | EO4: 0 | EP4: 0 | EQ4: 0 | ER4: 0 | ES4: 0 | ET4: 0 | EU4: 0 | EV4: 0 | EW4: 0 | EX4: 0 | EY4: 0 | EZ4: 0 | FA4: 0 | FB4: 0 | FC4: 0 | FD4: 0 | FE4: 0 | FF4: 0 | FG4: 0 | FH4: 0 | FI4: 0 | FJ4: 0 | FK4: 0 | FL4: 0 | FM4: 0 | FN4: 0 | FO4: 0 | FP4: 0 | FQ4: 0 | FR4: 0 | FS4: 0 | FT4: 0 | FU4: 0 | FV4: 0 | FW4: 0 | FX4: 0 | FY4: 0 | FZ4: 0 | GA4: 0 | GB4: 0 | GC4: 0 | GD4: 0 | GE4: 0 | GF4: 0 | GG4: 0 | GH4: 0 | GI4: 0 | GJ4: 0 | GK4: 0 | GL4: 0 | GM4: 0 | GN4: 0 | GO4: 0 | GP4: 0 | GQ4: 0 | GR4: 0 | GS4: 0 | GT4: 0 | GU4: 0 | GV4: 0 | GW4: 0 | GX4: 0 | GY4: 0 | GZ4: 0 | HA4: 0 | HB4: 0 | HC4: 0 | HD4: 0 | HE4: 0 | HF4: 0 | HG4: 0 | HH4: 0 | HI4: 0 | HJ4: 0 | HK4: 0 | HL4: 0 | HM4: 0 | HN4: 0 | HO4: 0 | HP4: 0 | HQ4: 0 | HR4: 0 | HS4: 0 | HT4: 0 | HU4: 0 | HV4: 0 | HW4: 0 | HX4: 0 | HY4: 0 | HZ4: 0 | IA4: 0 | IB4: 0 | IC4: 0 | ID4: 0 | IE4: 0 | IF4: 0 | IG4: 0 | IH4: 0 | II4: 0 | IJ4: 0 | IK4: 0 | IL4: 0 | IM4: 0 | IN4: 0 | IO4: 0 | IP4: 0 | IQ4: 0 | IR4: 0 | IS4: 0 | IT4: 0 | IU4: 0 | IV4: 0 | IW4: 0 | IX4: 0 | IY4: 0 | IZ4: 0 | JA4: 0 | JB4: 0 | JC4: 0 | JD4: 0 | JE4: 0 | JF4: 0 | JG4: 0 | JH4: 0 | JI4: 0 | JJ4: 0 | JK4: 0 | JL4: 0 | JM4: 0 | JN4: 0 | JO4: 0 | JP4: 0 | JQ4: 0 | JR4: 0 | JS4: 0 | JT4: 0 | JU4: 0 | JV4: 0 | JW4: 0 | JX4: 0 | JY4: 0 | JZ4: 0 | KA4: 0 | KB4: 0 | KC4: 0 | KD4: 0 | KE4: 0 | KF4: 0 | KG4: 0 | KH4: 0 | KI4: 0 | KJ4: 0 | KK4: 0 | KL4: 0 | KM4: 0 | KN4: 0 | KO4: 0 | KP4: 0 | KQ4: 0 | KR4: 0 | KS4: 0 | KT4: 0 | KU4: 0 | KV4: 0 | KW4: 0 | KX4: 0 | KY4: 0 | KZ4: 0 | LA4: 0 | LB4: 0
A5: Andrzej | B5: Dyśko | C5: =A5&" "&B5 -> Andrzej Dyśko | D5: =VLOOKUP(C5,CAPACITY!$C$12:$E$69,2,0) -> #N/A | E5: =VLOOKUP(C5,CAPACITY!$C$12:$E$69,3,0) -> #N/A | F5: C | G5: =SUM(H5:L5) -> 0.2 | H5: 0.2 | I5: 0 | J5: 0 | K5: 0 | L5: 0 | M5: 0 | N5: 0 | O5: 0 | P5: 0 | Q5: 0 | R5: 0 | S5: 0 | T5: 0 | U5: 0 | V5: 0 | W5: 0 | X5: 0 | Y5: 0 | Z5: 0 | AA5: 0 | AB5: 0 | AC5: 0 | AD5: 0 | AE5: 0 | AF5: 0 | AG5: 0 | AH5: 0 | AI5: 0 | AJ5: 0 | AK5: 0 | AL5: 0 | AM5: 0 | AN5: 0 | AO5: 0 | AP5: 0 | AQ5: 0 | AR5: 0 | AS5: 0 | AT5: 0 | AU5: 0 | AV5: 0 | AW5: 0 | AX5: 0 | AY5: 0 | AZ5: 0 | BA5: 0 | BB5: 0 | BC5: 0 | BD5: 0 | BE5: 0 | BF5: 0 | BG5: 0 | BH5: 0 | BI5: 0 | BJ5: 0 | BK5: 0 | BL5: 0 | BM5: 0 | BN5: 0 | BO5: 0 | BP5: 0 | BQ5: 0 | BR5: 0 | BS5: 0 | BT5: 0 | BU5: 0 | BV5: 0 | BW5: 0 | BX5: =SUM(BX6:BX8) -> 0 | BY5: =SUM(BY6:BY8) -> 0 | BZ5: 0 | CA5: 0 | CB5: 0 | CC5: 0 | CD5: 0 | CE5: 0 | CF5: 0 | CG5: 0 | CH5: 0 | CI5: 0 | CJ5: 0 | CK5: 0 | CL5: 0 | CM5: 0 | CN5: 0 | CO5: 0 | CP5: 0 | CQ5: 0 | CR5: 0 | CS5: 0 | CT5: 0 | CU5: 0 | CV5: 0 | CW5: 0 | CX5: 0 | CY5: 0 | CZ5: 0 | DA5: 0 | DB5: 0 | DC5: 0 | DD5: 0 | DE5: 0 | DF5: 0 | DG5: 0 | DH5: 0 | DI5: 0 | DJ5: 0 | DK5: 0 | DL5: 0 | DM5: 0 | DN5: 0 | DO5: 0 | DP5: 0 | DQ5: 0 | DR5: 0 | DS5: 0 | DT5: 0 | DU5: 0 | DV5: 0 | DW5: 0 | DX5: 0 | DY5: 0 | DZ5: 0 | EA5: 0 | EB5: 0 | EC5: 0 | ED5: 0 | EE5: 0 | EF5: 0 | EG5: 0 | EH5: 0 | EI5: 0 | EJ5: 0 | EK5: 0 | EL5: 0 | EM5: 0 | EN5: 0 | EO5: 0 | EP5: 0 | EQ5: 0 | ER5: 0 | ES5: 0 | ET5: 0 | EU5: 0 | EV5: 0 | EW5: 0 | EX5: 0 | EY5: 0 | EZ5: 0 | FA5: 0 | FB5: 0 | FC5: 0 | FD5: 0 | FE5: 0 | FF5: 0 | FG5: 0 | FH5: 0 | FI5: 0 | FJ5: 0 | FK5: 0 | FL5: 0 | FM5: 0 | FN5: 0 | FO5: 0 | FP5: 0 | FQ5: 0 | FR5: 0 | FS5: 0 | FT5: 0 | FU5: 0 | FV5: 0 | FW5: 0 | FX5: 0 | FY5: 0 | FZ5: 0 | GA5: 0 | GB5: 0 | GC5: 0 | GD5: 0 | GE5: 0 | GF5: 0 | GG5: 0 | GH5: 0 | GI5: 0 | GJ5: 0 | GK5: 0 | GL5: 0 | GM5: 0 | GN5: 0 | GO5: 0 | GP5: 0 | GQ5: 0 | GR5: 0 | GS5: 0 | GT5: 0 | GU5: 0 | GV5: 0 | GW5: 0 | GX5: 0 | GY5: 0 | GZ5: 0 | HA5: 0 | HB5: 0 | HC5: 0 | HD5: 0 | HE5: 0 | HF5: 0 | HG5: 0 | HH5: 0 | HI5: 0 | HJ5: 0 | HK5: 0 | HL5: 0 | HM5: 0 | HN5: 0 | HO5: 0 | HP5: 0 | HQ5: 0 | HR5: 0 | HS5: 0 | HT5: 0 | HU5: 0 | HV5: 0 | HW5: 0 | HX5: 0 | HY5: 0 | HZ5: 0 | IA5: 0 | IB5: 0 | IC5: 0 | ID5: 0 | IE5: 0 | IF5: 0 | IG5: 0 | IH5: 0 | II5: 0 | IJ5: 0 | IK5: 0 | IL5: 0 | IM5: 0 | IN5: 0 | IO5: 0 | IP5: 0 | IQ5: 0 | IR5: 0 | IS5: 0 | IT5: 0 | IU5: 0 | IV5: 0 | IW5: 0 | IX5: 0 | IY5: 0 | IZ5: 0 | JA5: 0 | JB5: 0 | JC5: 0 | JD5: 0 | JE5: 0 | JF5: 0 | JG5: 0 | JH5: 0 | JI5: 0 | JJ5: 0 | JK5: 0 | JL5: 0 | JM5: 0 | JN5: 0 | JO5: 0 | JP5: 0 | JQ5: 0 | JR5: 0 | JS5: 0 | JT5: 0 | JU5: 0 | JV5: 0 | JW5: 0 | JX5: 0 | JY5: 0 | JZ5: 0 | KA5: 0 | KB5: 0 | KC5: 0 | KD5: 0 | KE5: 0 | KF5: 0 | KG5: 0 | KH5: 0 | KI5: 0 | KJ5: 0 | KK5: 0 | KL5: 0 | KM5: 0 | KN5: 0 | KO5: 0 | KP5: 0 | KQ5: 0 | KR5: 0 | KS5: 0 | KT5: 0 | KU5: 0 | KV5: 0 | KW5: 0 | KX5: 0 | KY5: 0 | KZ5: 0 | LA5: 0 | LB5: 0
A6: Mikołaj | B6: Banaszkiewicz | C6: =A6&" "&B6 -> Mikołaj Banaszkiewicz | D6: =VLOOKUP(C6,CAPACITY!$C$12:$E$69,2,0) -> BE Developer | E6: =VLOOKUP(C6,CAPACITY!$C$12:$E$69,3,0) -> ALF | BI6: =SUM(BI7:BI9) -> 0 | BJ6: =SUM(BJ7:BJ9) -> 0 | BK6: =SUM(BK7:BK9) -> 0 | BL6: =SUM(BL7:BL9) -> 0 | BM6: =SUM(BM7:BM9) -> 0 | BN6: =SUM(BN7:BN9) -> 0 | BO6: =SUM(BO7:BO9) -> 0 | BP6: =SUM(BP7:BP9) -> 0 | ... CF6: =SUM(CF7:CF9) -> 0
A7: Mikołaj | B7: Banaszkiewicz | C7: =A7&" "&B7 -> Mikołaj Banaszkiewicz | D7: =VLOOKUP(C7,CAPACITY!$C$12:$E$69,2,0) -> BE Developer | E7: =VLOOKUP(C7,CAPACITY!$C$12:$E$69,3,0) -> ALF | BI7: 0 | BJ7: 0 | BK7: 0 | BL7: 0 | BM7: 0 | BN7: 0 | BO7: 0 | BP7: 0 | BQ7: 0 | BR7: 0 | BS7: 0 | BT7: 0 | BU7: 0 | BV7: 0 | BW7: 0 | BX7: =SUM(BX8:BX10) -> 0 | BY7: =SUM(BY8:BY10) -> 0 | BZ7: 0 | CA7: 0 | CB7: 0 | CC7: 0 | CD7: 0 | CE7: 0 | CF7: 0
A8: Mikołaj | B8: Banaszkiewicz | C8: =A8&" "&B8 -> Mikołaj Banaszkiewicz | D8: =VLOOKUP(C8,CAPACITY!$C$12:$E$69,2,0) -> BE Developer | E8: =VLOOKUP(C8,CAPACITY!$C$12:$E$69,3,0) -> ALF | BI8: 0 | BJ8: 0 | BK8: 0 | BL8: 0 | BM8: 0 | BN8: 0 | BO8: 0 | BP8: 0 | BQ8: 0 | BR8: 0 | BS8: 0 | BT8: 0 | BU8: 0 | BV8: 0 | BW8: 0 | BX8: =SUM(BX9:BX11) -> 0 | BY8: =SUM(BY9:BY11) -> 0 | BZ8: 0 | CA8: 0 | CB8: 0 | CC8: 0 | CD8: 0 | CE8: 0 | CF8: 0
A9: Mikołaj | B9: Banaszkiewicz | C9: =A9&" "&B9 -> Mikołaj Banaszkiewicz | D9: =VLOOKUP(C9,CAPACITY!$C$12:$E$69,2,0) -> BE Developer | E9: =VLOOKUP(C9,CAPACITY!$C$12:$E$69,3,0) -> ALF | BI9: 0 | BJ9: 0 | BK9: 0 | BL9: 0 | BM9: 0 | BN9: 0 | BO9: 0 | BP9: 0 | BQ9: 0 | BR9: 0 | BS9: 0 | BT9: 0 | BU9: 0 | BV9: 0 | BW9: 0 | BX9: =SUM(BX10:BX12) -> 0 | BY9: =SUM(BY10:BY12) -> 0 | BZ9: 0 | CA9: 0 | CB9: 0 | CC9: 0 | CD9: 0 | CE9: 0 | CF9: 0
A10: Michał | B10: Godziszewski | C10: =A10&" "&B10 -> Michał Godziszewski | D10: =VLOOKUP(C10,CAPACITY!$C$12:$E$69,2,0) -> FE Developer | E10: =VLOOKUP(C10,CAPACITY!$C$12:$E$69,3,0) -> ALF | BI10: =SUM(BI11:BI13) -> 0 | BJ10: =SUM(BJ11:BJ13) -> 0 | BK10: =SUM(BK11:BK13) -> 0 | BL10: =SUM(BL11:BL13) -> 0 | BM10: =SUM(BM11:BM13) -> 0 | BN10: =SUM(BN11:BN13) -> 0 | BO10: =SUM(BO11:BO13) -> 0 | BP10: =SUM(BP11:BP13) -> 0 | ... CF10: =SUM(CF11:CF13) -> 0
A11: Michał | B11: Godziszewski | C11: =A11&" "&B11 -> Michał Godziszewski | D11: =VLOOKUP(C11,CAPACITY!$C$12:$E$69,2,0) -> FE Developer | E11: =VLOOKUP(C11,CAPACITY!$C$12:$E$69,3,0) -> ALF | F11: JET | BI11: 0 | BJ11: 0 | BK11: 0 | BL11: 0 | BM11: 0 | BN11: 0 | BO11: 0 | BP11: 0 | BQ11: 0 | BR11: 0 | BS11: 1 | BT11: 1 | BU11: 1 | BV11: 1 | BW11: 1 | BX11: =SUM(BX12:BX14) -> 0 | BY11: =SUM(BY12:BY14) -> 0 | BZ11: 1 | CA11: 1 | CB11: 1 | CC11: 1 | CD11: 1 | CE11: 0 | CF11: 0
A12: Michał | B12: Godziszewski | C12: =A12&" "&B12 -> Michał Godziszewski | D12: =VLOOKUP(C12,CAPACITY!$C$12:$E$69,2,0) -> FE Developer | E12: =VLOOKUP(C12,CAPACITY!$C$12:$E$69,3,0) -> ALF | BI12: 0 | BJ12: 0 | BK12: 0 | BL12: 0 | BM12: 0 | BN12: 0 | BO12: 0 | BP12: 0 | BQ12: 0 | BR12: 0 | BS12: 0 | BT12: 0 | BU12: 0 | BV12: 0 | BW12: 0 | BX12: =SUM(BX13:BX15) -> 0 | BY12: =SUM(BY13:BY15) -> 0 | BZ12: 0 | CA12: 0 | CB12: 0 | CC12: 0 | CD12: 0 | CE12: 0 | CF12: 0
A13: Michał | B13: Godziszewski | C13: =A13&" "&B13 -> Michał Godziszewski | D13: =VLOOKUP(C13,CAPACITY!$C$12:$E$69,2,0) -> FE Developer | E13: =VLOOKUP(C13,CAPACITY!$C$12:$E$69,3,0) -> ALF | BI13: 0 | BJ13: 0 | BK13: 0 | BL13: 0 | BM13: 0 | BN13: 0 | BO13: 0 | BP13: 0 | BQ13: 0 | BR13: 0 | BS13: 0 | BT13: 0 | BU13: 0 | BV13: 0 | BW13: 0 | BX13: =SUM(BX14:BX16) -> 0 | BY13: =SUM(BY14:BY16) -> 0 | BZ13: 0 | CA13: 0 | CB13: 0 | CC13: 0 | CD13: 0 | CE13: 0 | CF13: 0
A14: Adam | B14: Gruszecki | C14: =A14&" "&B14 -> Adam Gruszecki | D14: =VLOOKUP(C14,CAPACITY!$C$12:$E$69,2,0) -> BE Developer | E14: =VLOOKUP(C14,CAPACITY!$C$12:$E$69,3,0) -> ALF | BI14: =SUM(BI15:BI17) -> 0 | BJ14: =SUM(BJ15:BJ17) -> 0 | BK14: =SUM(BK15:BK17) -> 0 | BL14: =SUM(BL15:BL17) -> 0 | BM14: =SUM(BM15:BM17) -> 0 | BN14: =SUM(BN15:BN17) -> 0 | BO14: =SUM(BO15:BO17) -> 0 | BP14: =SUM(BP15:BP17) -> 0 | ... CF14: =SUM(CF15:CF17) -> 0
A15: Adam | B15: Gruszecki | C15: =A15&" "&B15 -> Adam Gruszecki | D15: =VLOOKUP(C15,CAPACITY!$C$12:$E$69,2,0) -> BE Developer | E15: =VLOOKUP(C15,CAPACITY!$C$12:$E$69,3,0) -> ALF | BI15: 0 | BJ15: 0 | BK15: 0 | BL15: 0 | BM15: 0 | BN15: 0 | BO15: 0 | BP15: 0 | BQ15: 0 | BR15: 0 | BS15: 0 | BT15: 0 | BU15: 0 | BV15: 0 | BW15: 0 | BX15: =SUM(BX16:BX18) -> 0 | BY15: =SUM(BY16:BY18) -> 0 | BZ15: 0 | CA15: 0 | CB15: 0 | CC15: 0 | CD15: 0 | CE15: 0 | CF15: 0
A16: Adam | B16: Gruszecki | C16: =A16&" "&B16 -> Adam Gruszecki | D16: =VLOOKUP(C16,CAPACITY!$C$12:$E$69,2,0) -> BE Developer | E16: =VLOOKUP(C16,CAPACITY!$C$12:$E$69,3,0) -> ALF | BI16: 0 | BJ16: 0 | BK16: 0 | BL16: 0 | BM16: 0 | BN16: 0 | BO16: 0 | BP16: 0 | BQ16: 0 | BR16: 0 | BS16: 0 | BT16: 0 | BU16: 0 | BV16: 0 | BW16: 0 | BX16: =SUM(BX17:BX19) -> 0 | BY16: =SUM(BY17:BY19) -> 0 | BZ16: 0 | CA16: 0 | CB16: 0 | CC16: 0 | CD16: 0 | CE16: 0 | CF16: 0
A17: Adam | B17: Gruszecki | C17: =A17&" "&B17 -> Adam Gruszecki | D17: =VLOOKUP(C17,CAPACITY!$C$12:$E$69,2,0) -> BE Developer | E17: =VLOOKUP(C17,CAPACITY!$C$12:$E$69,3,0) -> ALF | BI17: 0 | BJ17: 0 | BK17: 0 | BL17: 0 | BM17: 0 | BN17: 0 | BO17: 0 | BP17: 0 | BQ17: 0 | BR17: 0 | BS17: 0 | BT17: 0 | BU17: 0 | BV17: 0 | BW17: 0 | BX17: =SUM(BX18:BX20) -> 0 | BY17: =SUM(BY18:BY20) -> 0 | BZ17: 0 | CA17: 0 | CB17: 0 | CC17: 0 | CD17: 0 | CE17: 0 | CF17: 0
A18: Bartosz | B18: Listwan | C18: =A18&" "&B18 -> Bartosz Listwan | D18: =VLOOKUP(C18,CAPACITY!$C$12:$E$69,2,0) -> BE Developer | E18: =VLOOKUP(C18,CAPACITY!$C$12:$E$69,3,0) -> ALF | BI18: =SUM(BI19:BI21) -> 0 | BJ18: =SUM(BJ19:BJ21) -> 0 | BK18: =SUM(BK19:BK21) -> 0 | BL18: =SUM(BL19:BL21) -> 0 | BM18: =SUM(BM19:BM21) -> 0 | BN18: =SUM(BN19:BN21) -> 0 | BO18: =SUM(BO19:BO21) -> 0 | BP18: =SUM(BP19:BP21) -> 0 | ... CF18: =SUM(CF19:CF21) -> 0
A19: Bartosz | B19: Listwan | C19: =A19&" "&B19 -> Bartosz Listwan | D19: =VLOOKUP(C19,CAPACITY!$C$12:$E$69,2,0) -> BE Developer | E19: =VLOOKUP(C19,CAPACITY!$C$12:$E$69,3,0) -> ALF | BI19: 0 | BJ19: 0 | BK19: 0 | BL19: 0 | BM19: 0 | BN19: 0 | BO19: 0 | BP19: 0 | BQ19: 0 | BR19: 0 | BS19: 0 | BT19: 0 | BU19: 0 | BV19: 0 | BW19: 0 | BX19: =SUM(BX20:BX22) -> 0 | BY19: =SUM(BY20:BY22) -> 0 | BZ19: 0 | CA19: 0 | CB19: 0 | CC19: 0 | CD19: 0 | CE19: 0 | CF19: 0
A20: Bartosz | B20: Listwan | C20: =A20&" "&B20 -> Bartosz Listwan | D20: =VLOOKUP(C20,CAPACITY!$C$12:$E$69,2,0) -> BE Developer | E20: =VLOOKUP(C20,CAPACITY!$C$12:$E$69,3,0) -> ALF | BI20: 0 | BJ20: 0 | BK20: 0 | BL20: 0 | BM20: 0 | BN20: 0 | BO20: 0 | BP20: 0 | BQ20: 0 | BR20: 0 | BS20: 0 | BT20: 0 | BU20: 0 | BV20: 0 | BW20: 0 | BX20: =SUM(BX21:BX23) -> 0 | BY20: =SUM(BY21:BY23) -> 0 | BZ20: 0 | CA20: 0 | CB20: 0 | CC20: 0 | CD20: 0 | CE20: 0 | CF20: 0
A21: Bartosz | B21: Listwan | C21: =A21&" "&B21 -> Bartosz Listwan | D21: =VLOOKUP(C21,CAPACITY!$C$12:$E$69,2,0) -> BE Developer | E21: =VLOOKUP(C21,CAPACITY!$C$12:$E$69,3,0) -> ALF | BI21: 0 | BJ21: 0 | BK21: 0 | BL21: 0 | BM21: 0 | BN21: 0 | BO21: 0 | BP21: 0 | BQ21: 0 | BR21: 0 | BS21: 0 | BT21: 0 | BU21: 0 | BV21: 0 | BW21: 0 | BX21: =SUM(BX22:BX24) -> 0 | BY21: =SUM(BY22:BY24) -> 0 | BZ21: 0 | CA21: 0 | CB21: 0 | CC21: 0 | CD21: 0 | CE21: 0 | CF21: 0
A22: Joanna | B22: Redes | C22: =A22&" "&B22 -> Joanna Redes | D22: =VLOOKUP(C22,CAPACITY!$C$12:$E$69,2,0) -> BE Developer | E22: =VLOOKUP(C22,CAPACITY!$C$12:$E$69,3,0) -> ALF | BI22: =SUM(BI23:BI25) -> 0 | BJ22: =SUM(BJ23:BJ25) -> 0 | BK22: =SUM(BK23:BK25) -> 0 | BL22: =SUM(BL23:BL25) -> 0 | BM22: =SUM(BM23:BM25) -> 0 | BN22: =SUM(BN23:BN25) -> 0 | BO22: =SUM(BO23:BO25) -> 0 | BP22: =SUM(BP23:BP25) -> 0 | ... CF22: =SUM(CF23:CF25) -> 0
A23: Vacancy | B23: Vacancy | C23: =A23&" "&B23 -> Vacancy Vacancy | D23: =VLOOKUP(C23,CAPACITY!$C$12:$E$69,2,0) -> #N/A | E23: =VLOOKUP(C23,CAPACITY!$C$12:$E$69,3,0) -> #N/A | BI23: 0 | BJ23: 0 | BK23: 0 | BL23: 0 | BM23: 0 | BN23: 0 | BO23: 0 | BP23: 0 | BQ23: 0 | BR23: 0 | BS23: 0 | BT23: 0 | BU23: 0 | BV23: 0 | BW23: 0 | BX23: =SUM(BX24:BX26) -> 0 | BY23: =SUM(BY24:BY26) -> 0 | BZ23: 0 | CA23: 0 | CB23: 0 | CC23: 0 | CD23: 0 | CE23: 0 | CF23: 0
A24: Daniel | B24: Martyniuk | C24: =A24&" "&B24 -> Daniel Martyniuk | D24: =VLOOKUP(C24,CAPACITY!$C$12:$E$69,2,0) -> #N/A | E24: =VLOOKUP(C24,CAPACITY!$C$12:$E$69,3,0) -> #N/A
A25: Konrad | B25: Janiak | C25: =A25&" "&B25 -> Konrad Janiak | D25: =VLOOKUP(C25,CAPACITY!$C$12:$E$69,2,0) -> #N/A | E25: =VLOOKUP(C25,CAPACITY!$C$12:$E$69,3,0) -> #N/A
A26: Tomasz | B26: Sabała | C26: =A26&" "&B26 -> Tomasz Sabała | D26: =VLOOKUP(C26,CAPACITY!$C$12:$E$69,2,0) -> BE Developer | E26: =VLOOKUP(C26,CAPACITY!$C$12:$E$69,3,0) -> MASH
A27: Adrian | B27: Słabicki | C27: =A27&" "&B27 -> Adrian Słabicki | D27: =VLOOKUP(C27,CAPACITY!$C$12:$E$69,2,0) -> BE Developer | E27: =VLOOKUP(C27,CAPACITY!$C$12:$E$69,3,0) -> ALF
A28: Szymon | B28: Bratnik | C28: =A28&" "&B28 -> Szymon Bratnik | D28: =VLOOKUP(C28,CAPACITY!$C$12:$E$69,2,0) -> #N/A | E28: =VLOOKUP(C28,CAPACITY!$C$12:$E$69,3,0) -> #N/A
A29: Żaneta | B29: Fedor-Zalewska | C29: =A29&" "&B29 -> Żaneta Fedor-Zalewska | D29: =VLOOKUP(C29,CAPACITY!$C$12:$E$69,2,0) -> QA coordinator | E29: =VLOOKUP(C29,CAPACITY!$C$12:$E$69,3,0) -> ALF
A30: Jarosław | B30: Gawroński | C30: =A30&" "&B30 -> Jarosław Gawroński | D30: =VLOOKUP(C30,CAPACITY!$C$12:$E$69,2,0) -> QAA | E30: =VLOOKUP(C30,CAPACITY!$C$12:$E$69,3,0) -> ALF
A31: Karpo | B31: Dub | C31: =A31&" "&B31 -> Karpo Dub | D31: =VLOOKUP(C31,CAPACITY!$C$12:$E$69,2,0) -> #N/A | E31: =VLOOKUP(C31,CAPACITY!$C$12:$E$69,3,0) -> #N/A
A32: Tomasz | B32: Wierachowski | C32: =A32&" "&B32 -> Tomasz Wierachowski | D32: =VLOOKUP(C32,CAPACITY!$C$12:$E$69,2,0) -> QAE | E32: =VLOOKUP(C32,CAPACITY!$C$12:$E$69,3,0) -> MASH
A33: Jarosław | B33: Gawroński | C33: =A33&" "&B33 -> Jarosław Gawroński | D33: =VLOOKUP(C33,CAPACITY!$C$12:$E$69,2,0) -> QAA | E33: =VLOOKUP(C33,CAPACITY!$C$12:$E$69,3,0) -> ALF
A34: Karpo | B34: Dub | C34: =A34&" "&B34 -> Karpo Dub | D34: =VLOOKUP(C34,CAPACITY!$C$12:$E$69,2,0) -> #N/A | E34: =VLOOKUP(C34,CAPACITY!$C$12:$E$69,3,0) -> #N/A
A35: Tomasz | B35: Wierachowski | C35: =A35&" "&B35 -> Tomasz Wierachowski | D35: =VLOOKUP(C35,CAPACITY!$C$12:$E$69,2,0) -> QAE | E35: =VLOOKUP(C35,CAPACITY!$C$12:$E$69,3,0) -> MASH
... A39: Tomasz | B39: Wierachowski | C39: =A39&" "&B39 -> Tomasz Wierachowski | D39: =VLOOKUP(C39,CAPACITY!$C$12:$E$69,2,0) -> QAE | E39: =VLOOKUP(C39,CAPACITY!$C$12:$E$69,3,0) -> MASH

Sheet WORKLOAD_TEAMS (2)
A1: PRIORYTET | B1: DATE | C1: DATE | D1: TOTALS | E1: =TEXT(DATE(2024,1,1)+(E2-1)*7-WEEKDAY(DATE(2024,1,1),2)+1,"dd.mm")&"-"&TEXT(DATE(2024,1,1)+(E2-1)*7-WEEKDAY(DATE(2024,1,1),2)+7,"dd.mm") -> 11.03-17.03 | F1: =TEXT(DATE(2024,1,1)+(F2-1)*7-WEEKDAY(DATE(2024,1,1),2)+1,"dd.mm")&"-"&TEXT(DATE(2024,1,1)+(F2-1)*7-WEEKDAY(DATE(2024,1,1),2)+7,"dd.mm") -> 18.03-24.03 | G1: =TEXT(DATE(2024,1,1)+(G2-1)*7-WEEKDAY(DATE(2024,1,1),2)+1,"dd.mm")&"-"&TEXT(DATE(2024,1,1)+(G2-1)*7-WEEKDAY(DATE(2024,1,1),2)+7,"dd.mm") -> 25.03-31.03 | H1: =TEXT(DATE(2024,1,1)+(H2-1)*7-WEEKDAY(DATE(2024,1,1),2)+1,"dd.mm")&"-"&TEXT(DATE(2024,1,1)+(H2-1)*7-WEEKDAY(DATE(2024,1,1),2)+7,"dd.mm") -> 01.04-07.04 | I1: =TEXT(DATE(2024,1,1)+(I2-1)*7-WEEKDAY(DATE(2024,1,1),2)+1,"dd.mm")&"-"&TEXT(DATE(2024,1,1)+(I2-1)*7-WEEKDAY(DATE(2024,1,1),2)+7,"dd.mm") -> 08.04-14.04 | J1: =TEXT(DATE(2024,1,1)+(J2-1)*7-WEEKDAY(DATE(2024,1,1),2)+1,"dd.mm")&"-"&TEXT(DATE(2024,1,1)+(J2-1)*7-WEEKDAY(DATE(2024,1,1),2)+7,"dd.mm") -> 15.04-21.04 | K1: =TEXT(DATE(2024,1,1)+(K2-1)*7-WEEKDAY(DATE(2024,1,1),2)+1,"dd.mm")&"-"&TEXT(DATE(2024,1,1)+(K2-1)*7-WEEKDAY(DATE(2024,1,1),2)+7,"dd.mm") -> 22.04-28.04 | L1: =TEXT(DATE(2024,1,1)+(L2-1)*7-WEEKDAY(DATE(2024,1,1),2)+1,"dd.mm")&"-"&TEXT(DATE(2024,1,1)+(L2-1)*7-WEEKDAY(DATE(2024,1,1),2)+7,"dd.mm") -> 29.04-05.05 | ... AT1: =TEXT(DATE(2024,1,1)+(AT2-1)*7-WEEKDAY(DATE(2024,1,1),2)+1,"dd.mm")&"-"&TEXT(DATE(2024,1,1)+(AT2-1)*7-WEEKDAY(DATE(2024,1,1),2)+7,"dd.mm") -> 23.12-29.12 | AU1: =TEXT(DATE(2025,1,1)+(AU2-1)*7-WEEKDAY(DATE(2025,1,1),2)+1,"dd.mm")&"-"&TEXT(DATE(2025,1,1)+(AU2-1)*7-WEEKDAY(DATE(2025,1,1),2)+7,"dd.mm") -> 30.12-05.01 | AV1: =TEXT(DATE(2025,1,1)+(AV2-1)*7-WEEKDAY(DATE(2025,1,1),2)+1,"dd.mm")&"-"&TEXT(DATE(2025,1,1)+(AV2-1)*7-WEEKDAY(DATE(2025,1,1),2)+7,"dd.mm") -> 06.01-12.01 | AW1: =TEXT(DATE(2025,1,1)+(AW2-1)*7-WEEKDAY(DATE(2025,1,1),2)+1,"dd.mm")&"-"&TEXT(DATE(2025,1,1)+(AW2-1)*7-WEEKDAY(DATE(2025,1,1),2)+7,"dd.mm") -> 13.01-19.01 | AX1: =TEXT(DATE(2025,1,1)+(AX2-1)*7-WEEKDAY(DATE(2025,1,1),2)+1,"dd.mm")&"-"&TEXT(DATE(2025,1,1)+(AX2-1)*7-WEEKDAY(DATE(2025,1,1),2)+7,"dd.mm") -> 20.01-26.01 | AY1: =TEXT(DATE(2025,1,1)+(AY2-1)*7-WEEKDAY(DATE(2025,1,1),2)+1,"dd.mm")&"-"&TEXT(DATE(2025,1,1)+(AY2-1)*7-WEEKDAY(DATE(2025,1,1),2)+7,"dd.mm") -> 27.01-02.02 | AZ1: =TEXT(DATE(2025,1,1)+(AZ2-1)*7-WEEKDAY(DATE(2025,1,1),2)+1,"dd.mm")&"-"&TEXT(DATE(2025,1,1)+(AZ2-1)*7-WEEKDAY(DATE(2025,1,1),2)+7,"dd.mm") -> 03.02-09.02 | BA1: =TEXT(DATE(2025,1,1)+(BA2-1)*7-WEEKDAY(DATE(2025,1,1),2)+1,"dd.mm")&"-"&TEXT(DATE(2025,1,1)+(BA2-1)*7-WEEKDAY(DATE(2025,1,1),2)+7,"dd.mm") -> 10.02-16.02 | BB1: =TEXT(DATE(2025,1,1)+(BB2-1)*7-WEEKDAY(DATE(2025,1,1),2)+1,"dd.mm")&"-"&TEXT(DATE(2025,1,1)+(BB2-1)*7-WEEKDAY(DATE(2025,1,1),2)+7,"dd.mm") -> 17.02-23.02 | ... CT1: =TEXT(DATE(2025,1,1)+(CT2-1)*7-WEEKDAY(DATE(2025,1,1),2)+1,"dd.mm")&"-"&TEXT(DATE(2025,1,1)+(CT2-1)*7-WEEKDAY(DATE(2025,1,1),2)+7,"dd.mm") -> 22.12-28.12
C2: WEEK | E2: 11 | F2: 12 | G2: 13 | H2: 14 | I2: 15 | J2: 16 | K2: 17 | L2: 18 | M2: 19 | N2: 20 | O2: 21 | P2: 22 | Q2: 23 | R2: 24 | S2: 25 | T2: 26 | U2: 27 | V2: 28 | W2: 29 | X2: 30 | Y2: 31 | Z2: 32 | AA2: 33 | AB2: 34 | AC2: 35 | AD2: 36 | AE2: 37 | AF2: 38 | AG2: 39 | AH2: 40 | AI2: 41 | AJ2: 42 | AK2: 43 | AL2: 44 | AM2: 45 | AN2: 46 | AO2: 47 | AP2: 48 | AQ2: 49 | AR2: 50 | AS2: 51 | AT2: 52 | AU2: 1 | AV2: 2 | AW2: 3 | AX2: 4 | AY2: 5 | AZ2: 6 | BA2: 7 | BB2: 8 | BC2: 9 | BD2: 10 | BE2: 11 | BF2: 12 | BG2: 13 | BH2: 14 | BI2: 15 | BJ2: 16 | BK2: 17 | BL2: 18 | BM2: 19 | BN2: 20 | BO2: 21 | BP2: 22 | BQ2: 23 | BR2: 24 | BS2: 25 | BT2: 26 | BU2: 27 | BV2: 28 | BW2: 29 | BX2: 30 | BY2: 31 | BZ2: 32 | CA2: 33 | CB2: 34 | CC2: 35 | CD2: 36 | CE2: 37 | CF2: 38 | CG2: 39 | CH2: 40 | CI2: 41 | CJ2: 42 | CK2: 43 | CL2: 44 | CM2: 45 | CN2: 46 | CO2: 47 | CP2: 48 | CQ2: 49 | CR2: 50 | CS2: 51 | CT2: 52
B3: PROJECTS & FUNCTIONALITIES CAPACITY | C3: ALF | E3: =CAPACITY!G2 -> 27.342 | F3: =OFFSET(CAPACITY!$G$2,0,7*(F$2-$E$2)) -> 27.342 | G3: =OFFSET(CAPACITY!$G$2,0,7*(G$2-$E$2)) -> 27.342 | H3: =OFFSET(CAPACITY!$G$2,0,7*(H$2-$E$2)) -> 21.462 | I3: =OFFSET(CAPACITY!$G$2,0,7*(I$2-$E$2)) -> 27.342 | J3: =OFFSET(CAPACITY!$G$2,0,7*(J$2-$E$2)) -> 27.342 | K3: =OFFSET(CAPACITY!$G$2,0,7*(K$2-$E$2)) -> 27.342 | L3: =OFFSET(CAPACITY!$G$2,0,7*(L$2-$E$2)) -> 14.028 | M3: =OFFSET(CAPACITY!$G$2,0,7*(M$2-$E$2)) -> 28.371 | ... AT3: =OFFSET(CAPACITY!$G$2,0,7*(AT$2-$E$2)) -> 12.39 | AU3: =OFFSET(CAPACITY!$G$2,0,7*(AU$2+52-$E$2)) -> 17.346 | AV3: =OFFSET(CAPACITY!$G$2,0,7*(AV$2+52-$E$2)) -> 23.247 | AW3: =OFFSET(CAPACITY!$G$2,0,7*(AW$2+52-$E$2)) -> 28.728 | AX3: =OFFSET(CAPACITY!$G$2,0,7*(AX$2+52-$E$2)) -> 28.728 | AY3: =OFFSET(CAPACITY!$G$2,0,7*(AY$2+52-$E$2)) -> 26.439 | AZ3: =OFFSET(CAPACITY!$G$2,0,7*(AZ$2+52-$E$2)) -> 28.455 | BA3: =OFFSET(CAPACITY!$G$2,0,7*(BA$2+52-$E$2)) -> 27.342 | BB3: =OFFSET(CAPACITY!$G$2,0,7*(BB$2+52-$E$2)) -> 28.581 | ... CT3: =OFFSET(CAPACITY!$G$2,0,7*(CT$2+52-$E$2)) -> 9.66
C4: WAREX | E4: =CAPACITY!G4 -> 10.388559 | F4: =OFFSET(CAPACITY!$G$4,0,7*(F$2-$E$2)) -> 10.388559 | G4: =OFFSET(CAPACITY!$G$4,0,7*(G$2-$E$2)) -> 10.388559 | H4: =OFFSET(CAPACITY!$G$4,0,7*(H$2-$E$2)) -> 8.1544599 | I4: =OFFSET(CAPACITY!$G$4,0,7*(I$2-$E$2)) -> 10.388559 | J4: =OFFSET(CAPACITY!$G$4,0,7*(J$2-$E$2)) -> 10.069402 | K4: =OFFSET(CAPACITY!$G$4,0,7*(K$2-$E$2)) -> 10.388559 | L4: =OFFSET(CAPACITY!$G$4,0,7*(L$2-$E$2)) -> 1.9149417 | M4: =OFFSET(CAPACITY!$G$4,0,7*(M$2-$E$2)) -> 9.4310877 | ... AT4: =OFFSET(CAPACITY!$G$4,0,7*(AT$2-$E$2)) -> 9.4151298 | AU4: =OFFSET(CAPACITY!$G$4,0,7*(AU$2+52-$E$2)) -> 13.181182 | AV4: =OFFSET(CAPACITY!$G$4,0,7*(AV$2+52-$E$2)) -> 17.665337 | AW4: =OFFSET(CAPACITY!$G$4,0,7*(AW$2+52-$E$2)) -> 21.830335 | AX4: =OFFSET(CAPACITY!$G$4,0,7*(AX$2+52-$E$2)) -> 21.830335 | AY4: =OFFSET(CAPACITY!$G$4,0,7*(AY$2+52-$E$2)) -> 20.09093 | AZ4: =OFFSET(CAPACITY!$G$4,0,7*(AZ$2+52-$E$2)) -> 21.622883 | BA4: =OFFSET(CAPACITY!$G$4,0,7*(BA$2+52-$E$2)) -> 20.777117 | BB4: =OFFSET(CAPACITY!$G$4,0,7*(BB$2+52-$E$2)) -> 21.71863 | ... CT4: =OFFSET(CAPACITY!$G$4,0,7*(CT$2+52-$E$2)) -> 7.3406097
C5: OPTIMUS | E5: =CAPACITY!G6 -> 21.241748 | F5: =OFFSET(CAPACITY!$G$6,0,7*(F$2-$E$2)) -> 21.241748 | G5: =OFFSET(CAPACITY!$G$6,0,7*(G$2-$E$2)) -> 21.241748 | H5: =OFFSET(CAPACITY!$G$6,0,7*(H$2-$E$2)) -> 16.67363 | I5: =OFFSET(CAPACITY!$G$6,0,7*(I$2-$E$2)) -> 21.241748 | J5: =OFFSET(CAPACITY!$G$6,0,7*(J$2-$E$2)) -> 21.241748 | K5: =OFFSET(CAPACITY!$G$6,0,7*(K$2-$E$2)) -> 21.241748 | L5: =OFFSET(CAPACITY!$G$6,0,7*(L$2-$E$2)) -> 8.995678 | M5: =OFFSET(CAPACITY!$G$6,0,7*(M$2-$E$2)) -> 18.395459 | ... AT5: =OFFSET(CAPACITY!$G$6,0,7*(AT$2-$E$2)) -> 7.9063577 | AU5: =OFFSET(CAPACITY!$G$6,0,7*(AU$2+52-$E$2)) -> 12.281209 | AV5: =OFFSET(CAPACITY!$G$6,0,7*(AV$2+52-$E$2)) -> 14.705825 | AW5: =OFFSET(CAPACITY!$G$6,0,7*(AW$2+52-$E$2)) -> 20.082148 | AX5: =OFFSET(CAPACITY!$G$6,0,7*(AX$2+52-$E$2)) -> 20.082148 | AY5: =OFFSET(CAPACITY!$G$6,0,7*(AY$2+52-$E$2)) -> 18.852271 | AZ5: =OFFSET(CAPACITY!$G$6,0,7*(AZ$2+52-$E$2)) -> 19.027967 | BA5: =OFFSET(CAPACITY!$G$6,0,7*(BA$2+52-$E$2)) -> 17.270999 | BB5: =OFFSET(CAPACITY!$G$6,0,7*(BB$2+52-$E$2)) -> 15.074789 | ... CT5: =OFFSET(CAPACITY!$G$6,0,7*(CT$2+52-$E$2)) -> 4.9195114
C6: MASH | E6: =CAPACITY!G8 -> 8.1375 | F6: =OFFSET(CAPACITY!$G$8,0,7*(F$2-$E$2)) -> 8.1375 | G6: =OFFSET(CAPACITY!$G$8,0,7*(G$2-$E$2)) -> 8.1375 | H6: =OFFSET(CAPACITY!$G$8,0,7*(H$2-$E$2)) -> 6.3875 | I6: =OFFSET(CAPACITY!$G$8,0,7*(I$2-$E$2)) -> 8.1375 | J6: =OFFSET(CAPACITY!$G$8,0,7*(J$2-$E$2)) -> 8.1375 | K6: =OFFSET(CAPACITY!$G$8,0,7*(K$2-$E$2)) -> 8.1375 | L6: =OFFSET(CAPACITY!$G$8,0,7*(L$2-$E$2)) -> 5.25 | M6: =OFFSET(CAPACITY!$G$8,0,7*(M$2-$E$2)) -> 8.1375 | ... AT6: =OFFSET(CAPACITY!$G$8,0,7*(AT$2-$E$2)) -> 2.205 | AU6: =OFFSET(CAPACITY!$G$8,0,7*(AU$2+52-$E$2)) -> 3.4825 | AV6: =OFFSET(CAPACITY!$G$8,0,7*(AV$2+52-$E$2)) -> 6.0375 | AW6: =OFFSET(CAPACITY!$G$8,0,7*(AW$2+52-$E$2)) -> 7.91 | AX6: =OFFSET(CAPACITY!$G$8,0,7*(AX$2+52-$E$2)) -> 7.21 | AY6: =OFFSET(CAPACITY!$G$8,0,7*(AY$2+52-$E$2)) -> 6.86 | AZ6: =OFFSET(CAPACITY!$G$8,0,7*(AZ$2+52-$E$2)) -> 6.7375 | BA6: =OFFSET(CAPACITY!$G$8,0,7*(BA$2+52-$E$2)) -> 6.16 | BB6: =OFFSET(CAPACITY!$G$8,0,7*(BB$2+52-$E$2)) -> 7.56 | ... CT6: =OFFSET(CAPACITY!$G$8,0,7*(CT$2+52-$E$2)) -> 3.15
C7: MAGENTO | E7: =CAPACITY!G10 -> 23.2875 | F7: =OFFSET(CAPACITY!$G$10,0,7*(F$2-$E$2)) -> 23.2875 | G7: =OFFSET(CAPACITY!$G$10,0,7*(G$2-$E$2)) -> 23.2875 | H7: =OFFSET(CAPACITY!$G$10,0,7*(H$2-$E$2)) -> 22.5375 | I7: =OFFSET(CAPACITY!$G$10,0,7*(I$2-$E$2)) -> 23.2875 | J7: =OFFSET(CAPACITY!$G$10,0,7*(J$2-$E$2)) -> 23.2875 | K7: =OFFSET(CAPACITY!$G$10,0,7*(K$2-$E$2)) -> 23.2875 | L7: =OFFSET(CAPACITY!$G$10,0,7*(L$2-$E$2)) -> 20.25 | M7: =OFFSET(CAPACITY!$G$10,0,7*(M$2-$E$2)) -> 24.1575 | ... AT7: =OFFSET(CAPACITY!$G$10,0,7*(AT$2-$E$2)) -> 12.1125 | AU7: =OFFSET(CAPACITY!$G$10,0,7*(AU$2+52-$E$2)) -> 15.6675 | AV7: =OFFSET(CAPACITY!$G$10,0,7*(AV$2+52-$E$2)) -> 19.18875 | AW7: =OFFSET(CAPACITY!$G$10,0,7*(AW$2+52-$E$2)) -> 24.1575 | AX7: =OFFSET(CAPACITY!$G$10,0,7*(AX$2+52-$E$2)) -> 24.1575 | AY7: =OFFSET(CAPACITY!$G$10,0,7*(AY$2+52-$E$2)) -> 24.1575 | AZ7: =OFFSET(CAPACITY!$G$10,0,7*(AZ$2+52-$E$2)) -> 24.1575 | BA7: =OFFSET(CAPACITY!$G$10,0,7*(BA$2+52-$E$2)) -> 24.1575 | BB7: =OFFSET(CAPACITY!$G$10,0,7*(BB$2+52-$E$2)) -> 24.1575 | ... CT7: =OFFSET(CAPACITY!$G$10,0,7*(CT$2+52-$E$2)) -> 7.5
B8: PROJECTS & FUNCTIONALITIES CAPACITY UTILISATION | C8: ALF | E8: =E3-SUMIF($C$13:$C$519,$C8,E13:E519) -> 15.342 | F8: =F3-SUMIF($C$13:$C$519,$C8,F13:F519) -> 15.342 | G8: =G3-SUMIF($C$13:$C$519,$C8,G13:G519) -> 15.342 | H8: =H3-SUMIF($C$13:$C$519,$C8,H13:H519) -> 9.462 | I8: =I3-SUMIF($C$13:$C$519,$C8,I13:I519) -> 15.342 | J8: =J3-SUMIF($C$13:$C$519,$C8,J13:J519) -> 15.342 | K8: =K3-SUMIF($C$13:$C$519,$C8,K13:K519) -> 5.342 | L8: =L3-SUMIF($C$13:$C$519,$C8,L13:L519) -> -3.972 | ... BI8: =BI3-SUMIF($C$13:$C$519,$C8,BI13:BI519) -> 30.702
C9: WAREX | E9: =E4-SUMIF($C$13:$C$519,$C9,E13:E519) -> 10.388559 | F9: =F4-SUMIF($C$13:$C$519,$C9,F13:F519) -> 10.388559 | G9: =G4-SUMIF($C$13:$C$519,$C9,G13:G519) -> 10.388559 | H9: =H4-SUMIF($C$13:$C$519,$C9,H13:H519) -> 0.15445992 | I9: =I4-SUMIF($C$13:$C$519,$C9,I13:I519) -> 2.3885585 | J9: =J4-SUMIF($C$13:$C$519,$C9,J13:J519) -> 2.0694016 | K9: =K4-SUMIF($C$13:$C$519,$C9,K13:K519) -> -3.6114415 | L9: =L4-SUMIF($C$13:$C$519,$C9,L13:L519) -> -4.0850583 | ... BI9: =BI4-SUMIF($C$13:$C$519,$C9,BI13:BI519) -> 23.330373
C10: OPTIMUS | E10: =E5-SUMIF($C$13:$C$519,$C10,E13:E519) -> 21.241748 | F10: =F5-SUMIF($C$13:$C$519,$C10,F13:F519) -> 21.241748 | G10: =G5-SUMIF($C$13:$C$519,$C10,G13:G519) -> 21.241748 | H10: =H5-SUMIF($C$13:$C$519,$C10,H13:H519) -> 16.67363 | I10: =I5-SUMIF($C$13:$C$519,$C10,I13:I519) -> 21.241748 | J10: =J5-SUMIF($C$13:$C$519,$C10,J13:J519) -> 21.241748 | K10: =K5-SUMIF($C$13:$C$519,$C10,K13:K519) -> 21.241748 | L10: =L5-SUMIF($C$13:$C$519,$C10,L13:L519) -> 8.995678 | ... BI10: =BI5-SUMIF($C$13:$C$519,$C10,BI13:BI519) -> 17.868368
C11: MASH | E11: =E6-SUMIF($C$13:$C$519,$C11,E13:E519) -> 7.6375 | F11: =F6-SUMIF($C$13:$C$519,$C11,F13:F519) -> 7.6375 | G11: =G6-SUMIF($C$13:$C$519,$C11,G13:G519) -> 7.6375 | H11: =H6-SUMIF($C$13:$C$519,$C11,H13:H519) -> 4.8875 | I11: =I6-SUMIF($C$13:$C$519,$C11,I13:I519) -> 5.6375 | J11: =J6-SUMIF($C$13:$C$519,$C11,J13:J519) -> 3.6375 | K11: =K6-SUMIF($C$13:$C$519,$C11,K13:K519) -> 0.6375 | L11: =L6-SUMIF($C$13:$C$519,$C11,L13:L519) -> -2.25 | ... BI11: =BI6-SUMIF($C$13:$C$519,$C11,BI13:BI519) -> 8.1375
C12: MAGENTO | E12: =E7-SUMIF($C$13:$C$519,$C12,E13:E519) -> 23.2875 | F12: =F7-SUMIF($C$13:$C$519,$C12,F13:F519) -> 23.2875 | G12: =G7-SUMIF($C$13:$C$519,$C12,G13:G519) -> 23.2875 | H12: =H7-SUMIF($C$13:$C$519,$C12,H13:H519) -> 22.5375 | I12: =I7-SUMIF($C$13:$C$519,$C12,I13:I519) -> 23.2875 | J12: =J7-SUMIF($C$13:$C$519,$C12,J13:J519) -> 11.2875 | K12: =K7-SUMIF($C$13:$C$519,$C12,K13:K519) -> 0.2875 | L12: =L7-SUMIF($C$13:$C$519,$C12,L13:L519) -> 2.25 | ... BI12: =BI7-SUMIF($C$13:$C$519,$C12,BI13:BI519) -> 24.4125
B13: DŁUG FUNKCJONALNY ALF | C13: ALF | D13: =SUM(E13:CT13) -> 612 | E13: 12 | F13: 12 | G13: 12 | H13: 12 | I13: 12 | J13: 12 | K13: 12 | L13: 12 | M13: 12 | N13: 12 | O13: 12 | P13: 12 | Q13: 12 | R13: 12 | S13: 12 | T13: 12 | U13: 12 | V13: 12 | W13: 12 | X13: 12 | Y13: 12 | Z13: 12 | AA13: 12 | AB13: 12 | AC13: 12 | AD13: 12 | AE13: 12 | AF13: 12 | AG13: 12 | AH13: 12 | AI13: 12 | AJ13: 12 | AK13: 12 | AL13: 12 | AM13: 12 | AN13: 12 | AO13: 12 | AP13: 12 | AQ13: 12 | AR13: 12 | AS13: 12 | AV13: 12 | AW13: 12 | AX13: 12 | AY13: 12 | AZ13: 12 | BA13: 12 | BB13: 12 | BC13: 12 | BD13: 12 | BE13: 12
C14: WAREX | D14: =SUM(E14:CT14) -> 0
C15: OPTIMUS | D15: =SUM(E15:CT15) -> 0
C16: MASH | D16: =SUM(E16:CT16) -> 25.5 | E16: 0.5 | F16: 0.5 | G16: 0.5 | H16: 0.5 | I16: 0.5 | J16: 0.5 | K16: 0.5 | L16: 0.5 | M16: 0.5 | N16: 0.5 | O16: 0.5 | P16: 0.5 | Q16: 0.5 | R16: 0.5 | S16: 0.5 | T16: 0.5 | U16: 0.5 | V16: 0.5 | W16: 0.5 | X16: 0.5 | Y16: 0.5 | Z16: 0.5 | AA16: 0.5 | AB16: 0.5 | AC16: 0.5 | AD16: 0.5 | AE16: 0.5 | AF16: 0.5 | AG16: 0.5 | AH16: 0.5 | AI16: 0.5 | AJ16: 0.5 | AK16: 0.5 | AL16: 0.5 | AM16: 0.5 | AN16: 0.5 | AO16: 0.5 | AP16: 0.5 | AQ16: 0.5 | AR16: 0.5 | AS16: 0.5 | AV16: 0.5 | AW16: 0.5 | AX16: 0.5 | AY16: 0.5 | AZ16: 0.5 | BA16: 0.5 | BB16: 0.5 | BC16: 0.5 | BD16: 0.5 | BE16: 0.5
C17: MAGENTO | D17: =SUM(E17:CT17) -> 0
A18: 0 | B18: Project - Portal B2B 1(1.5) | C18: ALF | D18: =SUM(E18:CT18) -> 2 | K18: 2
C19: WAREX | D19: =SUM(E19:CT19) -> 0
C20: OPTIMUS | D20: =SUM(E20:CT20) -> 0
C21: MASH | D21: =SUM(E21:CT21) -> 2 | J21: 1 | M21: 1
C22: MAGENTO | D22: =SUM(E22:CT22) -> 27 | J22: 6 | K22: 3 | L22: 3 | M22: 3 | N22: 2 | R22: 5 | S22: 5
A23: 0 | B23: Project - Multibrand for iMad | C23: ALF | D23: =SUM(E23:CT23) -> 2 | K23: 2
C24: WAREX | D24: =SUM(E24:CT24) -> 0
C25: OPTIMUS | D25: =SUM(E25:CT25) -> 0
C26: MASH | D26: =SUM(E26:CT26) -> 1 | K26: 1
C27: MAGENTO | D27: =SUM(E27:CT27) -> 35 | K27: 5 | L27: 5 | M27: 5 | Q27: 5 | R27: 5 | S27: 5 | T27: 5
A28: 0 | B28: Project - Malezja Faza 1A | C28: ALF | D28: =SUM(E28:CT28) -> 8.5 | K28: 1 | L28: 1 | M28: 0.5 | O28: 1 | P28: 3 | Q28: 2
C29: WAREX | D29: =SUM(E29:CT29) -> 1 | M29: 0.5 | N29: 0.5
C30: OPTIMUS | D30: =SUM(E30:CT30) -> 8 | P30: 0.5 | Q30: 0.5 | R30: 5 | S30: 2
C31: MASH | D31: =SUM(E31:CT31) -> 21 | H31: 1 | I31: 2 | J31: 3 | K31: 3 | L31: 2 | M31: 3 | N31: 1 | P31: 0.5 | Q31: 1 | R31: 0.5 | S31: 1 | T31: 2 | U31: 1
C32: MAGENTO | D32: =SUM(E32:CT32) -> 92 | J32: 6 | K32: 15 | L32: 10 | M32: 5 | N32: 15 | O32: 15 | P32: 10 | Q32: 5 | R32: 4 | S32: 4 | T32: 3
A33: 0 | B33: MM Open Days: Faza1 - 22/05 | C33: ALF | D33: =SUM(E33:CT33) -> 25 | K33: 5 | L33: 5 | M33: 5 | N33: 5 | O33: 5
C34: WAREX | D34: =SUM(E34:CT34) -> 2 | N34: 2
C35: OPTIMUS | D35: =SUM(E35:CT35) -> 0
C36: MASH | D36: =SUM(E36:CT36) -> 15 | K36: 3 | L36: 5 | M36: 3 | N36: 2 | O36: 2
C37: MAGENTO | D37: =SUM(E37:CT37) -> 10 | N37: 5 | O37: 5
A38: 0 | B38: MM Open Days: Faza2 - 03/06 | C38: ALF | D38: =SUM(E38:CT38) -> 0
C39: WAREX | D39: =SUM(E39:CT39) -> 0
C40: OPTIMUS | D40: =SUM(E40:CT40) -> 0
C41: MASH | D41: =SUM(E41:CT41) -> 0
C42: MAGENTO | D42: =SUM(E42:CT42) -> 4 | P42: 4
A43: 0 | B43: Open Days tMobile - 23/06 + Genetal Open Days Tasks | C43: ALF | D43: =SUM(E43:CT43) -> 0
C44: WAREX | D44: =SUM(E44:CT44) -> 0
C45: OPTIMUS | D45: =SUM(E45:CT45) -> 0
C46: MASH | D46: =SUM(E46:CT46) -> 0
C47: MAGENTO | D47: =SUM(E47:CT47) -> 12 | Q47: 4 | R47: 3 | S47: 5
A48: 0 | B48: PLAY New Assortment Groups | C48: ALF | D48: =SUM(E48:CT48) -> 0
C49: WAREX | D49: =SUM(E49:CT49) -> 44 | H49: 3 | I49: 3 | J49: 3 | K49: 8 | L49: 3 | M49: 12 | N49: 8 | O49: 2 | Q49: 1 | R49: 1
C50: OPTIMUS | D50: =SUM(E50:CT50) -> 29 | P50: 5 | Q50: 10 | R50: 10 | S50: 3 | T50: 1
C51: MASH | D51: =SUM(E51:CT51) -> 0
C52: MAGENTO | D52: =SUM(E52:CT52) -> 0
A53: 0 | B53: Inicjatywa PLK karta usług (B2B Enterprise + Frontend) | C53: ALF | D53: =SUM(E53:CT53) -> 0
C54: WAREX | D54: =SUM(E54:CT54) -> 105 | H54: 5 | I54: 5 | J54: 5 | K54: 6 | L54: 3 | M54: 8 | N54: 8 | O54: 9 | P54: 9 | Q54: 4 | R54: 4 | S54: 8 | T54: 4 | U54: 5 | V54: 3 | W54: 4 | X54: 4 | Y54: 3 | Z54: 2 | AA54: 3 | AB54: 2 | AC54: 1
C55: OPTIMUS | D55: =SUM(E55:CT55) -> 25 | U55: 1 | Y55: 7 | Z55: 5 | AA55: 5 | AB55: 3 | AC55: 4
C56: MASH | D56: =SUM(E56:CT56) -> 0
C57: MAGENTO | D57: =SUM(E57:CT57) -> 0
A58: 0 | B58: JET (zmiana leasingu na najem do 27 maja) | C58: ALF | D58: =SUM(E58:CT58) -> 10 | N58: 2 | O58: 5 | Q58: 3
C59: WAREX | D59: =SUM(E59:CT59) -> 0
C60: OPTIMUS | D60: =SUM(E60:CT60) -> 0
C61: MASH | D61: =SUM(E61:CT61) -> 0
C62: MAGENTO | D62: =SUM(E62:CT62) -> 0
A63: 0 | B63: ALLPSI | C63: ALF | D63: =SUM(E63:CT63) -> 36 | N63: 2 | O63: 5 | P63: 5 | Q63: 6 | R63: 5 | S63: 4 | T63: 2 | U63: 2 | V63: 2 | W63: 3
C64: WAREX | D64: =SUM(E64:CT64) -> 0
C65: OPTIMUS | D65: =SUM(E65:CT65) -> 0
C66: MASH | D66: =SUM(E66:CT66) -> 10 | M66: 1 | N66: 3 | O66: 1 | P66: 1 | Q66: 1 | R66: 1 | S66: 1 | T66: 1
C67: MAGENTO | D67: =SUM(E67:CT67) -> 0
A68: 0 | B68: PHOX | C68: ALF | D68: =SUM(E68:CT68) -> 30 | X68: 5 | Y68: 5 | Z68: 5 | AA68: 5 | AB68: 5 | AC68: 5
C69: WAREX | D69: =SUM(E69:CT69) -> 25 | Z69: 5 | AA69: 5 | AB69: 5 | AC69: 5 | AD69: 5
C70: OPTIMUS | D70: =SUM(E70:CT70) -> 20 | AB70: 5 | AC70: 5 | AD70: 5 | AE70: 5
C71: MASH | D71: =SUM(E71:CT71) -> 5 | X71: 1 | Y71: 1 | Z71: 1 | AA71: 1 | AB71: 1
C72: MAGENTO
A73: 0 | B73: (BIK) Antyfraud CFD | C73: ALF | D73: =SUM(E73:CT73) -> 0
C74: WAREX | D74: =SUM(E74:CT74) -> 0
C75: OPTIMUS | D75: =SUM(E75:CT75) -> 0
C76: MASH | D76: =SUM(E76:CT76) -> 21 | M76: 1 | N76: 1 | O76: 1 | P76: 0.5 | Q76: 1 | R76: 1 | S76: 3 | T76: 3 | U76: 2 | V76: 2 | W76: 2 | X76: 0.5 | Y76: 0.5 | Z76: 0.5 | AA76: 1 | AB76: 1
C77: MAGENTO | D77: =SUM(E77:CT77) -> 41 | R77: 2 | S77: 5 | T77: 3 | U77: 3 | V77: 3 | W77: 3 | X77: 5 | Y77: 5 | Z77: 2 | AA77: 5 | AB77: 5
A78: 0 | B78: Inicjatywa API PLAY | C78: ALF | D78: =SUM(E78:CT78) -> 0
C79: WAREX | D79: =SUM(E79:CT79) -> 0
C80: OPTIMUS | D80: =SUM(E80:CT80) -> 7 | T80: 1 | U80: 2 | V80: 2 | W80: 2
C81: MASH | D81: =SUM(E81:CT81) -> 0
C82: MAGENTO | D82: =SUM(E82:CT82) -> 0
B83: Mbox for MM (Worten) - 23.07 | C83: ALF | D83: =SUM(E83:CT83) -> 20 | V83: 10 | W83: 8 | X83: 2
C84: WAREX | D84: =SUM(E84:CT84) -> 0
C85: OPTIMUS | D85: =SUM(E85:CT85) -> 0
C86: MASH | D86: =SUM(E86:CT86) -> 0
C87: MAGENTO | D87: =SUM(E87:CT87) -> 20 | V87: 10 | W87: 8 | X87: 2
A88: 1 | B88: Rebranding | C88: ALF | D88: =SUM(E88:CT88) -> 73 | Q88: 6 | R88: 10 | S88: 8 | T88: 8 | U88: 8 | V88: 8 | W88: 5 | Y88: 5 | AC88: 5 | AD88: 5 | AE88: 5
C89: WAREX | D89: =SUM(E89:CT89) -> 60 | Q89: 5 | R89: 3 | S89: 5 | T89: 2 | U89: 2 | V89: 2 | W89: 0 | X89: 2 | Y89: 2 | Z89: 5 | AA89: 5 | AB89: 5 | AC89: 5 | AD89: 5 | AE89: 5 | AF89: 5 | AG89: 2
C90: OPTIMUS | D90: =SUM(E90:CT90) -> 266 | M90: 2 | N90: 6 | O90: 10 | P90: 15 | Q90: 15 | R90: 15 | S90: 5 | T90: 5 | U90: 10 | V90: 10 | W90: 10 | X90: 10 | Y90: 10 | Z90: 10 | AA90: 10 | AB90: 10 | AC90: 10 | AD90: 10 | AE90: 10 | AF90: 10 | AG90: 10 | AH90: 10 | AI90: 10 | AJ90: 10 | AK90: 10 | AL90: 10 | AM90: 10 | AN90: 3
C91: MASH | D91: =SUM(E91:CT91) -> 3.5 | P91: 1 | Q91: 1 | R91: 1 | U91: 0.5
C92: MAGENTO | D92: =SUM(E92:CT92) -> 21 | P92: 1 | U92: 5 | V92: 5 | W92: 5 | X92: 5
A93: 2 | B93: Project - HT Rental | C93: ALF | D93: =SUM(E93:CT93) -> 40 | Q93: 5 | R93: 5 | T93: 4 | U93: 4 | V93: 5 | W93: 5 | X93: 5 | Y93: 5 | Z93: 2
C94: WAREX | D94: =SUM(E94:CT94) -> 20 | P94: 1 | S94: 2 | T94: 1 | U94: 3 | V94: 4 | W94: 5 | X94: 0 | Y94: 3 | Z94: 1
C95: OPTIMUS | D95: =SUM(E95:CT95) -> 30 | V95: 5 | W95: 10 | X95: 5 | Y95: 5 | Z95: 5
C96: MASH | D96: =SUM(E96:CT96) -> 0
C97: MAGENTO | D97: =SUM(E97:CT97) -> 0
A98: 3 | B98: Project - iStyle HU | C98: ALF | D98: =SUM(E98:CT98) -> 37 | N98: 5 | O98: 10 | P98: 11 | Q98: 5 | R98: 4 | S98: 2
C99: WAREX | D99: =SUM(E99:CT99) -> 17 | O99: 2 | P99: 3 | Q99: 6 | R99: 4 | S99: 2
C100: OPTIMUS | D100: =SUM(E100:CT100) -> 22 | S100: 1 | T100: 9 | U100: 5 | V100: 5 | W100: 2
...

Sheet WORKLOAD_TEAMS (4)
A1: PRIORYTET | B1: DATE | C1: DATE | D1: TOTALS | E1: =TEXT(DATE(2024,1,1)+(E2-1)*7-WEEKDAY(DATE(2024,1,1),2)+1,"dd.mm")&"-"&TEXT(DATE(2024,1,1)+(E2-1)*7-WEEKDAY(DATE(2024,1,1),2)+7,"dd.mm") -> 11.03-17.03 | F1: =TEXT(DATE(2024,1,1)+(F2-1)*7-WEEKDAY(DATE(2024,1,1),2)+1,"dd.mm")&"-"&TEXT(DATE(2024,1,1)+(F2-1)*7-WEEKDAY(DATE(2024,1,1),2)+7,"dd.mm") -> 18.03-24.03 | G1: =TEXT(DATE(2024,1,1)+(G2-1)*7-WEEKDAY(DATE(2024,1,1),2)+1,"dd.mm")&"-"&TEXT(DATE(2024,1,1)+(G2-1)*7-WEEKDAY(DATE(2024,1,1),2)+7,"dd.mm") -> 25.03-31.03 | H1: =TEXT(DATE(2024,1,1)+(H2-1)*7-WEEKDAY(DATE(2024,1,1),2)+1,"dd.mm")&"-"&TEXT(DATE(2024,1,1)+(H2-1)*7-WEEKDAY(DATE(2024,1,1),2)+7,"dd.mm") -> 01.04-07.04 | I1: =TEXT(DATE(2024,1,1)+(I2-1)*7-WEEKDAY(DATE(2024,1,1),2)+1,"dd.mm")&"-"&TEXT(DATE(2024,1,1)+(I2-1)*7-WEEKDAY(DATE(2024,1,1),2)+7,"dd.mm") -> 08.04-14.04 | J1: =TEXT(DATE(2024,1,1)+(J2-1)*7-WEEKDAY(DATE(2024,1,1),2)+1,"dd.mm")&"-"&TEXT(DATE(2024,1,1)+(J2-1)*7-WEEKDAY(DATE(2024,1,1),2)+7,"dd.mm") -> 15.04-21.04 | K1: =TEXT(DATE(2024,1,1)+(K2-1)*7-WEEKDAY(DATE(2024,1,1),2)+1,"dd.mm")&"-"&TEXT(DATE(2024,1,1)+(K2-1)*7-WEEKDAY(DATE(2024,1,1),2)+7,"dd.mm") -> 22.04-28.04 | L1: =TEXT(DATE(2024,1,1)+(L2-1)*7-WEEKDAY(DATE(2024,1,1),2)+1,"dd.mm")&"-"&TEXT(DATE(2024,1,1)+(L2-1)*7-WEEKDAY(DATE(2024,1,1),2)+7,"dd.mm") -> 29.04-05.05 | ... AT1: =TEXT(DATE(2024,1,1)+(AT2-1)*7-WEEKDAY(DATE(2024,1,1),2)+1,"dd.mm")&"-"&TEXT(DATE(2024,1,1)+(AT2-1)*7-WEEKDAY(DATE(2024,1,1),2)+7,"dd.mm") -> 23.12-29.12 | AU1: =TEXT(DATE(2025,1,1)+(AU2-1)*7-WEEKDAY(DATE(2025,1,1),2)+1,"dd.mm")&"-"&TEXT(DATE(2025,1,1)+(AU2-1)*7-WEEKDAY(DATE(2025,1,1),2)+7,"dd.mm") -> 30.12-05.01 | AV1: =TEXT(DATE(2025,1,1)+(AV2-1)*7-WEEKDAY(DATE(2025,1,1),2)+1,"dd.mm")&"-"&TEXT(DATE(2025,1,1)+(AV2-1)*7-WEEKDAY(DATE(2025,1,1),2)+7,"dd.mm") -> 06.01-12.01 | AW1: =TEXT(DATE(2025,1,1)+(AW2-1)*7-WEEKDAY(DATE(2025,1,1),2)+1,"dd.mm")&"-"&TEXT(DATE(2025,1,1)+(AW2-1)*7-WEEKDAY(DATE(2025,1,1),2)+7,"dd.mm") -> 13.01-19.01 | AX1: =TEXT(DATE(2025,1,1)+(AX2-1)*7-WEEKDAY(DATE(2025,1,1),2)+1,"dd.mm")&"-"&TEXT(DATE(2025,1,1)+(AX2-1)*7-WEEKDAY(DATE(2025,1,1),2)+7,"dd.mm") -> 20.01-26.01 | AY1: =TEXT(DATE(2025,1,1)+(AY2-1)*7-WEEKDAY(DATE(2025,1,1),2)+1,"dd.mm")&"-"&TEXT(DATE(2025,1,1)+(AY2-1)*7-WEEKDAY(DATE(2025,1,1),2)+7,"dd.mm") -> 27.01-02.02 | AZ1: =TEXT(DATE(2025,1,1)+(AZ2-1)*7-WEEKDAY(DATE(2025,1,1),2)+1,"dd.mm")&"-"&TEXT(DATE(2025,1,1)+(AZ2-1)*7-WEEKDAY(DATE(2025,1,1),2)+7,"dd.mm") -> 03.02-09.02 | BA1: =TEXT(DATE(2025,1,1)+(BA2-1)*7-WEEKDAY(DATE(2025,1,1),2)+1,"dd.mm")&"-"&TEXT(DATE(2025,1,1)+(BA2-1)*7-WEEKDAY(DATE(2025,1,1),2)+7,"dd.mm") -> 10.02-16.02 | BB1: =TEXT(DATE(2025,1,1)+(BB2-1)*7-WEEKDAY(DATE(2025,1,1),2)+1,"dd.mm")&"-"&TEXT(DATE(2025,1,1)+(BB2-1)*7-WEEKDAY(DATE(2025,1,1),2)+7,"dd.mm") -> 17.02-23.02 | ... CT1: =TEXT(DATE(2025,1,1)+(CT2-1)*7-WEEKDAY(DATE(2025,1,1),2)+1,"dd.mm")&"-"&TEXT(DATE(2025,1,1)+(CT2-1)*7-WEEKDAY(DATE(2025,1,1),2)+7,"dd.mm") -> 22.12-28.12
C2: WEEK | E2: 11 | F2: 12 | G2: 13 | H2: 14 | I2: 15 | J2: 16 | K2: 17 | L2: 18 | M2: 19 | N2: 20 | O2: 21 | P2: 22 | Q2: 23 | R2: 24 | S2: 25 | T2: 26 | U2: 27 | V2: 28 | W2: 29 | X2: 30 | Y2: 31 | Z2: 32 | AA2: 33 | AB2: 34 | AC2: 35 | AD2: 36 | AE2: 37 | AF2: 38 | AG2: 39 | AH2: 40 | AI2: 41 | AJ2: 42 | AK2: 43 | AL2: 44 | AM2: 45 | AN2: 46 | AO2: 47 | AP2: 48 | AQ2: 49 | AR2: 50 | AS2: 51 | AT2: 52 | AU2: 1 | AV2: 2 | AW2: 3 | AX2: 4 | AY2: 5 | AZ2: 6 | BA2: 7 | BB2: 8 | BC2: 9 | BD2: 10 | BE2: 11 | BF2: 12 | BG2: 13 | BH2: 14 | BI2: 15 | BJ2: 16 | BK2: 17 | BL2: 18 | BM2: 19 | BN2: 20 | BO2: 21 | BP2: 22 | BQ2: 23 | BR2: 24 | BS2: 25 | BT2: 26 | BU2: 27 | BV2: 28 | BW2: 29 | BX2: 30 | BY2: 31 | BZ2: 32 | CA2: 33 | CB2: 34 | CC2: 35 | CD2: 36 | CE2: 37 | CF2: 38 | CG2: 39 | CH2: 40 | CI2: 41 | CJ2: 42 | CK2: 43 | CL2: 44 | CM2: 45 | CN2: 46 | CO2: 47 | CP2: 48 | CQ2: 49 | CR2: 50 | CS2: 51 | CT2: 52
B3: PROJECTS & FUNCTIONALITIES CAPACITY | C3: ALF | E3: =CAPACITY!G2 -> 27.342 | F3: =OFFSET(CAPACITY!$G$2,0,7*(F$2-$E$2)) -> 27.342 | G3: =OFFSET(CAPACITY!$G$2,0,7*(G$2-$E$2)) -> 27.342 | H3: =OFFSET(CAPACITY!$G$2,0,7*(H$2-$E$2)) -> 21.462 | I3: =OFFSET(CAPACITY!$G$2,0,7*(I$2-$E$2)) -> 27.342 | J3: =OFFSET(CAPACITY!$G$2,0,7*(J$2-$E$2)) -> 27.342 | K3: =OFFSET(CAPACITY!$G$2,0,7*(K$2-$E$2)) -> 27.342 | L3: =OFFSET(CAPACITY!$G$2,0,7*(L$2-$E$2)) -> 14.028 | M3: =OFFSET(CAPACITY!$G$2,0,7*(M$2-$E$2)) -> 28.371 | ... AT3: =OFFSET(CAPACITY!$G$2,0,7*(AT$2-$E$2)) -> 12.39 | AU3: =OFFSET(CAPACITY!$G$2,0,7*(AU$2+52-$E$2)) -> 17.346 | AV3: =OFFSET(CAPACITY!$G$2,0,7*(AV$2+52-$E$2)) -> 23.247 | AW3: =OFFSET(CAPACITY!$G$2,0,7*(AW$2+52-$E$2)) -> 28.728 | AX3: =OFFSET(CAPACITY!$G$2,0,7*(AX$2+52-$E$2)) -> 28.728 | AY3: =OFFSET(CAPACITY!$G$2,0,7*(AY$2+52-$E$2)) -> 26.439 | AZ3: =OFFSET(CAPACITY!$G$2,0,7*(AZ$2+52-$E$2)) -> 28.455 | BA3: =OFFSET(CAPACITY!$G$2,0,7*(BA$2+52-$E$2)) -> 27.342 | BB3: =OFFSET(CAPACITY!$G$2,0,7*(BB$2+52-$E$2)) -> 28.581 | ... CT3: =OFFSET(CAPACITY!$G$2,0,7*(CT$2+52-$E$2)) -> 9.66
C4: WAREX | E4: =CAPACITY!G4 -> 10.388559 | F4: =OFFSET(CAPACITY!$G$4,0,7*(F$2-$E$2)) -> 10.388559 | G4: =OFFSET(CAPACITY!$G$4,0,7*(G$2-$E$2)) -> 10.388559 | H4: =OFFSET(CAPACITY!$G$4,0,7*(H$2-$E$2)) -> 8.1544599 | I4: =OFFSET(CAPACITY!$G$4,0,7*(I$2-$E$2)) -> 10.388559 | J4: =OFFSET(CAPACITY!$G$4,0,7*(J$2-$E$2)) -> 10.069402 | K4: =OFFSET(CAPACITY!$G$4,0,7*(K$2-$E$2)) -> 10.388559 | L4: =OFFSET(CAPACITY!$G$4,0,7*(L$2-$E$2)) -> 1.9149417 | M4: =OFFSET(CAPACITY!$G$4,0,7*(M$2-$E$2)) -> 9.4310877 | ... AT4: =OFFSET(CAPACITY!$G$4,0,7*(AT$2-$E$2)) -> 9.4151298 | AU4: =OFFSET(CAPACITY!$G$4,0,7*(AU$2+52-$E$2)) -> 13.181182 | AV4: =OFFSET(CAPACITY!$G$4,0,7*(AV$2+52-$E$2)) -> 17.665337 | AW4: =OFFSET(CAPACITY!$G$4,0,7*(AW$2+52-$E$2)) -> 21.830335 | AX4: =OFFSET(CAPACITY!$G$4,0,7*(AX$2+52-$E$2)) -> 21.830335 | AY4: =OFFSET(CAPACITY!$G$4,0,7*(AY$2+52-$E$2)) -> 20.09093 | AZ4: =OFFSET(CAPACITY!$G$4,0,7*(AZ$2+52-$E$2)) -> 21.622883 | BA4: =OFFSET(CAPACITY!$G$4,0,7*(BA$2+52-$E$2)) -> 20.777117 | BB4: =OFFSET(CAPACITY!$G$4,0,7*(BB$2+52-$E$2)) -> 21.71863 | ... CT4: =OFFSET(CAPACITY!$G$4,0,7*(CT$2+52-$E$2)) -> 7.3406097
C5: OPTIMUS | E5: =CAPACITY!G6 -> 21.241748 | F5: =OFFSET(CAPACITY!$G$6,0,7*(F$2-$E$2)) -> 21.241748 | G5: =OFFSET(CAPACITY!$G$6,0,7*(G$2-$E$2)) -> 21.241748 | H5: =OFFSET(CAPACITY!$G$6,0,7*(H$2-$E$2)) -> 16.67363 | I5: =OFFSET(CAPACITY!$G$6,0,7*(I$2-$E$2)) -> 21.241748 | J5: =OFFSET(CAPACITY!$G$6,0,7*(J$2-$E$2)) -> 21.241748 | K5: =OFFSET(CAPACITY!$G$6,0,7*(K$2-$E$2)) -> 21.241748 | L5: =OFFSET(CAPACITY!$G$6,0,7*(L$2-$E$2)) -> 8.995678 | M5: =OFFSET(CAPACITY!$G$6,0,7*(M$2-$E$2)) -> 18.395459 | ... AT5: =OFFSET(CAPACITY!$G$6,0,7*(AT$2-$E$2)) -> 7.9063577 | AU5: =OFFSET(CAPACITY!$G$6,0,7*(AU$2+52-$E$2)) -> 12.281209 | AV5: =OFFSET(CAPACITY!$G$6,0,7*(AV$2+52-$E$2)) -> 14.705825 | AW5: =OFFSET(CAPACITY!$G$6,0,7*(AW$2+52-$E$2)) -> 20.082148 | AX5: =OFFSET(CAPACITY!$G$6,0,7*(AX$2+52-$E$2)) -> 20.082148 | AY5: =OFFSET(CAPACITY!$G$6,0,7*(AY$2+52-$E$2)) -> 18.852271 | AZ5: =OFFSET(CAPACITY!$G$6,0,7*(AZ$2+52-$E$2)) -> 19.027967 | BA5: =OFFSET(CAPACITY!$G$6,0,7*(BA$2+52-$E$2)) -> 17.270999 | BB5: =OFFSET(CAPACITY!$G$6,0,7*(BB$2+52-$E$2)) -> 15.074789 | ... CT5: =OFFSET(CAPACITY!$G$6,0,7*(CT$2+52-$E$2)) -> 4.9195114
C6: MASH | E6: =CAPACITY!G8 -> 8.1375 | F6: =OFFSET(CAPACITY!$G$8,0,7*(F$2-$E$2)) -> 8.1375 | G6: =OFFSET(CAPACITY!$G$8,0,7*(G$2-$E$2)) -> 8.1375 | H6: =OFFSET(CAPACITY!$G$8,0,7*(H$2-$E$2)) -> 6.3875 | I6: =OFFSET(CAPACITY!$G$8,0,7*(I$2-$E$2)) -> 8.1375 | J6: =OFFSET(CAPACITY!$G$8,0,7*(J$2-$E$2)) -> 8.1375 | K6: =OFFSET(CAPACITY!$G$8,0,7*(K$2-$E$2)) -> 8.1375 | L6: =OFFSET(CAPACITY!$G$8,0,7*(L$2-$E$2)) -> 5.25 | M6: =OFFSET(CAPACITY!$G$8,0,7*(M$2-$E$2)) -> 8.1375 | ... AT6: =OFFSET(CAPACITY!$G$8,0,7*(AT$2-$E$2)) -> 2.205 | AU6: =OFFSET(CAPACITY!$G$8,0,7*(AU$2+52-$E$2)) -> 3.4825 | AV6: =OFFSET(CAPACITY!$G$8,0,7*(AV$2+52-$E$2)) -> 6.0375 | AW6: =OFFSET(CAPACITY!$G$8,0,7*(AW$2+52-$E$2)) -> 7.91 | AX6: =OFFSET(CAPACITY!$G$8,0,7*(AX$2+52-$E$2)) -> 7.21 | AY6: =OFFSET(CAPACITY!$G$8,0,7*(AY$2+52-$E$2)) -> 6.86 | AZ6: =OFFSET(CAPACITY!$G$8,0,7*(AZ$2+52-$E$2)) -> 6.7375 | BA6: =OFFSET(CAPACITY!$G$8,0,7*(BA$2+52-$E$2)) -> 6.16 | BB6: =OFFSET(CAPACITY!$G$8,0,7*(BB$2+52-$E$2)) -> 7.56 | ... CT6: =OFFSET(CAPACITY!$G$8,0,7*(CT$2+52-$E$2)) -> 3.15
C7: MAGENTO | E7: =CAPACITY!G10 -> 23.2875 | F7: =OFFSET(CAPACITY!$G$10,0,7*(F$2-$E$2)) -> 23.2875 | G7: =OFFSET(CAPACITY!$G$10,0,7*(G$2-$E$2)) -> 23.2875 | H7: =OFFSET(CAPACITY!$G$10,0,7*(H$2-$E$2)) -> 22.5375 | I7: =OFFSET(CAPACITY!$G$10,0,7*(I$2-$E$2)) -> 23.2875 | J7: =OFFSET(CAPACITY!$G$10,0,7*(J$2-$E$2)) -> 23.2875 | K7: =OFFSET(CAPACITY!$G$10,0,7*(K$2-$E$2)) -> 23.2875 | L7: =OFFSET(CAPACITY!$G$10,0,7*(L$2-$E$2)) -> 20.25 | M7: =OFFSET(CAPACITY!$G$10,0,7*(M$2-$E$2)) -> 24.1575 | ... AT7: =OFFSET(CAPACITY!$G$10,0,7*(AT$2-$E$2)) -> 12.1125 | AU7: =OFFSET(CAPACITY!$G$10,0,7*(AU$2+52-$E$2)) -> 15.6675 | AV7: =OFFSET(CAPACITY!$G$10,0,7*(AV$2+52-$E$2)) -> 19.18875 | AW7: =OFFSET(CAPACITY!$G$10,0,7*(AW$2+52-$E$2)) -> 24.1575 | AX7: =OFFSET(CAPACITY!$G$10,0,7*(AX$2+52-$E$2)) -> 24.1575 | AY7: =OFFSET(CAPACITY!$G$10,0,7*(AY$2+52-$E$2)) -> 24.1575 | AZ7: =OFFSET(CAPACITY!$G$10,0,7*(AZ$2+52-$E$2)) -> 24.1575 | BA7: =OFFSET(CAPACITY!$G$10,0,7*(BA$2+52-$E$2)) -> 24.1575 | BB7: =OFFSET(CAPACITY!$G$10,0,7*(BB$2+52-$E$2)) -> 24.1575 | ... CT7: =OFFSET(CAPACITY!$G$10,0,7*(CT$2+52-$E$2)) -> 7.5
B8: PROJECTS & FUNCTIONALITIES CAPACITY UTILISATION | C8: ALF | E8: =E3-SUMIF($C$13:$C$516,$C8,E13:E516) -> 15.342 | F8: =F3-SUMIF($C$13:$C$516,$C8,F13:F516) -> 15.342 | G8: =G3-SUMIF($C$13:$C$516,$C8,G13:G516) -> 15.342 | H8: =H3-SUMIF($C$13:$C$516,$C8,H13:H516) -> 9.462 | I8: =I3-SUMIF($C$13:$C$516,$C8,I13:I516) -> 15.342 | J8: =J3-SUMIF($C$13:$C$516,$C8,J13:J516) -> 15.342 | K8: =K3-SUMIF($C$13:$C$516,$C8,K13:K516) -> 5.342 | L8: =L3-SUMIF($C$13:$C$516,$C8,L13:L516) -> -3.972 | ... BI8: =BI3-SUMIF($C$13:$C$516,$C8,BI13:BI516) -> 18.702
C9: WAREX | E9: =E4-SUMIF($C$13:$C$516,$C9,E13:E516) -> 10.388559 | F9: =F4-SUMIF($C$13:$C$516,$C9,F13:F516) -> 10.388559 | G9: =G4-SUMIF($C$13:$C$516,$C9,G13:G516) -> 10.388559 | H9: =H4-SUMIF($C$13:$C$516,$C9,H13:H516) -> 0.15445992 | I9: =I4-SUMIF($C$13:$C$516,$C9,I13:I516) -> 2.3885585 | J9: =J4-SUMIF($C$13:$C$516,$C9,J13:J516) -> 2.0694016 | K9: =K4-SUMIF($C$13:$C$516,$C9,K13:K516) -> -3.6114415 | L9: =L4-SUMIF($C$13:$C$516,$C9,L13:L516) -> -4.0850583 | ... BI9: =BI4-SUMIF($C$13:$C$516,$C9,BI13:BI516) -> 21.330373
C10: OPTIMUS | E10: =E5-SUMIF($C$13:$C$516,$C10,E13:E516) -> 21.241748 | F10: =F5-SUMIF($C$13:$C$516,$C10,F13:F516) -> 21.241748 | G10: =G5-SUMIF($C$13:$C$516,$C10,G13:G516) -> 21.241748 | H10: =H5-SUMIF($C$13:$C$516,$C10,H13:H516) -> 16.67363 | I10: =I5-SUMIF($C$13:$C$516,$C10,I13:I516) -> 21.241748 | J10: =J5-SUMIF($C$13:$C$516,$C10,J13:J516) -> 21.241748 | K10: =K5-SUMIF($C$13:$C$516,$C10,K13:K516) -> 21.241748 | L10: =L5-SUMIF($C$13:$C$516,$C10,L13:L516) -> 8.995678 | ... BI10: =BI5-SUMIF($C$13:$C$516,$C10,BI13:BI516) -> -2.1316317
C11: MASH | E11: =E6-SUMIF($C$13:$C$516,$C11,E13:E516) -> 7.6375 | F11: =F6-SUMIF($C$13:$C$516,$C11,F13:F516) -> 7.6375 | G11: =G6-SUMIF($C$13:$C$516,$C11,G13:G516) -> 7.6375 | H11: =H6-SUMIF($C$13:$C$516,$C11,H13:H516) -> 4.8875 | I11: =I6-SUMIF($C$13:$C$516,$C11,I13:I516) -> 5.6375 | J11: =J6-SUMIF($C$13:$C$516,$C11,J13:J516) -> 3.6375 | K11: =K6-SUMIF($C$13:$C$516,$C11,K13:K516) -> 0.6375 | L11: =L6-SUMIF($C$13:$C$516,$C11,L13:L516) -> -2.25 | ... BI11: =BI6-SUMIF($C$13:$C$516,$C11,BI13:BI516) -> 7.6375
C12: MAGENTO | E12: =E7-SUMIF($C$13:$C$516,$C12,E13:E516) -> 23.2875 | F12: =F7-SUMIF($C$13:$C$516,$C12,F13:F516) -> 23.2875 | G12: =G7-SUMIF($C$13:$C$516,$C12,G13:G516) -> 23.2875 | H12: =H7-SUMIF($C$13:$C$516,$C12,H13:H516) -> 22.5375 | I12: =I7-SUMIF($C$13:$C$516,$C12,I13:I516) -> 23.2875 | J12: =J7-SUMIF($C$13:$C$516,$C12,J13:J516) -> 11.2875 | K12: =K7-SUMIF($C$13:$C$516,$C12,K13:K516) -> 0.2875 | L12: =L7-SUMIF($C$13:$C$516,$C12,L13:L516) -> 2.25 | ... BI12: =BI7-SUMIF($C$13:$C$516,$C12,BI13:BI516) -> 24.4125
B13: DŁUG FUNKCJONALNY ALF | C13: ALF | D13: =SUM(E13:CT13) -> 660 | E13: 12 | F13: 12 | G13: 12 | H13: 12 | I13: 12 | J13: 12 | K13: 12 | L13: 12 | M13: 12 | N13: 12 | O13: 12 | P13: 12 | Q13: 12 | R13: 12 | S13: 12 | T13: 12 | U13: 12 | V13: 12 | W13: 12 | X13: 12 | Y13: 12 | Z13: 12 | AA13: 12 | AB13: 12 | AC13: 12 | AD13: 12 | AE13: 12 | AF13: 12 | AG13: 12 | AH13: 12 | AI13: 12 | AJ13: 12 | AK13: 12 | AL13: 12 | AM13: 12 | AN13: 12 | AO13: 12 | AP13: 12 | AQ13: 12 | AR13: 12 | AS13: 12 | AV13: 12 | AW13: 12 | AX13: 12 | AY13: 12 | AZ13: 12 | BA13: 12 | BB13: 12 | BC13: 12 | BD13: 12 | BE13: 12 | BF13: 12 | BG13: 12 | BH13: 12 | BI13: 12
C14: WAREX | D14: =SUM(E14:CT14) -> 0
C15: OPTIMUS | D15: =SUM(E15:CT15) -> 0
C16: MASH | D16: =SUM(E16:CT16) -> 27.5 | E16: 0.5 | F16: 0.5 | G16: 0.5 | H16: 0.5 | I16: 0.5 | J16: 0.5 | K16: 0.5 | L16: 0.5 | M16: 0.5 | N16: 0.5 | O16: 0.5 | P16: 0.5 | Q16: 0.5 | R16: 0.5 | S16: 0.5 | T16: 0.5 | U16: 0.5 | V16: 0.5 | W16: 0.5 | X16: 0.5 | Y16: 0.5 | Z16: 0.5 | AA16: 0.5 | AB16: 0.5 | AC16: 0.5 | AD16: 0.5 | AE16: 0.5 | AF16: 0.5 | AG16: 0.5 | AH16: 0.5 | AI16: 0.5 | AJ16: 0.5 | AK16: 0.5 | AL16: 0.5 | AM16: 0.5 | AN16: 0.5 | AO16: 0.5 | AP16: 0.5 | AQ16: 0.5 | AR16: 0.5 | AS16: 0.5 | AV16: 0.5 | AW16: 0.5 | AX16: 0.5 | AY16: 0.5 | AZ16: 0.5 | BA16: 0.5 | BB16: 0.5 | BC16: 0.5 | BD16: 0.5 | BE16: 0.5 | BF16: 0.5 | BG16: 0.5 | BH16: 0.5 | BI16: 0.5
C17: MAGENTO | D17: =SUM(E17:CT17) -> 0
A18: 0 | B18: Project - Portal B2B 1(1.5) | C18: ALF | D18: =SUM(E18:CT18) -> 2 | K18: 2
C19: WAREX | D19: =SUM(E19:CT19) -> 0
C20: OPTIMUS | D20: =SUM(E20:CT20) -> 0
C21: MASH | D21: =SUM(E21:CT21) -> 2 | J21: 1 | M21: 1
C22: MAGENTO | D22: =SUM(E22:CT22) -> 27 | J22: 6 | K22: 3 | L22: 3 | M22: 3 | N22: 2 | R22: 5 | S22: 5
A23: 0 | B23: Project - Multibrand for iMad | C23: ALF | D23: =SUM(E23:CT23) -> 2 | K23: 2
C24: WAREX | D24: =SUM(E24:CT24) -> 0
C25: OPTIMUS | D25: =SUM(E25:CT25) -> 0
C26: MASH | D26: =SUM(E26:CT26) -> 1 | K26: 1
C27: MAGENTO | D27: =SUM(E27:CT27) -> 35 | K27: 5 | L27: 5 | M27: 5 | Q27: 5 | R27: 5 | S27: 5 | T27: 5
A28: 0 | B28: Project - Malezja Faza 1A | C28: ALF | D28: =SUM(E28:CT28) -> 8.5 | K28: 1 | L28: 1 | M28: 0.5 | O28: 1 | P28: 3 | Q28: 2
C29: WAREX | D29: =SUM(E29:CT29) -> 1 | M29: 0.5 | N29: 0.5
C30: OPTIMUS | D30: =SUM(E30:CT30) -> 8 | P30: 0.5 | Q30: 0.5 | R30: 5 | S30: 2
C31: MASH | D31: =SUM(E31:CT31) -> 25 | H31: 1 | I31: 2 | J31: 3 | K31: 3 | L31: 2 | M31: 3 | N31: 1 | P31: 0.5 | Q31: 1 | R31: 0.5 | S31: 1 | T31: 2 | U31: 1 | AB31: 2 | AC31: 2
C32: MAGENTO | D32: =SUM(E32:CT32) -> 98 | J32: 6 | K32: 15 | L32: 10 | M32: 5 | N32: 15 | O32: 15 | P32: 10 | Q32: 5 | R32: 4 | S32: 4 | T32: 3 | AD32: 3 | AE32: 3
A33: 0 | B33: MM Open Days: Faza1 - 22/05 | C33: ALF | D33: =SUM(E33:CT33) -> 25 | K33: 5 | L33: 5 | M33: 5 | N33: 5 | O33: 5
C34: WAREX | D34: =SUM(E34:CT34) -> 2 | N34: 2
C35: OPTIMUS | D35: =SUM(E35:CT35) -> 0
C36: MASH | D36: =SUM(E36:CT36) -> 15 | K36: 3 | L36: 5 | M36: 3 | N36: 2 | O36: 2
C37: MAGENTO | D37: =SUM(E37:CT37) -> 10 | N37: 5 | O37: 5
A38: 0 | B38: MM Open Days: Faza2 - 03/06 | C38: ALF | D38: =SUM(E38:CT38) -> 0
C39: WAREX | D39: =SUM(E39:CT39) -> 0
C40: OPTIMUS | D40: =SUM(E40:CT40) -> 0
C41: MASH | D41: =SUM(E41:CT41) -> 0
C42: MAGENTO | D42: =SUM(E42:CT42) -> 4 | P42: 4
A43: 0 | B43: Open Days tMobile - 23/06 + Genetal Open Days Tasks | C43: ALF | D43: =SUM(E43:CT43) -> 0
C44: WAREX | D44: =SUM(E44:CT44) -> 0
C45: OPTIMUS | D45: =SUM(E45:CT45) -> 0
C46: MASH | D46: =SUM(E46:CT46) -> 0
C47: MAGENTO | D47: =SUM(E47:CT47) -> 12 | Q47: 4 | R47: 3 | S47: 5
A48: 0 | B48: PLAY New Assortment Groups | C48: ALF | D48: =SUM(E48:CT48) -> 0
C49: WAREX | D49: =SUM(E49:CT49) -> 44 | H49: 3 | I49: 3 | J49: 3 | K49: 8 | L49: 3 | M49: 12 | N49: 8 | O49: 2 | Q49: 1 | R49: 1
C50: OPTIMUS | D50: =SUM(E50:CT50) -> 29 | P50: 5 | Q50: 10 | R50: 10 | S50: 3 | T50: 1
C51: MASH | D51: =SUM(E51:CT51) -> 0
C52: MAGENTO | D52: =SUM(E52:CT52) -> 0
A53: 0 | B53: Inicjatywa PLK karta usług (B2B Enterprise + Frontend) | C53: ALF | D53: =SUM(E53:CT53) -> 0
C54: WAREX | D54: =SUM(E54:CT54) -> 105 | H54: 5 | I54: 5 | J54: 5 | K54: 6 | L54: 3 | M54: 8 | N54: 8 | O54: 9 | P54: 9 | Q54: 4 | R54: 4 | S54: 8 | T54: 4 | U54: 5 | V54: 3 | W54: 4 | X54: 4 | Y54: 3 | Z54: 2 | AA54: 3 | AB54: 1 | AC54: 2
C55: OPTIMUS | D55: =SUM(E55:CT55) -> 25 | U55: 1 | AA55: 1 | AB55: 8 | AC55: 7 | AD55: 2 | AE55: 3 | AF55: 3
C56: MASH | D56: =SUM(E56:CT56) -> 0
C57: MAGENTO | D57: =SUM(E57:CT57) -> 0
A58: 0 | B58: JET (zmiana leasingu na najem do 27 maja) | C58: ALF | D58: =SUM(E58:CT58) -> 10 | N58: 2 | O58: 5 | Q58: 3
C59: WAREX | D59: =SUM(E59:CT59) -> 0
C60: OPTIMUS | D60: =SUM(E60:CT60) -> 0
C61: MASH | D61: =SUM(E61:CT61) -> 0
C62: MAGENTO | D62: =SUM(E62:CT62) -> 0
A63: 0 | B63: ALLPSI | C63: ALF | D63: =SUM(E63:CT63) -> 36 | N63: 2 | O63: 5 | P63: 5 | Q63: 6 | R63: 5 | S63: 4 | T63: 2 | U63: 2 | V63: 2 | W63: 3
C64: WAREX | D64: =SUM(E64:CT64) -> 0
C65: OPTIMUS | D65: =SUM(E65:CT65) -> 0
C66: MASH | D66: =SUM(E66:CT66) -> 10 | M66: 1 | N66: 3 | O66: 1 | P66: 1 | Q66: 1 | R66: 1 | S66: 1 | T66: 1
C67: MAGENTO | D67: =SUM(E67:CT67) -> 0
A68: 0 | B68: PHOX | C68: ALF | D68: =SUM(E68:CT68) -> 30 | AE68: 2 | AF68: 5 | AG68: 5 | AH68: 5 | AI68: 5 | AJ68: 5 | AK68: 3
C69: WAREX | D69: =SUM(E69:CT69) -> 31 | AE69: 2 | AF69: 3 | AG69: 5 | AH69: 5 | AI69: 1 | AJ69: 5 | AK69: 5 | AL69: 5
C70: OPTIMUS | D70: =SUM(E70:CT70) -> 20 | AK70: 5 | AL70: 5 | AM70: 5 | AN70: 5
C71: MASH | D71: =SUM(E71:CT71) -> 5 | AH71: 1 | AI71: 1 | AJ71: 1 | AK71: 1 | AL71: 1
C72: MAGENTO
A73: 0 | B73: (BIK) Antyfraud CFD | C73: ALF | D73: =SUM(E73:CT73) -> 0
C74: WAREX | D74: =SUM(E74:CT74) -> 0
C75: OPTIMUS | D75: =SUM(E75:CT75) -> 0
C76: MASH | D76: =SUM(E76:CT76) -> 22 | M76: 1 | N76: 1 | O76: 1 | P76: 0.5 | Q76: 1 | R76: 1 | S76: 3 | T76: 3 | U76: 2 | V76: 2 | W76: 2 | X76: 0.5 | Y76: 0.5 | Z76: 0.5 | AA76: 1 | AB76: 1 | AC76: 1
C77: MAGENTO | D77: =SUM(E77:CT77) -> 37 | R77: 2 | S77: 5 | T77: 3 | U77: 3 | V77: 3 | W77: 3 | X77: 5 | Y77: 5 | Z77: 2 | AA77: 2 | AB77: 2 | AC77: 2
A78: 0 | B78: Inicjatywa API PLAY | C78: ALF | D78: =SUM(E78:CT78) -> 0
C79: WAREX | D79: =SUM(E79:CT79) -> 0
C80: OPTIMUS | D80: =SUM(E80:CT80) -> 43 | T80: 1 | U80: 2 | V80: 2 | W80: 2 | X80: 2 | Y80: 5 | Z80: 10 | AA80: 3 | AB80: 5 | AC80: 5 | AD80: 3 | AE80: 3
C81: MASH | D81: =SUM(E81:CT81) -> 0
C82: MAGENTO | D82: =SUM(E82:CT82) -> 0
A83: 0 | B83: Decision Cube | C83: ALF | D83: =SUM(E83:CT83) -> 83 | U83: 5 | V83: 5 | W83: 5 | X83: 5 | Y83: 5 | Z83: 5 | AA83: 5 | AB83: 5 | AC83: 5 | AD83: 3 | AE83: 5 | AF83: 6 | AG83: 6 | AH83: 3 | AI83: 3 | AJ83: 3 | AK83: 3 | AL83: 3 | AM83: 3
C84: WAREX | D84: =SUM(E84:CT84) -> 0
C85: OPTIMUS | D85: =SUM(E85:CT85) -> 0
C86: MASH | D86: =SUM(E86:CT86) -> 0
C87: MAGENTO | D87: =SUM(E87:CT87) -> 0
A88: 0 | B88: Dynamic Pricing | C88: ALF | D88: =SUM(E88:CT88) -> 0
C89: WAREX | D89: =SUM(E89:CT89) -> 0
C90: OPTIMUS | D90: =SUM(E90:CT90) -> 0
C91: MASH | D91: =SUM(E91:CT91) -> 0
C92: MAGENTO | D92: =SUM(E92:CT92) -> 0
A93: 0 | B93: Paperless | C93: ALF | D93: =SUM(E93:CT93) -> 0
C94: WAREX | D94: =SUM(E94:CT94) -> 0
C95: OPTIMUS | D95: =SUM(E95:CT95) -> 0
C96: MASH | D96: =SUM(E96:CT96) -> 0
C97: MAGENTO | D97: =SUM(E97:CT97) -> 0
A98: 0 | B98: Risk Changes | C98: ALF | D98: =SUM(E98:CT98) -> 22 | AA98: 2 | AB98: 5 | AC98: 5 | AD98: 5 | AE98: 5
C99: WAREX | D99: =SUM(E99:CT99) -> 0
C100: OPTIMUS | D100: =SUM(E100:CT100) -> 0
...

Sheet WORKLOAD_TEAMS (3)
A1: PRIORYTET | B1: DATE | C1: DATE | D1: TOTALS | E1: =TEXT(DATE(2024,1,1)+(E2-1)*7-WEEKDAY(DATE(2024,1,1),2)+1,"dd.mm")&"-"&TEXT(DATE(2024,1,1)+(E2-1)*7-WEEKDAY(DATE(2024,1,1),2)+7,"dd.mm") -> 11.03-17.03 | F1: =TEXT(DATE(2024,1,1)+(F2-1)*7-WEEKDAY(DATE(2024,1,1),2)+1,"dd.mm")&"-"&TEXT(DATE(2024,1,1)+(F2-1)*7-WEEKDAY(DATE(2024,1,1),2)+7,"dd.mm") -> 18.03-24.03 | G1: =TEXT(DATE(2024,1,1)+(G2-1)*7-WEEKDAY(DATE(2024,1,1),2)+1,"dd.mm")&"-"&TEXT(DATE(2024,1,1)+(G2-1)*7-WEEKDAY(DATE(2024,1,1),2)+7,"dd.mm") -> 25.03-31.03 | H1: =TEXT(DATE(2024,1,1)+(H2-1)*7-WEEKDAY(DATE(2024,1,1),2)+1,"dd.mm")&"-"&TEXT(DATE(2024,1,1)+(H2-1)*7-WEEKDAY(DATE(2024,1,1),2)+7,"dd.mm") -> 01.04-07.04 | I1: =TEXT(DATE(2024,1,1)+(I2-1)*7-WEEKDAY(DATE(2024,1,1),2)+1,"dd.mm")&"-"&TEXT(DATE(2024,1,1)+(I2-1)*7-WEEKDAY(DATE(2024,1,1),2)+7,"dd.mm") -> 08.04-14.04 | J1: =TEXT(DATE(2024,1,1)+(J2-1)*7-WEEKDAY(DATE(2024,1,1),2)+1,"dd.mm")&"-"&TEXT(DATE(2024,1,1)+(J2-1)*7-WEEKDAY(DATE(2024,1,1),2)+7,"dd.mm") -> 15.04-21.04 | K1: =TEXT(DATE(2024,1,1)+(K2-1)*7-WEEKDAY(DATE(2024,1,1),2)+1,"dd.mm")&"-"&TEXT(DATE(2024,1,1)+(K2-1)*7-WEEKDAY(DATE(2024,1,1),2)+7,"dd.mm") -> 22.04-28.04 | L1: =TEXT(DATE(2024,1,1)+(L2-1)*7-WEEKDAY(DATE(2024,1,1),2)+1,"dd.mm")&"-"&TEXT(DATE(2024,1,1)+(L2-1)*7-WEEKDAY(DATE(2024,1,1),2)+7,"dd.mm") -> 29.04-05.05 | ... AT1: =TEXT(DATE(2024,1,1)+(AT2-1)*7-WEEKDAY(DATE(2024,1,1),2)+1,"dd.mm")&"-"&TEXT(DATE(2024,1,1)+(AT2-1)*7-WEEKDAY(DATE(2024,1,1),2)+7,"dd.mm") -> 23.12-29.12 | AU1: =TEXT(DATE(2025,1,1)+(AU2-1)*7-WEEKDAY(DATE(2025,1,1),2)+1,"dd.mm")&"-"&TEXT(DATE(2025,1,1)+(AU2-1)*7-WEEKDAY(DATE(2025,1,1),2)+7,"dd.mm") -> 30.12-05.01 | AV1: =TEXT(DATE(2025,1,1)+(AV2-1)*7-WEEKDAY(DATE(2025,1,1),2)+1,"dd.mm")&"-"&TEXT(DATE(2025,1,1)+(AV2-1)*7-WEEKDAY(DATE(2025,1,1),2)+7,"dd.mm") -> 06.01-12.01 | AW1: =TEXT(DATE(2025,1,1)+(AW2-1)*7-WEEKDAY(DATE(2025,1,1),2)+1,"dd.mm")&"-"&TEXT(DATE(2025,1,1)+(AW2-1)*7-WEEKDAY(DATE(2025,1,1),2)+7,"dd.mm") -> 13.01-19.01 | AX1: =TEXT(DATE(2025,1,1)+(AX2-1)*7-WEEKDAY(DATE(2025,1,1),2)+1,"dd.mm")&"-"&TEXT(DATE(2025,1,1)+(AX2-1)*7-WEEKDAY(DATE(2025,1,1),2)+7,"dd.mm") -> 20.01-26.01 | AY1: =TEXT(DATE(2025,1,1)+(AY2-1)*7-WEEKDAY(DATE(2025,1,1),2)+1,"dd.mm")&"-"&TEXT(DATE(2025,1,1)+(AY2-1)*7-WEEKDAY(DATE(2025,1,1),2)+7,"dd.mm") -> 27.01-02.02 | AZ1: =TEXT(DATE(2025,1,1)+(AZ2-1)*7-WEEKDAY(DATE(2025,1,1),2)+1,"dd.mm")&"-"&TEXT(DATE(2025,1,1)+(AZ2-1)*7-WEEKDAY(DATE(2025,1,1),2)+7,"dd.mm") -> 03.02-09.02 | BA1: =TEXT(DATE(2025,1,1)+(BA2-1)*7-WEEKDAY(DATE(2025,1,1),2)+1,"dd.mm")&"-"&TEXT(DATE(2025,1,1)+(BA2-1)*7-WEEKDAY(DATE(2025,1,1),2)+7,"dd.mm") -> 10.02-16.02 | BB1: =TEXT(DATE(2025,1,1)+(BB2-1)*7-WEEKDAY(DATE(2025,1,1),2)+1,"dd.mm")&"-"&TEXT(DATE(2025,1,1)+(BB2-1)*7-WEEKDAY(DATE(2025,1,1),2)+7,"dd.mm") -> 17.02-23.02 | ... CT1: =TEXT(DATE(2025,1,1)+(CT2-1)*7-WEEKDAY(DATE(2025,1,1),2)+1,"dd.mm")&"-"&TEXT(DATE(2025,1,1)+(CT2-1)*7-WEEKDAY(DATE(2025,1,1),2)+7,"dd.mm") -> 22.12-28.12
C2: WEEK | E2: 11 | F2: 12 | G2: 13 | H2: 14 | I2: 15 | J2: 16 | K2: 17 | L2: 18 | M2: 19 | N2: 20 | O2: 21 | P2: 22 | Q2: 23 | R2: 24 | S2: 25 | T2: 26 | U2: 27 | V2: 28 | W2: 29 | X2: 30 | Y2: 31 | Z2: 32 | AA2: 33 | AB2: 34 | AC2: 35 | AD2: 36 | AE2: 37 | AF2: 38 | AG2: 39 | AH2: 40 | AI2: 41 | AJ2: 42 | AK2: 43 | AL2: 44 | AM2: 45 | AN2: 46 | AO2: 47 | AP2: 48 | AQ2: 49 | AR2: 50 | AS2: 51 | AT2: 52 | AU2: 1 | AV2: 2 | AW2: 3 | AX2: 4 | AY2: 5 | AZ2: 6 | BA2: 7 | BB2: 8 | BC2: 9 | BD2: 10 | BE2: 11 | BF2: 12 | BG2: 13 | BH2: 14 | BI2: 15 | BJ2: 16 | BK2: 17 | BL2: 18 | BM2: 19 | BN2: 20 | BO2: 21 | BP2: 22 | BQ2: 23 | BR2: 24 | BS2: 25 | BT2: 26 | BU2: 27 | BV2: 28 | BW2: 29 | BX2: 30 | BY2: 31 | BZ2: 32 | CA2: 33 | CB2: 34 | CC2: 35 | CD2: 36 | CE2: 37 | CF2: 38 | CG2: 39 | CH2: 40 | CI2: 41 | CJ2: 42 | CK2: 43 | CL2: 44 | CM2: 45 | CN2: 46 | CO2: 47 | CP2: 48 | CQ2: 49 | CR2: 50 | CS2: 51 | CT2: 52
B3: PROJECTS & FUNCTIONALITIES CAPACITY | C3: ALF | E3: =CAPACITY!G2 -> 27.342 | F3: =OFFSET(CAPACITY!$G$2,0,7*(F$2-$E$2)) -> 27.342 | G3: =OFFSET(CAPACITY!$G$2,0,7*(G$2-$E$2)) -> 27.342 | H3: =OFFSET(CAPACITY!$G$2,0,7*(H$2-$E$2)) -> 21.462 | I3: =OFFSET(CAPACITY!$G$2,0,7*(I$2-$E$2)) -> 27.342 | J3: =OFFSET(CAPACITY!$G$2,0,7*(J$2-$E$2)) -> 27.342 | K3: =OFFSET(CAPACITY!$G$2,0,7*(K$2-$E$2)) -> 27.342 | L3: =OFFSET(CAPACITY!$G$2,0,7*(L$2-$E$2)) -> 14.028 | M3: =OFFSET(CAPACITY!$G$2,0,7*(M$2-$E$2)) -> 28.371 | ... AT3: =OFFSET(CAPACITY!$G$2,0,7*(AT$2-$E$2)) -> 12.39 | AU3: =OFFSET(CAPACITY!$G$2,0,7*(AU$2+52-$E$2)) -> 17.346 | AV3: =OFFSET(CAPACITY!$G$2,0,7*(AV$2+52-$E$2)) -> 23.247 | AW3: =OFFSET(CAPACITY!$G$2,0,7*(AW$2+52-$E$2)) -> 28.728 | AX3: =OFFSET(CAPACITY!$G$2,0,7*(AX$2+52-$E$2)) -> 28.728 | AY3: =OFFSET(CAPACITY!$G$2,0,7*(AY$2+52-$E$2)) -> 26.439 | AZ3: =OFFSET(CAPACITY!$G$2,0,7*(AZ$2+52-$E$2)) -> 28.455 | BA3: =OFFSET(CAPACITY!$G$2,0,7*(BA$2+52-$E$2)) -> 27.342 | BB3: =OFFSET(CAPACITY!$G$2,0,7*(BB$2+52-$E$2)) -> 28.581 | ... CT3: =OFFSET(CAPACITY!$G$2,0,7*(CT$2+52-$E$2)) -> 9.66
C4: WAREX | E4: =CAPACITY!G4 -> 10.388559 | F4: =OFFSET(CAPACITY!$G$4,0,7*(F$2-$E$2)) -> 10.388559 | G4: =OFFSET(CAPACITY!$G$4,0,7*(G$2-$E$2)) -> 10.388559 | H4: =OFFSET(CAPACITY!$G$4,0,7*(H$2-$E$2)) -> 8.1544599 | I4: =OFFSET(CAPACITY!$G$4,0,7*(I$2-$E$2)) -> 10.388559 | J4: =OFFSET(CAPACITY!$G$4,0,7*(J$2-$E$2)) -> 10.069402 | K4: =OFFSET(CAPACITY!$G$4,0,7*(K$2-$E$2)) -> 10.388559 | L4: =OFFSET(CAPACITY!$G$4,0,7*(L$2-$E$2)) -> 1.9149417 | M4: =OFFSET(CAPACITY!$G$4,0,7*(M$2-$E$2)) -> 9.4310877 | ... AT4: =OFFSET(CAPACITY!$G$4,0,7*(AT$2-$E$2)) -> 9.4151298 | AU4: =OFFSET(CAPACITY!$G$4,0,7*(AU$2+52-$E$2)) -> 13.181182 | AV4: =OFFSET(CAPACITY!$G$4,0,7*(AV$2+52-$E$2)) -> 17.665337 | AW4: =OFFSET(CAPACITY!$G$4,0,7*(AW$2+52-$E$2)) -> 21.830335 | AX4: =OFFSET(CAPACITY!$G$4,0,7*(AX$2+52-$E$2)) -> 21.830335 | AY4: =OFFSET(CAPACITY!$G$4,0,7*(AY$2+52-$E$2)) -> 20.09093 | AZ4: =OFFSET(CAPACITY!$G$4,0,7*(AZ$2+52-$E$2)) -> 21.622883 | BA4: =OFFSET(CAPACITY!$G$4,0,7*(BA$2+52-$E$2)) -> 20.777117 | BB4: =OFFSET(CAPACITY!$G$4,0,7*(BB$2+52-$E$2)) -> 21.71863 | ... CT4: =OFFSET(CAPACITY!$G$4,0,7*(CT$2+52-$E$2)) -> 7.3406097
C5: OPTIMUS | E5: =CAPACITY!G6 -> 21.241748 | F5: =OFFSET(CAPACITY!$G$6,0,7*(F$2-$E$2)) -> 21.241748 | G5: =OFFSET(CAPACITY!$G$6,0,7*(G$2-$E$2)) -> 21.241748 | H5: =OFFSET(CAPACITY!$G$6,0,7*(H$2-$E$2)) -> 16.67363 | I5: =OFFSET(CAPACITY!$G$6,0,7*(I$2-$E$2)) -> 21.241748 | J5: =OFFSET(CAPACITY!$G$6,0,7*(J$2-$E$2)) -> 21.241748 | K5: =OFFSET(CAPACITY!$G$6,0,7*(K$2-$E$2)) -> 21.241748 | L5: =OFFSET(CAPACITY!$G$6,0,7*(L$2-$E$2)) -> 8.995678 | M5: =OFFSET(CAPACITY!$G$6,0,7*(M$2-$E$2)) -> 18.395459 | ... AT5: =OFFSET(CAPACITY!$G$6,0,7*(AT$2-$E$2)) -> 7.9063577 | AU5: =OFFSET(CAPACITY!$G$6,0,7*(AU$2+52-$E$2)) -> 12.281209 | AV5: =OFFSET(CAPACITY!$G$6,0,7*(AV$2+52-$E$2)) -> 14.705825 | AW5: =OFFSET(CAPACITY!$G$6,0,7*(AW$2+52-$E$2)) -> 20.082148 | AX5: =OFFSET(CAPACITY!$G$6,0,7*(AX$2+52-$E$2)) -> 20.082148 | AY5: =OFFSET(CAPACITY!$G$6,0,7*(AY$2+52-$E$2)) -> 18.852271 | AZ5: =OFFSET(CAPACITY!$G$6,0,7*(AZ$2+52-$E$2)) -> 19.027967 | BA5: =OFFSET(CAPACITY!$G$6,0,7*(BA$2+52-$E$2)) -> 17.270999 | BB5: =OFFSET(CAPACITY!$G$6,0,7*(BB$2+52-$E$2)) -> 15.074789 | ... CT5: =OFFSET(CAPACITY!$G$6,0,7*(CT$2+52-$E$2)) -> 4.9195114
C6: MASH | E6: =CAPACITY!G8 -> 8.1375 | F6: =OFFSET(CAPACITY!$G$8,0,7*(F$2-$E$2)) -> 8.1375 | G6: =OFFSET(CAPACITY!$G$8,0,7*(G$2-$E$2)) -> 8.1375 | H6: =OFFSET(CAPACITY!$G$8,0,7*(H$2-$E$2)) -> 6.3875 | I6: =OFFSET(CAPACITY!$G$8,0,7*(I$2-$E$2)) -> 8.1375 | J6: =OFFSET(CAPACITY!$G$8,0,7*(J$2-$E$2)) -> 8.1375 | K6: =OFFSET(CAPACITY!$G$8,0,7*(K$2-$E$2)) -> 8.1375 | L6: =OFFSET(CAPACITY!$G$8,0,7*(L$2-$E$2)) -> 5.25 | M6: =OFFSET(CAPACITY!$G$8,0,7*(M$2-$E$2)) -> 8.1375 | ... AT6: =OFFSET(CAPACITY!$G$8,0,7*(AT$2-$E$2)) -> 2.205 | AU6: =OFFSET(CAPACITY!$G$8,0,7*(AU$2+52-$E$2)) -> 3.4825 | AV6: =OFFSET(CAPACITY!$G$8,0,7*(AV$2+52-$E$2)) -> 6.0375 | AW6: =OFFSET(CAPACITY!$G$8,0,7*(AW$2+52-$E$2)) -> 7.91 | AX6: =OFFSET(CAPACITY!$G$8,0,7*(AX$2+52-$E$2)) -> 7.21 | AY6: =OFFSET(CAPACITY!$G$8,0,7*(AY$2+52-$E$2)) -> 6.86 | AZ6: =OFFSET(CAPACITY!$G$8,0,7*(AZ$2+52-$E$2)) -> 6.7375 | BA6: =OFFSET(CAPACITY!$G$8,0,7*(BA$2+52-$E$2)) -> 6.16 | BB6: =OFFSET(CAPACITY!$G$8,0,7*(BB$2+52-$E$2)) -> 7.56 | ... CT6: =OFFSET(CAPACITY!$G$8,0,7*(CT$2+52-$E$2)) -> 3.15
C7: MAGENTO | E7: =CAPACITY!G10 -> 23.2875 | F7: =OFFSET(CAPACITY!$G$10,0,7*(F$2-$E$2)) -> 23.2875 | G7: =OFFSET(CAPACITY!$G$10,0,7*(G$2-$E$2)) -> 23.2875 | H7: =OFFSET(CAPACITY!$G$10,0,7*(H$2-$E$2)) -> 22.5375 | I7: =OFFSET(CAPACITY!$G$10,0,7*(I$2-$E$2)) -> 23.2875 | J7: =OFFSET(CAPACITY!$G$10,0,7*(J$2-$E$2)) -> 23.2875 | K7: =OFFSET(CAPACITY!$G$10,0,7*(K$2-$E$2)) -> 23.2875 | L7: =OFFSET(CAPACITY!$G$10,0,7*(L$2-$E$2)) -> 20.25 | M7: =OFFSET(CAPACITY!$G$10,0,7*(M$2-$E$2)) -> 24.1575 | ... AT7: =OFFSET(CAPACITY!$G$10,0,7*(AT$2-$E$2)) -> 12.1125 | AU7: =OFFSET(CAPACITY!$G$10,0,7*(AU$2+52-$E$2)) -> 15.6675 | AV7: =OFFSET(CAPACITY!$G$10,0,7*(AV$2+52-$E$2)) -> 19.18875 | AW7: =OFFSET(CAPACITY!$G$10,0,7*(AW$2+52-$E$2)) -> 24.1575 | AX7: =OFFSET(CAPACITY!$G$10,0,7*(AX$2+52-$E$2)) -> 24.1575 | AY7: =OFFSET(CAPACITY!$G$10,0,7*(AY$2+52-$E$2)) -> 24.1575 | AZ7: =OFFSET(CAPACITY!$G$10,0,7*(AZ$2+52-$E$2)) -> 24.1575 | BA7: =OFFSET(CAPACITY!$G$10,0,7*(BA$2+52-$E$2)) -> 24.1575 | BB7: =OFFSET(CAPACITY!$G$10,0,7*(BB$2+52-$E$2)) -> 24.1575 | ... CT7: =OFFSET(CAPACITY!$G$10,0,7*(CT$2+52-$E$2)) -> 7.5
B8: PROJECTS & FUNCTIONALITIES CAPACITY UTILISATION | C8: ALF | E8: =E3-SUMIF($C$13:$C$516,$C8,E13:E516) -> 15.342 | F8: =F3-SUMIF($C$13:$C$516,$C8,F13:F516) -> 15.342 | G8: =G3-SUMIF($C$13:$C$516,$C8,G13:G516) -> 15.342 | H8: =H3-SUMIF($C$13:$C$516,$C8,H13:H516) -> 9.462 | I8: =I3-SUMIF($C$13:$C$516,$C8,I13:I516) -> 15.342 | J8: =J3-SUMIF($C$13:$C$516,$C8,J13:J516) -> 15.342 | K8: =K3-SUMIF($C$13:$C$516,$C8,K13:K516) -> 5.342 | L8: =L3-SUMIF($C$13:$C$516,$C8,L13:L516) -> -3.972 | ... BI8: =BI3-SUMIF($C$13:$C$516,$C8,BI13:BI516) -> 18.702
C9: WAREX | E9: =E4-SUMIF($C$13:$C$516,$C9,E13:E516) -> 10.388559 | F9: =F4-SUMIF($C$13:$C$516,$C9,F13:F516) -> 10.388559 | G9: =G4-SUMIF($C$13:$C$516,$C9,G13:G516) -> 10.388559 | H9: =H4-SUMIF($C$13:$C$516,$C9,H13:H516) -> 0.15445992 | I9: =I4-SUMIF($C$13:$C$516,$C9,I13:I516) -> 2.3885585 | J9: =J4-SUMIF($C$13:$C$516,$C9,J13:J516) -> 2.0694016 | K9: =K4-SUMIF($C$13:$C$516,$C9,K13:K516) -> -3.6114415 | L9: =L4-SUMIF($C$13:$C$516,$C9,L13:L516) -> -4.0850583 | ... BI9: =BI4-SUMIF($C$13:$C$516,$C9,BI13:BI516) -> 23.330373
C10: OPTIMUS | E10: =E5-SUMIF($C$13:$C$516,$C10,E13:E516) -> 21.241748 | F10: =F5-SUMIF($C$13:$C$516,$C10,F13:F516) -> 21.241748 | G10: =G5-SUMIF($C$13:$C$516,$C10,G13:G516) -> 21.241748 | H10: =H5-SUMIF($C$13:$C$516,$C10,H13:H516) -> 16.67363 | I10: =I5-SUMIF($C$13:$C$516,$C10,I13:I516) -> 21.241748 | J10: =J5-SUMIF($C$13:$C$516,$C10,J13:J516) -> 21.241748 | K10: =K5-SUMIF($C$13:$C$516,$C10,K13:K516) -> 21.241748 | L10: =L5-SUMIF($C$13:$C$516,$C10,L13:L516) -> 8.995678 | ... BI10: =BI5-SUMIF($C$13:$C$516,$C10,BI13:BI516) -> 17.868368
C11: MASH | E11: =E6-SUMIF($C$13:$C$516,$C11,E13:E516) -> 7.6375 | F11: =F6-SUMIF($C$13:$C$516,$C11,F13:F516) -> 7.6375 | G11: =G6-SUMIF($C$13:$C$516,$C11,G13:G516) -> 7.6375 | H11: =H6-SUMIF($C$13:$C$516,$C11,H13:H516) -> 4.8875 | I11: =I6-SUMIF($C$13:$C$516,$C11,I13:I516) -> 5.6375 | J11: =J6-SUMIF($C$13:$C$516,$C11,J13:J516) -> 3.6375 | K11: =K6-SUMIF($C$13:$C$516,$C11,K13:K516) -> 0.6375 | L11: =L6-SUMIF($C$13:$C$516,$C11,L13:L516) -> -2.25 | ... BI11: =BI6-SUMIF($C$13:$C$516,$C11,BI13:BI516) -> 7.6375
C12: MAGENTO | E12: =E7-SUMIF($C$13:$C$516,$C12,E13:E516) -> 23.2875 | F12: =F7-SUMIF($C$13:$C$516,$C12,F13:F516) -> 23.2875 | G12: =G7-SUMIF($C$13:$C$516,$C12,G13:G516) -> 23.2875 | H12: =H7-SUMIF($C$13:$C$516,$C12,H13:H516) -> 22.5375 | I12: =I7-SUMIF($C$13:$C$516,$C12,I13:I516) -> 23.2875 | J12: =J7-SUMIF($C$13:$C$516,$C12,J13:J516) -> 11.2875 | K12: =K7-SUMIF($C$13:$C$516,$C12,K13:K516) -> 0.2875 | L12: =L7-SUMIF($C$13:$C$516,$C12,L13:L516) -> 2.25 | ... BI12: =BI7-SUMIF($C$13:$C$516,$C12,BI13:BI516) -> 24.4125
B13: DŁUG FUNKCJONALNY ALF | C13: ALF | D13: =SUM(E13:CT13) -> 660 | E13: 12 | F13: 12 | G13: 12 | H13: 12 | I13: 12 | J13: 12 | K13: 12 | L13: 12 | M13: 12 | N13: 12 | O13: 12 | P13: 12 | Q13: 12 | R13: 12 | S13: 12 | T13: 12 | U13: 12 | V13: 12 | W13: 12 | X13: 12 | Y13: 12 | Z13: 12 | AA13: 12 | AB13: 12 | AC13: 12 | AD13: 12 | AE13: 12 | AF13: 12 | AG13: 12 | AH13: 12 | AI13: 12 | AJ13: 12 | AK13: 12 | AL13: 12 | AM13: 12 | AN13: 12 | AO13: 12 | AP13: 12 | AQ13: 12 | AR13: 12 | AS13: 12 | AV13: 12 | AW13: 12 | AX13: 12 | AY13: 12 | AZ13: 12 | BA13: 12 | BB13: 12 | BC13: 12 | BD13: 12 | BE13: 12 | BF13: 12 | BG13: 12 | BH13: 12 | BI13: 12
C14: WAREX | D14: =SUM(E14:CT14) -> 0
C15: OPTIMUS | D15: =SUM(E15:CT15) -> 0
C16: MASH | D16: =SUM(E16:CT16) -> 27.5 | E16: 0.5 | F16: 0.5 | G16: 0.5 | H16: 0.5 | I16: 0.5 | J16: 0.5 | K16: 0.5 | L16: 0.5 | M16: 0.5 | N16: 0.5 | O16: 0.5 | P16: 0.5 | Q16: 0.5 | R16: 0.5 | S16: 0.5 | T16: 0.5 | U16: 0.5 | V16: 0.5 | W16: 0.5 | X16: 0.5 | Y16: 0.5 | Z16: 0.5 | AA16: 0.5 | AB16: 0.5 | AC16: 0.5 | AD16: 0.5 | AE16: 0.5 | AF16: 0.5 | AG16: 0.5 | AH16: 0.5 | AI16: 0.5 | AJ16: 0.5 | AK16: 0.5 | AL16: 0.5 | AM16: 0.5 | AN16: 0.5 | AO16: 0.5 | AP16: 0.5 | AQ16: 0.5 | AR16: 0.5 | AS16: 0.5 | AV16: 0.5 | AW16: 0.5 | AX16: 0.5 | AY16: 0.5 | AZ16: 0.5 | BA16: 0.5 | BB16: 0.5 | BC16: 0.5 | BD16: 0.5 | BE16: 0.5 | BF16: 0.5 | BG16: 0.5 | BH16: 0.5 | BI16: 0.5
C17: MAGENTO | D17: =SUM(E17:CT17) -> 0
A18: 0 | B18: Project - Portal B2B 1(1.5) | C18: ALF | D18: =SUM(E18:CT18) -> 2 | K18: 2
C19: WAREX | D19: =SUM(E19:CT19) -> 0
C20: OPTIMUS | D20: =SUM(E20:CT20) -> 0
C21: MASH | D21: =SUM(E21:CT21) -> 2 | J21: 1 | M21: 1
C22: MAGENTO | D22: =SUM(E22:CT22) -> 27 | J22: 6 | K22: 3 | L22: 3 | M22: 3 | N22: 2 | R22: 5 | S22: 5
A23: 0 | B23: Project - Multibrand for iMad | C23: ALF | D23: =SUM(E23:CT23) -> 2 | K23: 2
C24: WAREX | D24: =SUM(E24:CT24) -> 0
C25: OPTIMUS | D25: =SUM(E25:CT25) -> 0
C26: MASH | D26: =SUM(E26:CT26) -> 1 | K26: 1
C27: MAGENTO | D27: =SUM(E27:CT27) -> 35 | K27: 5 | L27: 5 | M27: 5 | Q27: 5 | R27: 5 | S27: 5 | T27: 5
A28: 0 | B28: Project - Malezja Faza 1A | C28: ALF | D28: =SUM(E28:CT28) -> 8.5 | K28: 1 | L28: 1 | M28: 0.5 | O28: 1 | P28: 3 | Q28: 2
C29: WAREX | D29: =SUM(E29:CT29) -> 1 | M29: 0.5 | N29: 0.5
C30: OPTIMUS | D30: =SUM(E30:CT30) -> 8 | P30: 0.5 | Q30: 0.5 | R30: 5 | S30: 2
C31: MASH | D31: =SUM(E31:CT31) -> 25 | H31: 1 | I31: 2 | J31: 3 | K31: 3 | L31: 2 | M31: 3 | N31: 1 | P31: 0.5 | Q31: 1 | R31: 0.5 | S31: 1 | T31: 2 | U31: 1 | AB31: 2 | AC31: 2
C32: MAGENTO | D32: =SUM(E32:CT32) -> 98 | J32: 6 | K32: 15 | L32: 10 | M32: 5 | N32: 15 | O32: 15 | P32: 10 | Q32: 5 | R32: 4 | S32: 4 | T32: 3 | AD32: 3 | AE32: 3
A33: 0 | B33: MM Open Days: Faza1 - 22/05 | C33: ALF | D33: =SUM(E33:CT33) -> 25 | K33: 5 | L33: 5 | M33: 5 | N33: 5 | O33: 5
C34: WAREX | D34: =SUM(E34:CT34) -> 2 | N34: 2
C35: OPTIMUS | D35: =SUM(E35:CT35) -> 0
C36: MASH | D36: =SUM(E36:CT36) -> 15 | K36: 3 | L36: 5 | M36: 3 | N36: 2 | O36: 2
C37: MAGENTO | D37: =SUM(E37:CT37) -> 10 | N37: 5 | O37: 5
A38: 0 | B38: MM Open Days: Faza2 - 03/06 | C38: ALF | D38: =SUM(E38:CT38) -> 0
C39: WAREX | D39: =SUM(E39:CT39) -> 0
C40: OPTIMUS | D40: =SUM(E40:CT40) -> 0
C41: MASH | D41: =SUM(E41:CT41) -> 0
C42: MAGENTO | D42: =SUM(E42:CT42) -> 4 | P42: 4
A43: 0 | B43: Open Days tMobile - 23/06 + Genetal Open Days Tasks | C43: ALF | D43: =SUM(E43:CT43) -> 0
C44: WAREX | D44: =SUM(E44:CT44) -> 0
C45: OPTIMUS | D45: =SUM(E45:CT45) -> 0
C46: MASH | D46: =SUM(E46:CT46) -> 0
C47: MAGENTO | D47: =SUM(E47:CT47) -> 12 | Q47: 4 | R47: 3 | S47: 5
A48: 0 | B48: PLAY New Assortment Groups | C48: ALF | D48: =SUM(E48:CT48) -> 0
C49: WAREX | D49: =SUM(E49:CT49) -> 44 | H49: 3 | I49: 3 | J49: 3 | K49: 8 | L49: 3 | M49: 12 | N49: 8 | O49: 2 | Q49: 1 | R49: 1
C50: OPTIMUS | D50: =SUM(E50:CT50) -> 29 | P50: 5 | Q50: 10 | R50: 10 | S50: 3 | T50: 1
C51: MASH | D51: =SUM(E51:CT51) -> 0
C52: MAGENTO | D52: =SUM(E52:CT52) -> 0
A53: 0 | B53: Inicjatywa PLK karta usług (B2B Enterprise + Frontend) | C53: ALF | D53: =SUM(E53:CT53) -> 0
C54: WAREX | D54: =SUM(E54:CT54) -> 105 | H54: 5 | I54: 5 | J54: 5 | K54: 6 | L54: 3 | M54: 8 | N54: 8 | O54: 9 | P54: 9 | Q54: 4 | R54: 4 | S54: 8 | T54: 4 | U54: 5 | V54: 3 | W54: 4 | X54: 4 | Y54: 3 | Z54: 2 | AA54: 3 | AB54: 1 | AC54: 2
C55: OPTIMUS | D55: =SUM(E55:CT55) -> 25 | U55: 1 | AA55: 1 | AB55: 8 | AC55: 7 | AD55: 2 | AE55: 3 | AF55: 3
C56: MASH | D56: =SUM(E56:CT56) -> 0
C57: MAGENTO | D57: =SUM(E57:CT57) -> 0
A58: 0 | B58: JET (zmiana leasingu na najem do 27 maja) | C58: ALF | D58: =SUM(E58:CT58) -> 10 | N58: 2 | O58: 5 | Q58: 3
C59: WAREX | D59: =SUM(E59:CT59) -> 0
C60: OPTIMUS | D60: =SUM(E60:CT60) -> 0
C61: MASH | D61: =SUM(E61:CT61) -> 0
C62: MAGENTO | D62: =SUM(E62:CT62) -> 0
A63: 0 | B63: ALLPSI | C63: ALF | D63: =SUM(E63:CT63) -> 36 | N63: 2 | O63: 5 | P63: 5 | Q63: 6 | R63: 5 | S63: 4 | T63: 2 | U63: 2 | V63: 2 | W63: 3
C64: WAREX | D64: =SUM(E64:CT64) -> 0
C65: OPTIMUS | D65: =SUM(E65:CT65) -> 0
C66: MASH | D66: =SUM(E66:CT66) -> 10 | M66: 1 | N66: 3 | O66: 1 | P66: 1 | Q66: 1 | R66: 1 | S66: 1 | T66: 1
C67: MAGENTO | D67: =SUM(E67:CT67) -> 0
A68: 0 | B68: PHOX | C68: ALF | D68: =SUM(E68:CT68) -> 30 | AE68: 2 | AF68: 5 | AG68: 5 | AH68: 5 | AI68: 5 | AJ68: 5 | AK68: 3
C69: WAREX | D69: =SUM(E69:CT69) -> 31 | AE69: 2 | AF69: 3 | AG69: 5 | AH69: 5 | AI69: 1 | AJ69: 5 | AK69: 5 | AL69: 5
C70: OPTIMUS | D70: =SUM(E70:CT70) -> 20 | AK70: 5 | AL70: 5 | AM70: 5 | AN70: 5
C71: MASH | D71: =SUM(E71:CT71) -> 5 | AH71: 1 | AI71: 1 | AJ71: 1 | AK71: 1 | AL71: 1
C72: MAGENTO
A73: 0 | B73: (BIK) Antyfraud CFD | C73: ALF | D73: =SUM(E73:CT73) -> 0
C74: WAREX | D74: =SUM(E74:CT74) -> 0
C75: OPTIMUS | D75: =SUM(E75:CT75) -> 0
C76: MASH | D76: =SUM(E76:CT76) -> 22 | M76: 1 | N76: 1 | O76: 1 | P76: 0.5 | Q76: 1 | R76: 1 | S76: 3 | T76: 3 | U76: 2 | V76: 2 | W76: 2 | X76: 0.5 | Y76: 0.5 | Z76: 0.5 | AA76: 1 | AB76: 1 | AC76: 1
C77: MAGENTO | D77: =SUM(E77:CT77) -> 37 | R77: 2 | S77: 5 | T77: 3 | U77: 3 | V77: 3 | W77: 3 | X77: 5 | Y77: 5 | Z77: 2 | AA77: 2 | AB77: 2 | AC77: 2
A78: 0 | B78: Inicjatywa API PLAY | C78: ALF | D78: =SUM(E78:CT78) -> 0
C79: WAREX | D79: =SUM(E79:CT79) -> 0
C80: OPTIMUS | D80: =SUM(E80:CT80) -> 43 | T80: 1 | U80: 2 | V80: 2 | W80: 2 | X80: 2 | Y80: 5 | Z80: 10 | AA80: 3 | AB80: 5 | AC80: 5 | AD80: 3 | AE80: 3
C81: MASH | D81: =SUM(E81:CT81) -> 0
C82: MAGENTO | D82: =SUM(E82:CT82) -> 0
A83: 0 | B83: Decision Cube | C83: ALF | D83: =SUM(E83:CT83) -> 83 | U83: 5 | V83: 5 | W83: 5 | X83: 5 | Y83: 5 | Z83: 5 | AA83: 5 | AB83: 5 | AC83: 5 | AD83: 3 | AE83: 5 | AF83: 6 | AG83: 6 | AH83: 3 | AI83: 3 | AJ83: 3 | AK83: 3 | AL83: 3 | AM83: 3
C84: WAREX | D84: =SUM(E84:CT84) -> 0
C85: OPTIMUS | D85: =SUM(E85:CT85) -> 0
C86: MASH | D86: =SUM(E86:CT86) -> 0
C87: MAGENTO | D87: =SUM(E87:CT87) -> 0
A88: 0 | B88: Dynamic Pricing | C88: ALF | D88: =SUM(E88:CT88) -> 0
C89: WAREX | D89: =SUM(E89:CT89) -> 0
C90: OPTIMUS | D90: =SUM(E90:CT90) -> 0
C91: MASH | D91: =SUM(E91:CT91) -> 0
C92: MAGENTO | D92: =SUM(E92:CT92) -> 0
A93: 0 | B93: Paperless | C93: ALF | D93: =SUM(E93:CT93) -> 0
C94: WAREX | D94: =SUM(E94:CT94) -> 0
C95: OPTIMUS | D95: =SUM(E95:CT95) -> 0
C96: MASH | D96: =SUM(E96:CT96) -> 0
C97: MAGENTO | D97: =SUM(E97:CT97) -> 0
A98: 0 | B98: Risk Changes | C98: ALF | D98: =SUM(E98:CT98) -> 22 | AA98: 2 | AB98: 5 | AC98: 5 | AD98: 5 | AE98: 5
C99: WAREX | D99: =SUM(E99:CT99) -> 0
C100: OPTIMUS | D100: =SUM(E100:CT100) -> 0
...

Sheet WORKLOAD_TEAMS (5)
A1: PRIORYTET | B1: DATE | C1: DATE | D1: TOTALS | E1: =TEXT(DATE(2024,1,1)+(E2-1)*7-WEEKDAY(DATE(2024,1,1),2)+1,"dd.mm")&"-"&TEXT(DATE(2024,1,1)+(E2-1)*7-WEEKDAY(DATE(2024,1,1),2)+7,"dd.mm") -> 11.03-17.03 | F1: =TEXT(DATE(2024,1,1)+(F2-1)*7-WEEKDAY(DATE(2024,1,1),2)+1,"dd.mm")&"-"&TEXT(DATE(2024,1,1)+(F2-1)*7-WEEKDAY(DATE(2024,1,1),2)+7,"dd.mm") -> 18.03-24.03 | G1: =TEXT(DATE(2024,1,1)+(G2-1)*7-WEEKDAY(DATE(2024,1,1),2)+1,"dd.mm")&"-"&TEXT(DATE(2024,1,1)+(G2-1)*7-WEEKDAY(DATE(2024,1,1),2)+7,"dd.mm") -> 25.03-31.03 | H1: =TEXT(DATE(2024,1,1)+(H2-1)*7-WEEKDAY(DATE(2024,1,1),2)+1,"dd.mm")&"-"&TEXT(DATE(2024,1,1)+(H2-1)*7-WEEKDAY(DATE(2024,1,1),2)+7,"dd.mm") -> 01.04-07.04 | I1: =TEXT(DATE(2024,1,1)+(I2-1)*7-WEEKDAY(DATE(2024,1,1),2)+1,"dd.mm")&"-"&TEXT(DATE(2024,1,1)+(I2-1)*7-WEEKDAY(DATE(2024,1,1),2)+7,"dd.mm") -> 08.04-14.04 | J1: =TEXT(DATE(2024,1,1)+(J2-1)*7-WEEKDAY(DATE(2024,1,1),2)+1,"dd.mm")&"-"&TEXT(DATE(2024,1,1)+(J2-1)*7-WEEKDAY(DATE(2024,1,1),2)+7,"dd.mm") -> 15.04-21.04 | K1: =TEXT(DATE(2024,1,1)+(K2-1)*7-WEEKDAY(DATE(2024,1,1),2)+1,"dd.mm")&"-"&TEXT(DATE(2024,1,1)+(K2-1)*7-WEEKDAY(DATE(2024,1,1),2)+7,"dd.mm") -> 22.04-28.04 | L1: =TEXT(DATE(2024,1,1)+(L2-1)*7-WEEKDAY(DATE(2024,1,1),2)+1,"dd.mm")&"-"&TEXT(DATE(2024,1,1)+(L2-1)*7-WEEKDAY(DATE(2024,1,1),2)+7,"dd.mm") -> 29.04-05.05 | ... AT1: =TEXT(DATE(2024,1,1)+(AT2-1)*7-WEEKDAY(DATE(2024,1,1),2)+1,"dd.mm")&"-"&TEXT(DATE(2024,1,1)+(AT2-1)*7-WEEKDAY(DATE(2024,1,1),2)+7,"dd.mm") -> 23.12-29.12 | AU1: =TEXT(DATE(2025,1,1)+(AU2-1)*7-WEEKDAY(DATE(2025,1,1),2)+1,"dd.mm")&"-"&TEXT(DATE(2025,1,1)+(AU2-1)*7-WEEKDAY(DATE(2025,1,1),2)+7,"dd.mm") -> 30.12-05.01 | AV1: =TEXT(DATE(2025,1,1)+(AV2-1)*7-WEEKDAY(DATE(2025,1,1),2)+1,"dd.mm")&"-"&TEXT(DATE(2025,1,1)+(AV2-1)*7-WEEKDAY(DATE(2025,1,1),2)+7,"dd.mm") -> 06.01-12.01 | AW1: =TEXT(DATE(2025,1,1)+(AW2-1)*7-WEEKDAY(DATE(2025,1,1),2)+1,"dd.mm")&"-"&TEXT(DATE(2025,1,1)+(AW2-1)*7-WEEKDAY(DATE(2025,1,1),2)+7,"dd.mm") -> 13.01-19.01 | AX1: =TEXT(DATE(2025,1,1)+(AX2-1)*7-WEEKDAY(DATE(2025,1,1),2)+1,"dd.mm")&"-"&TEXT(DATE(2025,1,1)+(AX2-1)*7-WEEKDAY(DATE(2025,1,1),2)+7,"dd.mm") -> 20.01-26.01 | AY1: =TEXT(DATE(2025,1,1)+(AY2-1)*7-WEEKDAY(DATE(2025,1,1),2)+1,"dd.mm")&"-"&TEXT(DATE(2025,1,1)+(AY2-1)*7-WEEKDAY(DATE(2025,1,1),2)+7,"dd.mm") -> 27.01-02.02 | AZ1: =TEXT(DATE(2025,1,1)+(AZ2-1)*7-WEEKDAY(DATE(2025,1,1),2)+1,"dd.mm")&"-"&TEXT(DATE(2025,1,1)+(AZ2-1)*7-WEEKDAY(DATE(2025,1,1),2)+7,"dd.mm") -> 03.02-09.02 | BA1: =TEXT(DATE(2025,1,1)+(BA2-1)*7-WEEKDAY(DATE(2025,1,1),2)+1,"dd.mm")&"-"&TEXT(DATE(2025,1,1)+(BA2-1)*7-WEEKDAY(DATE(2025,1,1),2)+7,"dd.mm") -> 10.02-16.02 | BB1: =TEXT(DATE(2025,1,1)+(BB2-1)*7-WEEKDAY(DATE(2025,1,1),2)+1,"dd.mm")&"-"&TEXT(DATE(2025,1,1)+(BB2-1)*7-WEEKDAY(DATE(2025,1,1),2)+7,"dd.mm") -> 17.02-23.02 | ... CT1: =TEXT(DATE(2025,1,1)+(CT2-1)*7-WEEKDAY(DATE(2025,1,1),2)+1,"dd.mm")&"-"&TEXT(DATE(2025,1,1)+(CT2-1)*7-WEEKDAY(DATE(2025,1,1),2)+7,"dd.mm") -> 22.12-28.12
C2: WEEK | E2: 11 | F2: 12 | G2: 13 | H2: 14 | I2: 15 | J2: 16 | K2: 17 | L2: 18 | M2: 19 | N2: 20 | O2: 21 | P2: 22 | Q2: 23 | R2: 24 | S2: 25 | T2: 26 | U2: 27 | V2: 28 | W2: 29 | X2: 30 | Y2: 31 | Z2: 32 | AA2: 33 | AB2: 34 | AC2: 35 | AD2: 36 | AE2: 37 | AF2: 38 | AG2: 39 | AH2: 40 | AI2: 41 | AJ2: 42 | AK2: 43 | AL2: 44 | AM2: 45 | AN2: 46 | AO2: 47 | AP2: 48 | AQ2: 49 | AR2: 50 | AS2: 51 | AT2: 52 | AU2: 1 | AV2: 2 | AW2: 3 | AX2: 4 | AY2: 5 | AZ2: 6 | BA2: 7 | BB2: 8 | BC2: 9 | BD2: 10 | BE2: 11 | BF2: 12 | BG2: 13 | BH2: 14 | BI2: 15 | BJ2: 16 | BK2: 17 | BL2: 18 | BM2: 19 | BN2: 20 | BO2: 21 | BP2: 22 | BQ2: 23 | BR2: 24 | BS2: 25 | BT2: 26 | BU2: 27 | BV2: 28 | BW2: 29 | BX2: 30 | BY2: 31 | BZ2: 32 | CA2: 33 | CB2: 34 | CC2: 35 | CD2: 36 | CE2: 37 | CF2: 38 | CG2: 39 | CH2: 40 | CI2: 41 | CJ2: 42 | CK2: 43 | CL2: 44 | CM2: 45 | CN2: 46 | CO2: 47 | CP2: 48 | CQ2: 49 | CR2: 50 | CS2: 51 | CT2: 52
B3: PROJECTS & FUNCTIONALITIES CAPACITY | C3: ALF | E3: =CAPACITY!G2 -> 27.342 | F3: =OFFSET(CAPACITY!$G$2,0,7*(F$2-$E$2)) -> 27.342 | G3: =OFFSET(CAPACITY!$G$2,0,7*(G$2-$E$2)) -> 27.342 | H3: =OFFSET(CAPACITY!$G$2,0,7*(H$2-$E$2)) -> 21.462 | I3: =OFFSET(CAPACITY!$G$2,0,7*(I$2-$E$2)) -> 27.342 | J3: =OFFSET(CAPACITY!$G$2,0,7*(J$2-$E$2)) -> 27.342 | K3: =OFFSET(CAPACITY!$G$2,0,7*(K$2-$E$2)) -> 27.342 | L3: =OFFSET(CAPACITY!$G$2,0,7*(L$2-$E$2)) -> 14.028 | M3: =OFFSET(CAPACITY!$G$2,0,7*(M$2-$E$2)) -> 28.371 | ... AT3: =OFFSET(CAPACITY!$G$2,0,7*(AT$2-$E$2)) -> 12.39 | AU3: =OFFSET(CAPACITY!$G$2,0,7*(AU$2+52-$E$2)) -> 17.346 | AV3: =OFFSET(CAPACITY!$G$2,0,7*(AV$2+52-$E$2)) -> 23.247 | AW3: =OFFSET(CAPACITY!$G$2,0,7*(AW$2+52-$E$2)) -> 28.728 | AX3: =OFFSET(CAPACITY!$G$2,0,7*(AX$2+52-$E$2)) -> 28.728 | AY3: =OFFSET(CAPACITY!$G$2,0,7*(AY$2+52-$E$2)) -> 26.439 | AZ3: =OFFSET(CAPACITY!$G$2,0,7*(AZ$2+52-$E$2)) -> 28.455 | BA3: =OFFSET(CAPACITY!$G$2,0,7*(BA$2+52-$E$2)) -> 27.342 | BB3: =OFFSET(CAPACITY!$G$2,0,7*(BB$2+52-$E$2)) -> 28.581 | ... CT3: =OFFSET(CAPACITY!$G$2,0,7*(CT$2+52-$E$2)) -> 9.66
C4: WAREX | E4: =CAPACITY!G4 -> 10.388559 | F4: =OFFSET(CAPACITY!$G$4,0,7*(F$2-$E$2)) -> 10.388559 | G4: =OFFSET(CAPACITY!$G$4,0,7*(G$2-$E$2)) -> 10.388559 | H4: =OFFSET(CAPACITY!$G$4,0,7*(H$2-$E$2)) -> 8.1544599 | I4: =OFFSET(CAPACITY!$G$4,0,7*(I$2-$E$2)) -> 10.388559 | J4: =OFFSET(CAPACITY!$G$4,0,7*(J$2-$E$2)) -> 10.069402 | K4: =OFFSET(CAPACITY!$G$4,0,7*(K$2-$E$2)) -> 10.388559 | L4: =OFFSET(CAPACITY!$G$4,0,7*(L$2-$E$2)) -> 1.9149417 | M4: =OFFSET(CAPACITY!$G$4,0,7*(M$2-$E$2)) -> 9.4310877 | ... AT4: =OFFSET(CAPACITY!$G$4,0,7*(AT$2-$E$2)) -> 9.4151298 | AU4: =OFFSET(CAPACITY!$G$4,0,7*(AU$2+52-$E$2)) -> 13.181182 | AV4: =OFFSET(CAPACITY!$G$4,0,7*(AV$2+52-$E$2)) -> 17.665337 | AW4: =OFFSET(CAPACITY!$G$4,0,7*(AW$2+52-$E$2)) -> 21.830335 | AX4: =OFFSET(CAPACITY!$G$4,0,7*(AX$2+52-$E$2)) -> 21.830335 | AY4: =OFFSET(CAPACITY!$G$4,0,7*(AY$2+52-$E$2)) -> 20.09093 | AZ4: =OFFSET(CAPACITY!$G$4,0,7*(AZ$2+52-$E$2)) -> 21.622883 | BA4: =OFFSET(CAPACITY!$G$4,0,7*(BA$2+52-$E$2)) -> 20.777117 | BB4: =OFFSET(CAPACITY!$G$4,0,7*(BB$2+52-$E$2)) -> 21.71863 | ... CT4: =OFFSET(CAPACITY!$G$4,0,7*(CT$2+52-$E$2)) -> 7.3406097
C5: OPTIMUS | E5: =CAPACITY!G6 -> 21.241748 | F5: =OFFSET(CAPACITY!$G$6,0,7*(F$2-$E$2)) -> 21.241748 | G5: =OFFSET(CAPACITY!$G$6,0,7*(G$2-$E$2)) -> 21.241748 | H5: =OFFSET(CAPACITY!$G$6,0,7*(H$2-$E$2)) -> 16.67363 | I5: =OFFSET(CAPACITY!$G$6,0,7*(I$2-$E$2)) -> 21.241748 | J5: =OFFSET(CAPACITY!$G$6,0,7*(J$2-$E$2)) -> 21.241748 | K5: =OFFSET(CAPACITY!$G$6,0,7*(K$2-$E$2)) -> 21.241748 | L5: =OFFSET(CAPACITY!$G$6,0,7*(L$2-$E$2)) -> 8.995678 | M5: =OFFSET(CAPACITY!$G$6,0,7*(M$2-$E$2)) -> 18.395459 | ... AT5: =OFFSET(CAPACITY!$G$6,0,7*(AT$2-$E$2)) -> 7.9063577 | AU5: =OFFSET(CAPACITY!$G$6,0,7*(AU$2+52-$E$2)) -> 12.281209 | AV5: =OFFSET(CAPACITY!$G$6,0,7*(AV$2+52-$E$2)) -> 14.705825 | AW5: =OFFSET(CAPACITY!$G$6,0,7*(AW$2+52-$E$2)) -> 20.082148 | AX5: =OFFSET(CAPACITY!$G$6,0,7*(AX$2+52-$E$2)) -> 20.082148 | AY5: =OFFSET(CAPACITY!$G$6,0,7*(AY$2+52-$E$2)) -> 18.852271 | AZ5: =OFFSET(CAPACITY!$G$6,0,7*(AZ$2+52-$E$2)) -> 19.027967 | BA5: =OFFSET(CAPACITY!$G$6,0,7*(BA$2+52-$E$2)) -> 17.270999 | BB5: =OFFSET(CAPACITY!$G$6,0,7*(BB$2+52-$E$2)) -> 15.074789 | ... CT5: =OFFSET(CAPACITY!$G$6,0,7*(CT$2+52-$E$2)) -> 4.9195114
C6: MASH | E6: =CAPACITY!G8 -> 8.1375 | F6: =OFFSET(CAPACITY!$G$8,0,7*(F$2-$E$2)) -> 8.1375 | G6: =OFFSET(CAPACITY!$G$8,0,7*(G$2-$E$2)) -> 8.1375 | H6: =OFFSET(CAPACITY!$G$8,0,7*(H$2-$E$2)) -> 6.3875 | I6: =OFFSET(CAPACITY!$G$8,0,7*(I$2-$E$2)) -> 8.1375 | J6: =OFFSET(CAPACITY!$G$8,0,7*(J$2-$E$2)) -> 8.1375 | K6: =OFFSET(CAPACITY!$G$8,0,7*(K$2-$E$2)) -> 8.1375 | L6: =OFFSET(CAPACITY!$G$8,0,7*(L$2-$E$2)) -> 5.25 | M6: =OFFSET(CAPACITY!$G$8,0,7*(M$2-$E$2)) -> 8.1375 | ... AT6: =OFFSET(CAPACITY!$G$8,0,7*(AT$2-$E$2)) -> 2.205 | AU6: =OFFSET(CAPACITY!$G$8,0,7*(AU$2+52-$E$2)) -> 3.4825 | AV6: =OFFSET(CAPACITY!$G$8,0,7*(AV$2+52-$E$2)) -> 6.0375 | AW6: =OFFSET(CAPACITY!$G$8,0,7*(AW$2+52-$E$2)) -> 7.91 | AX6: =OFFSET(CAPACITY!$G$8,0,7*(AX$2+52-$E$2)) -> 7.21 | AY6: =OFFSET(CAPACITY!$G$8,0,7*(AY$2+52-$E$2)) -> 6.86 | AZ6: =OFFSET(CAPACITY!$G$8,0,7*(AZ$2+52-$E$2)) -> 6.7375 | BA6: =OFFSET(CAPACITY!$G$8,0,7*(BA$2+52-$E$2)) -> 6.16 | BB6: =OFFSET(CAPACITY!$G$8,0,7*(BB$2+52-$E$2)) -> 7.56 | ... CT6: =OFFSET(CAPACITY!$G$8,0,7*(CT$2+52-$E$2)) -> 3.15
C7: MAGENTO | E7: =CAPACITY!G10 -> 23.2875 | F7: =OFFSET(CAPACITY!$G$10,0,7*(F$2-$E$2)) -> 23.2875 | G7: =OFFSET(CAPACITY!$G$10,0,7*(G$2-$E$2)) -> 23.2875 | H7: =OFFSET(CAPACITY!$G$10,0,7*(H$2-$E$2)) -> 22.5375 | I7: =OFFSET(CAPACITY!$G$10,0,7*(I$2-$E$2)) -> 23.2875 | J7: =OFFSET(CAPACITY!$G$10,0,7*(J$2-$E$2)) -> 23.2875 | K7: =OFFSET(CAPACITY!$G$10,0,7*(K$2-$E$2)) -> 23.2875 | L7: =OFFSET(CAPACITY!$G$10,0,7*(L$2-$E$2)) -> 20.25 | M7: =OFFSET(CAPACITY!$G$10,0,7*(M$2-$E$2)) -> 24.1575 | ... AT7: =OFFSET(CAPACITY!$G$10,0,7*(AT$2-$E$2)) -> 12.1125 | AU7: =OFFSET(CAPACITY!$G$10,0,7*(AU$2+52-$E$2)) -> 15.6675 | AV7: =OFFSET(CAPACITY!$G$10,0,7*(AV$2+52-$E$2)) -> 19.18875 | AW7: =OFFSET(CAPACITY!$G$10,0,7*(AW$2+52-$E$2)) -> 24.1575 | AX7: =OFFSET(CAPACITY!$G$10,0,7*(AX$2+52-$E$2)) -> 24.1575 | AY7: =OFFSET(CAPACITY!$G$10,0,7*(AY$2+52-$E$2)) -> 24.1575 | AZ7: =OFFSET(CAPACITY!$G$10,0,7*(AZ$2+52-$E$2)) -> 24.1575 | BA7: =OFFSET(CAPACITY!$G$10,0,7*(BA$2+52-$E$2)) -> 24.1575 | BB7: =OFFSET(CAPACITY!$G$10,0,7*(BB$2+52-$E$2)) -> 24.1575 | ... CT7: =OFFSET(CAPACITY!$G$10,0,7*(CT$2+52-$E$2)) -> 7.5
B8: PROJECTS & FUNCTIONALITIES CAPACITY UTILISATION | C8: ALF | E8: =E3-SUMIF($C$13:$C$531,$C8,E13:E531) -> 15.342 | F8: =F3-SUMIF($C$13:$C$531,$C8,F13:F531) -> 15.342 | G8: =G3-SUMIF($C$13:$C$531,$C8,G13:G531) -> 15.342 | H8: =H3-SUMIF($C$13:$C$531,$C8,H13:H531) -> 9.462 | I8: =I3-SUMIF($C$13:$C$531,$C8,I13:I531) -> 15.342 | J8: =J3-SUMIF($C$13:$C$531,$C8,J13:J531) -> 15.342 | K8: =K3-SUMIF($C$13:$C$531,$C8,K13:K531) -> 5.342 | L8: =L3-SUMIF($C$13:$C$531,$C8,L13:L531) -> -3.972 | ... BI8: =BI3-SUMIF($C$13:$C$531,$C8,BI13:BI531) -> 18.702
C9: WAREX | E9: =E4-SUMIF($C$13:$C$531,$C9,E13:E531) -> 10.388559 | F9: =F4-SUMIF($C$13:$C$531,$C9,F13:F531) -> 10.388559 | G9: =G4-SUMIF($C$13:$C$531,$C9,G13:G531) -> 10.388559 | H9: =H4-SUMIF($C$13:$C$531,$C9,H13:H531) -> 0.15445992 | I9: =I4-SUMIF($C$13:$C$531,$C9,I13:I531) -> 2.3885585 | J9: =J4-SUMIF($C$13:$C$531,$C9,J13:J531) -> 2.0694016 | K9: =K4-SUMIF($C$13:$C$531,$C9,K13:K531) -> -3.6114415 | L9: =L4-SUMIF($C$13:$C$531,$C9,L13:L531) -> -4.0850583 | ... BI9: =BI4-SUMIF($C$13:$C$531,$C9,BI13:BI531) -> 21.330373
C10: OPTIMUS | E10: =E5-SUMIF($C$13:$C$531,$C10,E13:E531) -> 21.241748 | F10: =F5-SUMIF($C$13:$C$531,$C10,F13:F531) -> 21.241748 | G10: =G5-SUMIF($C$13:$C$531,$C10,G13:G531) -> 21.241748 | H10: =H5-SUMIF($C$13:$C$531,$C10,H13:H531) -> 16.67363 | I10: =I5-SUMIF($C$13:$C$531,$C10,I13:I531) -> 21.241748 | J10: =J5-SUMIF($C$13:$C$531,$C10,J13:J531) -> 21.241748 | K10: =K5-SUMIF($C$13:$C$531,$C10,K13:K531) -> 21.241748 | L10: =L5-SUMIF($C$13:$C$531,$C10,L13:L531) -> 8.995678 | ... BI10: =BI5-SUMIF($C$13:$C$531,$C10,BI13:BI531) -> -2.1316317
C11: MASH | E11: =E6-SUMIF($C$13:$C$531,$C11,E13:E531) -> 7.6375 | F11: =F6-SUMIF($C$13:$C$531,$C11,F13:F531) -> 7.6375 | G11: =G6-SUMIF($C$13:$C$531,$C11,G13:G531) -> 7.6375 | H11: =H6-SUMIF($C$13:$C$531,$C11,H13:H531) -> 4.8875 | I11: =I6-SUMIF($C$13:$C$531,$C11,I13:I531) -> 5.6375 | J11: =J6-SUMIF($C$13:$C$531,$C11,J13:J531) -> 3.6375 | K11: =K6-SUMIF($C$13:$C$531,$C11,K13:K531) -> 0.6375 | L11: =L6-SUMIF($C$13:$C$531,$C11,L13:L531) -> -2.25 | ... BI11: =BI6-SUMIF($C$13:$C$531,$C11,BI13:BI531) -> 7.6375
C12: MAGENTO | E12: =E7-SUMIF($C$13:$C$531,$C12,E13:E531) -> 23.2875 | F12: =F7-SUMIF($C$13:$C$531,$C12,F13:F531) -> 23.2875 | G12: =G7-SUMIF($C$13:$C$531,$C12,G13:G531) -> 23.2875 | H12: =H7-SUMIF($C$13:$C$531,$C12,H13:H531) -> 22.5375 | I12: =I7-SUMIF($C$13:$C$531,$C12,I13:I531) -> 23.2875 | J12: =J7-SUMIF($C$13:$C$531,$C12,J13:J531) -> 11.2875 | K12: =K7-SUMIF($C$13:$C$531,$C12,K13:K531) -> 0.2875 | L12: =L7-SUMIF($C$13:$C$531,$C12,L13:L531) -> 2.25 | ... BI12: =BI7-SUMIF($C$13:$C$531,$C12,BI13:BI531) -> 24.4125
B13: DŁUG FUNKCJONALNY ALF | C13: ALF | D13: =SUM(E13:CT13) -> 660 | E13: 12 | F13: 12 | G13: 12 | H13: 12 | I13: 12 | J13: 12 | K13: 12 | L13: 12 | M13: 12 | N13: 12 | O13: 12 | P13: 12 | Q13: 12 | R13: 12 | S13: 12 | T13: 12 | U13: 12 | V13: 12 | W13: 12 | X13: 12 | Y13: 12 | Z13: 12 | AA13: 12 | AB13: 12 | AC13: 12 | AD13: 12 | AE13: 12 | AF13: 12 | AG13: 12 | AH13: 12 | AI13: 12 | AJ13: 12 | AK13: 12 | AL13: 12 | AM13: 12 | AN13: 12 | AO13: 12 | AP13: 12 | AQ13: 12 | AR13: 12 | AS13: 12 | AV13: 12 | AW13: 12 | AX13: 12 | AY13: 12 | AZ13: 12 | BA13: 12 | BB13: 12 | BC13: 12 | BD13: 12 | BE13: 12 | BF13: 12 | BG13: 12 | BH13: 12 | BI13: 12
C14: WAREX | D14: =SUM(E14:CT14) -> 0
C15: OPTIMUS | D15: =SUM(E15:CT15) -> 0
C16: MASH | D16: =SUM(E16:CT16) -> 27.5 | E16: 0.5 | F16: 0.5 | G16: 0.5 | H16: 0.5 | I16: 0.5 | J16: 0.5 | K16: 0.5 | L16: 0.5 | M16: 0.5 | N16: 0.5 | O16: 0.5 | P16: 0.5 | Q16: 0.5 | R16: 0.5 | S16: 0.5 | T16: 0.5 | U16: 0.5 | V16: 0.5 | W16: 0.5 | X16: 0.5 | Y16: 0.5 | Z16: 0.5 | AA16: 0.5 | AB16: 0.5 | AC16: 0.5 | AD16: 0.5 | AE16: 0.5 | AF16: 0.5 | AG16: 0.5 | AH16: 0.5 | AI16: 0.5 | AJ16: 0.5 | AK16: 0.5 | AL16: 0.5 | AM16: 0.5 | AN16: 0.5 | AO16: 0.5 | AP16: 0.5 | AQ16: 0.5 | AR16: 0.5 | AS16: 0.5 | AV16: 0.5 | AW16: 0.5 | AX16: 0.5 | AY16: 0.5 | AZ16: 0.5 | BA16: 0.5 | BB16: 0.5 | BC16: 0.5 | BD16: 0.5 | BE16: 0.5 | BF16: 0.5 | BG16: 0.5 | BH16: 0.5 | BI16: 0.5
C17: MAGENTO | D17: =SUM(E17:CT17) -> 0
A18: 0 | B18: Project - Portal B2B 1(1.5) | C18: ALF | D18: =SUM(E18:CT18) -> 2 | K18: 2
C19: WAREX | D19: =SUM(E19:CT19) -> 0
C20: OPTIMUS | D20: =SUM(E20:CT20) -> 0
C21: MASH | D21: =SUM(E21:CT21) -> 2 | J21: 1 | M21: 1
C22: MAGENTO | D22: =SUM(E22:CT22) -> 27 | J22: 6 | K22: 3 | L22: 3 | M22: 3 | N22: 2 | R22: 5 | S22: 5
A23: 0 | B23: Project - Multibrand for iMad | C23: ALF | D23: =SUM(E23:CT23) -> 2 | K23: 2
C24: WAREX | D24: =SUM(E24:CT24) -> 0
C25: OPTIMUS | D25: =SUM(E25:CT25) -> 0
C26: MASH | D26: =SUM(E26:CT26) -> 1 | K26: 1
C27: MAGENTO | D27: =SUM(E27:CT27) -> 35 | K27: 5 | L27: 5 | M27: 5 | Q27: 5 | R27: 5 | S27: 5 | T27: 5
A28: 0 | B28: Project - Malezja Faza 1A | C28: ALF | D28: =SUM(E28:CT28) -> 8.5 | K28: 1 | L28: 1 | M28: 0.5 | O28: 1 | P28: 3 | Q28: 2
C29: WAREX | D29: =SUM(E29:CT29) -> 1 | M29: 0.5 | N29: 0.5
C30: OPTIMUS | D30: =SUM(E30:CT30) -> 8 | P30: 0.5 | Q30: 0.5 | R30: 5 | S30: 2
C31: MASH | D31: =SUM(E31:CT31) -> 25 | H31: 1 | I31: 2 | J31: 3 | K31: 3 | L31: 2 | M31: 3 | N31: 1 | P31: 0.5 | Q31: 1 | R31: 0.5 | S31: 1 | T31: 2 | U31: 1 | AB31: 2 | AC31: 2
C32: MAGENTO | D32: =SUM(E32:CT32) -> 98 | J32: 6 | K32: 15 | L32: 10 | M32: 5 | N32: 15 | O32: 15 | P32: 10 | Q32: 5 | R32: 4 | S32: 4 | T32: 3 | AD32: 3 | AE32: 3
A33: 0 | B33: MM Open Days: Faza1 - 22/05 | C33: ALF | D33: =SUM(E33:CT33) -> 25 | K33: 5 | L33: 5 | M33: 5 | N33: 5 | O33: 5
C34: WAREX | D34: =SUM(E34:CT34) -> 2 | N34: 2
C35: OPTIMUS | D35: =SUM(E35:CT35) -> 0
C36: MASH | D36: =SUM(E36:CT36) -> 15 | K36: 3 | L36: 5 | M36: 3 | N36: 2 | O36: 2
C37: MAGENTO | D37: =SUM(E37:CT37) -> 10 | N37: 5 | O37: 5
A38: 0 | B38: MM Open Days: Faza2 - 03/06 | C38: ALF | D38: =SUM(E38:CT38) -> 0
C39: WAREX | D39: =SUM(E39:CT39) -> 0
C40: OPTIMUS | D40: =SUM(E40:CT40) -> 0
C41: MASH | D41: =SUM(E41:CT41) -> 0
C42: MAGENTO | D42: =SUM(E42:CT42) -> 4 | P42: 4
A43: 0 | B43: Open Days tMobile - 23/06 + Genetal Open Days Tasks | C43: ALF | D43: =SUM(E43:CT43) -> 0
C44: WAREX | D44: =SUM(E44:CT44) -> 0
C45: OPTIMUS | D45: =SUM(E45:CT45) -> 0
C46: MASH | D46: =SUM(E46:CT46) -> 0
C47: MAGENTO | D47: =SUM(E47:CT47) -> 12 | Q47: 4 | R47: 3 | S47: 5
A48: 0 | B48: PLAY New Assortment Groups | C48: ALF | D48: =SUM(E48:CT48) -> 0
C49: WAREX | D49: =SUM(E49:CT49) -> 44 | H49: 3 | I49: 3 | J49: 3 | K49: 8 | L49: 3 | M49: 12 | N49: 8 | O49: 2 | Q49: 1 | R49: 1
C50: OPTIMUS | D50: =SUM(E50:CT50) -> 29 | P50: 5 | Q50: 10 | R50: 10 | S50: 3 | T50: 1
C51: MASH | D51: =SUM(E51:CT51) -> 0
C52: MAGENTO | D52: =SUM(E52:CT52) -> 0
A53: 0 | B53: Inicjatywa PLK karta usług (B2B Enterprise + Frontend) | C53: ALF | D53: =SUM(E53:CT53) -> 0
C54: WAREX | D54: =SUM(E54:CT54) -> 105 | H54: 5 | I54: 5 | J54: 5 | K54: 6 | L54: 3 | M54: 8 | N54: 8 | O54: 9 | P54: 9 | Q54: 4 | R54: 4 | S54: 8 | T54: 4 | U54: 5 | V54: 3 | W54: 4 | X54: 4 | Y54: 3 | Z54: 2 | AA54: 3 | AB54: 1 | AC54: 2
C55: OPTIMUS | D55: =SUM(E55:CT55) -> 22 | U55: 1 | AA55: 1 | AB55: 8 | AC55: 7 | AD55: 2 | AE55: 3
C56: MASH | D56: =SUM(E56:CT56) -> 0
C57: MAGENTO | D57: =SUM(E57:CT57) -> 0
A58: 0 | B58: JET (zmiana leasingu na najem do 27 maja) | C58: ALF | D58: =SUM(E58:CT58) -> 10 | N58: 2 | O58: 5 | Q58: 3
C59: WAREX | D59: =SUM(E59:CT59) -> 0
C60: OPTIMUS | D60: =SUM(E60:CT60) -> 0
C61: MASH | D61: =SUM(E61:CT61) -> 0
C62: MAGENTO | D62: =SUM(E62:CT62) -> 0
A63: 0 | B63: ALLPSI | C63: ALF | D63: =SUM(E63:CT63) -> 36 | N63: 2 | O63: 5 | P63: 5 | Q63: 6 | R63: 5 | S63: 4 | T63: 2 | U63: 2 | V63: 2 | W63: 3
C64: WAREX | D64: =SUM(E64:CT64) -> 0
C65: OPTIMUS | D65: =SUM(E65:CT65) -> 0
C66: MASH | D66: =SUM(E66:CT66) -> 10 | M66: 1 | N66: 3 | O66: 1 | P66: 1 | Q66: 1 | R66: 1 | S66: 1 | T66: 1
C67: MAGENTO | D67: =SUM(E67:CT67) -> 0
A68: 0 | B68: PHOX (iMad Now) | C68: ALF | D68: =SUM(E68:CT68) -> 32 | AE68: 2 | AF68: 2 | AG68: 2 | AH68: 2 | AI68: 2 | AJ68: 2 | AK68: 5 | AL68: 5 | AM68: 5 | AN68: 5
C69: WAREX | D69: =SUM(E69:CT69) -> 26 | AE69: 2 | AF69: 3 | AG69: 2 | AH69: 4 | AJ69: 5 | AK69: 5 | AL69: 5
C70: OPTIMUS | D70: =SUM(E70:CT70) -> 18 | AH70: 2 | AI70: 1 | AL70: 2 | AM70: 5 | AN70: 5 | AO70: 3
C71: MASH | D71: =SUM(E71:CT71) -> 6 | AH71: 1 | AI71: 1 | AJ71: 1 | AK71: 1 | AL71: 1 | AM71: 1
C72: MAGENTO
A73: 0 | B73: (BIK) Antyfraud CFD | C73: ALF | D73: =SUM(E73:CT73) -> 0
C74: WAREX | D74: =SUM(E74:CT74) -> 0
C75: OPTIMUS | D75: =SUM(E75:CT75) -> 0
C76: MASH | D76: =SUM(E76:CT76) -> 22 | M76: 1 | N76: 1 | O76: 1 | P76: 0.5 | Q76: 1 | R76: 1 | S76: 3 | T76: 3 | U76: 2 | V76: 2 | W76: 2 | X76: 0.5 | Y76: 0.5 | Z76: 0.5 | AA76: 1 | AB76: 1 | AC76: 1
C77: MAGENTO | D77: =SUM(E77:CT77) -> 37 | R77: 2 | S77: 5 | T77: 3 | U77: 3 | V77: 3 | W77: 3 | X77: 5 | Y77: 5 | Z77: 2 | AA77: 2 | AB77: 2 | AC77: 2
A78: 0 | B78: Inicjatywa API PLAY | C78: ALF | D78: =SUM(E78:CT78) -> 0
C79: WAREX | D79: =SUM(E79:CT79) -> 0
C80: OPTIMUS | D80: =SUM(E80:CT80) -> 60 | T80: 1 | U80: 2 | V80: 2 | W80: 2 | X80: 2 | Y80: 5 | Z80: 10 | AA80: 3 | AB80: 5 | AC80: 5 | AD80: 3 | AE80: 3 | AF80: 3 | AG80: 3 | AH80: 3 | AI80: 1 | AJ80: 2 | AK80: 5
C81: MASH | D81: =SUM(E81:CT81) -> 0
C82: MAGENTO | D82: =SUM(E82:CT82) -> 0
A83: 0 | B83: Decision Cube | C83: ALF | D83: =SUM(E83:CT83) -> 87 | U83: 5 | V83: 5 | W83: 5 | X83: 5 | Y83: 5 | Z83: 5 | AA83: 5 | AB83: 5 | AC83: 5 | AD83: 3 | AE83: 5 | AF83: 6 | AG83: 6 | AH83: 5 | AI83: 5 | AJ83: 3 | AK83: 3 | AL83: 3 | AM83: 3
C84: WAREX | D84: =SUM(E84:CT84) -> 0
C85: OPTIMUS | D85: =SUM(E85:CT85) -> 0
C86: MASH | D86: =SUM(E86:CT86) -> 0
C87: MAGENTO | D87: =SUM(E87:CT87) -> 0
A88: 0 | B88: Dynamic Pricing | C88: ALF | D88: =SUM(E88:CT88) -> 30 | AH88: 2 | AI88: 3 | AJ88: 3 | AK88: 5 | AL88: 5 | AM88: 5 | AN88: 5 | AO88: 1 | AP88: 1
C89: WAREX | D89: =SUM(E89:CT89) -> 0
C90: OPTIMUS | D90: =SUM(E90:CT90) -> 0
C91: MASH | D91: =SUM(E91:CT91) -> 10 | AI91: 2 | AJ91: 2 | AK91: 1 | AL91: 1 | AM91: 1 | AN91: 1 | AO91: 1 | AP91: 1
C92: MAGENTO | D92: =SUM(E92:CT92) -> 0
A93: 0 | B93: Paperless | C93: ALF | D93: =SUM(E93:CT93) -> 40 | AK93: 5 | AL93: 5 | AM93: 5 | AN93: 5 | AO93: 5 | AP93: 5 | AQ93: 5 | AR93: 5
C94: WAREX | D94: =SUM(E94:CT94) -> 0
C95: OPTIMUS | D95: =SUM(E95:CT95) -> 0
C96: MASH | D96: =SUM(E96:CT96) -> 0
C97: MAGENTO | D97: =SUM(E97:CT97) -> 0
A98: 0 | B98: Risk Changes | C98: ALF | D98: =SUM(E98:CT98) -> 24 | AA98: 2 | AB98: 5 | AC98: 5 | AD98: 5 | AE98: 5 | AF98: 2
C99: WAREX | D99: =SUM(E99:CT99) -> 0
C100: OPTIMUS | D100: =SUM(E100:CT100) -> 0
...

Sheet WORKLOAD_TEAMS (6)
A1: PRIORYTET | B1: DATE | C1: DATE | D1: TOTALS | E1: =TEXT(DATE(2024,1,1)+(E2-1)*7-WEEKDAY(DATE(2024,1,1),2)+1,"dd.mm")&"-"&TEXT(DATE(2024,1,1)+(E2-1)*7-WEEKDAY(DATE(2024,1,1),2)+7,"dd.mm") -> 11.03-17.03 | F1: =TEXT(DATE(2024,1,1)+(F2-1)*7-WEEKDAY(DATE(2024,1,1),2)+1,"dd.mm")&"-"&TEXT(DATE(2024,1,1)+(F2-1)*7-WEEKDAY(DATE(2024,1,1),2)+7,"dd.mm") -> 18.03-24.03 | G1: =TEXT(DATE(2024,1,1)+(G2-1)*7-WEEKDAY(DATE(2024,1,1),2)+1,"dd.mm")&"-"&TEXT(DATE(2024,1,1)+(G2-1)*7-WEEKDAY(DATE(2024,1,1),2)+7,"dd.mm") -> 25.03-31.03 | H1: =TEXT(DATE(2024,1,1)+(H2-1)*7-WEEKDAY(DATE(2024,1,1),2)+1,"dd.mm")&"-"&TEXT(DATE(2024,1,1)+(H2-1)*7-WEEKDAY(DATE(2024,1,1),2)+7,"dd.mm") -> 01.04-07.04 | I1: =TEXT(DATE(2024,1,1)+(I2-1)*7-WEEKDAY(DATE(2024,1,1),2)+1,"dd.mm")&"-"&TEXT(DATE(2024,1,1)+(I2-1)*7-WEEKDAY(DATE(2024,1,1),2)+7,"dd.mm") -> 08.04-14.04 | J1: =TEXT(DATE(2024,1,1)+(J2-1)*7-WEEKDAY(DATE(2024,1,1),2)+1,"dd.mm")&"-"&TEXT(DATE(2024,1,1)+(J2-1)*7-WEEKDAY(DATE(2024,1,1),2)+7,"dd.mm") -> 15.04-21.04 | K1: =TEXT(DATE(2024,1,1)+(K2-1)*7-WEEKDAY(DATE(2024,1,1),2)+1,"dd.mm")&"-"&TEXT(DATE(2024,1,1)+(K2-1)*7-WEEKDAY(DATE(2024,1,1),2)+7,"dd.mm") -> 22.04-28.04 | L1: =TEXT(DATE(2024,1,1)+(L2-1)*7-WEEKDAY(DATE(2024,1,1),2)+1,"dd.mm")&"-"&TEXT(DATE(2024,1,1)+(L2-1)*7-WEEKDAY(DATE(2024,1,1),2)+7,"dd.mm") -> 29.04-05.05 | ... AT1: =TEXT(DATE(2024,1,1)+(AT2-1)*7-WEEKDAY(DATE(2024,1,1),2)+1,"dd.mm")&"-"&TEXT(DATE(2024,1,1)+(AT2-1)*7-WEEKDAY(DATE(2024,1,1),2)+7,"dd.mm") -> 23.12-29.12 | AU1: =TEXT(DATE(2025,1,1)+(AU2-1)*7-WEEKDAY(DATE(2025,1,1),2)+1,"dd.mm")&"-"&TEXT(DATE(2025,1,1)+(AU2-1)*7-WEEKDAY(DATE(2025,1,1),2)+7,"dd.mm") -> 30.12-05.01 | AV1: =TEXT(DATE(2025,1,1)+(AV2-1)*7-WEEKDAY(DATE(2025,1,1),2)+1,"dd.mm")&"-"&TEXT(DATE(2025,1,1)+(AV2-1)*7-WEEKDAY(DATE(2025,1,1),2)+7,"dd.mm") -> 06.01-12.01 | AW1: =TEXT(DATE(2025,1,1)+(AW2-1)*7-WEEKDAY(DATE(2025,1,1),2)+1,"dd.mm")&"-"&TEXT(DATE(2025,1,1)+(AW2-1)*7-WEEKDAY(DATE(2025,1,1),2)+7,"dd.mm") -> 13.01-19.01 | AX1: =TEXT(DATE(2025,1,1)+(AX2-1)*7-WEEKDAY(DATE(2025,1,1),2)+1,"dd.mm")&"-"&TEXT(DATE(2025,1,1)+(AX2-1)*7-WEEKDAY(DATE(2025,1,1),2)+7,"dd.mm") -> 20.01-26.01 | AY1: =TEXT(DATE(2025,1,1)+(AY2-1)*7-WEEKDAY(DATE(2025,1,1),2)+1,"dd.mm")&"-"&TEXT(DATE(2025,1,1)+(AY2-1)*7-WEEKDAY(DATE(2025,1,1),2)+7,"dd.mm") -> 27.01-02.02 | AZ1: =TEXT(DATE(2025,1,1)+(AZ2-1)*7-WEEKDAY(DATE(2025,1,1),2)+1,"dd.mm")&"-"&TEXT(DATE(2025,1,1)+(AZ2-1)*7-WEEKDAY(DATE(2025,1,1),2)+7,"dd.mm") -> 03.02-09.02 | BA1: =TEXT(DATE(2025,1,1)+(BA2-1)*7-WEEKDAY(DATE(2025,1,1),2)+1,"dd.mm")&"-"&TEXT(DATE(2025,1,1)+(BA2-1)*7-WEEKDAY(DATE(2025,1,1),2)+7,"dd.mm") -> 10.02-16.02 | BB1: =TEXT(DATE(2025,1,1)+(BB2-1)*7-WEEKDAY(DATE(2025,1,1),2)+1,"dd.mm")&"-"&TEXT(DATE(2025,1,1)+(BB2-1)*7-WEEKDAY(DATE(2025,1,1),2)+7,"dd.mm") -> 17.02-23.02 | ... CT1: =TEXT(DATE(2025,1,1)+(CT2-1)*7-WEEKDAY(DATE(2025,1,1),2)+1,"dd.mm")&"-"&TEXT(DATE(2025,1,1)+(CT2-1)*7-WEEKDAY(DATE(2025,1,1),2)+7,"dd.mm") -> 22.12-28.12
C2: WEEK | E2: 11 | F2: 12 | G2: 13 | H2: 14 | I2: 15 | J2: 16 | K2: 17 | L2: 18 | M2: 19 | N2: 20 | O2: 21 | P2: 22 | Q2: 23 | R2: 24 | S2: 25 | T2: 26 | U2: 27 | V2: 28 | W2: 29 | X2: 30 | Y2: 31 | Z2: 32 | AA2: 33 | AB2: 34 | AC2: 35 | AD2: 36 | AE2: 37 | AF2: 38 | AG2: 39 | AH2: 40 | AI2: 41 | AJ2: 42 | AK2: 43 | AL2: 44 | AM2: 45 | AN2: 46 | AO2: 47 | AP2: 48 | AQ2: 49 | AR2: 50 | AS2: 51 | AT2: 52 | AU2: 1 | AV2: 2 | AW2: 3 | AX2: 4 | AY2: 5 | AZ2: 6 | BA2: 7 | BB2: 8 | BC2: 9 | BD2: 10 | BE2: 11 | BF2: 12 | BG2: 13 | BH2: 14 | BI2: 15 | BJ2: 16 | BK2: 17 | BL2: 18 | BM2: 19 | BN2: 20 | BO2: 21 | BP2: 22 | BQ2: 23 | BR2: 24 | BS2: 25 | BT2: 26 | BU2: 27 | BV2: 28 | BW2: 29 | BX2: 30 | BY2: 31 | BZ2: 32 | CA2: 33 | CB2: 34 | CC2: 35 | CD2: 36 | CE2: 37 | CF2: 38 | CG2: 39 | CH2: 40 | CI2: 41 | CJ2: 42 | CK2: 43 | CL2: 44 | CM2: 45 | CN2: 46 | CO2: 47 | CP2: 48 | CQ2: 49 | CR2: 50 | CS2: 51 | CT2: 52
B3: PROJECTS & FUNCTIONALITIES CAPACITY | C3: ALF | E3: =CAPACITY!G2 -> 27.342 | F3: =OFFSET(CAPACITY!$G$2,0,7*(F$2-$E$2)) -> 27.342 | G3: =OFFSET(CAPACITY!$G$2,0,7*(G$2-$E$2)) -> 27.342 | H3: =OFFSET(CAPACITY!$G$2,0,7*(H$2-$E$2)) -> 21.462 | I3: =OFFSET(CAPACITY!$G$2,0,7*(I$2-$E$2)) -> 27.342 | J3: =OFFSET(CAPACITY!$G$2,0,7*(J$2-$E$2)) -> 27.342 | K3: =OFFSET(CAPACITY!$G$2,0,7*(K$2-$E$2)) -> 27.342 | L3: =OFFSET(CAPACITY!$G$2,0,7*(L$2-$E$2)) -> 14.028 | M3: =OFFSET(CAPACITY!$G$2,0,7*(M$2-$E$2)) -> 28.371 | ... AT3: =OFFSET(CAPACITY!$G$2,0,7*(AT$2-$E$2)) -> 12.39 | AU3: =OFFSET(CAPACITY!$G$2,0,7*(AU$2+52-$E$2)) -> 17.346 | AV3: =OFFSET(CAPACITY!$G$2,0,7*(AV$2+52-$E$2)) -> 23.247 | AW3: =OFFSET(CAPACITY!$G$2,0,7*(AW$2+52-$E$2)) -> 28.728 | AX3: =OFFSET(CAPACITY!$G$2,0,7*(AX$2+52-$E$2)) -> 28.728 | AY3: =OFFSET(CAPACITY!$G$2,0,7*(AY$2+52-$E$2)) -> 26.439 | AZ3: =OFFSET(CAPACITY!$G$2,0,7*(AZ$2+52-$E$2)) -> 28.455 | BA3: =OFFSET(CAPACITY!$G$2,0,7*(BA$2+52-$E$2)) -> 27.342 | BB3: =OFFSET(CAPACITY!$G$2,0,7*(BB$2+52-$E$2)) -> 28.581 | ... CT3: =OFFSET(CAPACITY!$G$2,0,7*(CT$2+52-$E$2)) -> 9.66
C4: WAREX | E4: =CAPACITY!G4 -> 10.388559 | F4: =OFFSET(CAPACITY!$G$4,0,7*(F$2-$E$2)) -> 10.388559 | G4: =OFFSET(CAPACITY!$G$4,0,7*(G$2-$E$2)) -> 10.388559 | H4: =OFFSET(CAPACITY!$G$4,0,7*(H$2-$E$2)) -> 8.1544599 | I4: =OFFSET(CAPACITY!$G$4,0,7*(I$2-$E$2)) -> 10.388559 | J4: =OFFSET(CAPACITY!$G$4,0,7*(J$2-$E$2)) -> 10.069402 | K4: =OFFSET(CAPACITY!$G$4,0,7*(K$2-$E$2)) -> 10.388559 | L4: =OFFSET(CAPACITY!$G$4,0,7*(L$2-$E$2)) -> 1.9149417 | M4: =OFFSET(CAPACITY!$G$4,0,7*(M$2-$E$2)) -> 9.4310877 | ... AT4: =OFFSET(CAPACITY!$G$4,0,7*(AT$2-$E$2)) -> 9.4151298 | AU4: =OFFSET(CAPACITY!$G$4,0,7*(AU$2+52-$E$2)) -> 13.181182 | AV4: =OFFSET(CAPACITY!$G$4,0,7*(AV$2+52-$E$2)) -> 17.665337 | AW4: =OFFSET(CAPACITY!$G$4,0,7*(AW$2+52-$E$2)) -> 21.830335 | AX4: =OFFSET(CAPACITY!$G$4,0,7*(AX$2+52-$E$2)) -> 21.830335 | AY4: =OFFSET(CAPACITY!$G$4,0,7*(AY$2+52-$E$2)) -> 20.09093 | AZ4: =OFFSET(CAPACITY!$G$4,0,7*(AZ$2+52-$E$2)) -> 21.622883 | BA4: =OFFSET(CAPACITY!$G$4,0,7*(BA$2+52-$E$2)) -> 20.777117 | BB4: =OFFSET(CAPACITY!$G$4,0,7*(BB$2+52-$E$2)) -> 21.71863 | ... CT4: =OFFSET(CAPACITY!$G$4,0,7*(CT$2+52-$E$2)) -> 7.3406097
C5: OPTIMUS | E5: =CAPACITY!G6 -> 21.241748 | F5: =OFFSET(CAPACITY!$G$6,0,7*(F$2-$E$2)) -> 21.241748 | G5: =OFFSET(CAPACITY!$G$6,0,7*(G$2-$E$2)) -> 21.241748 | H5: =OFFSET(CAPACITY!$G$6,0,7*(H$2-$E$2)) -> 16.67363 | I5: =OFFSET(CAPACITY!$G$6,0,7*(I$2-$E$2)) -> 21.241748 | J5: =OFFSET(CAPACITY!$G$6,0,7*(J$2-$E$2)) -> 21.241748 | K5: =OFFSET(CAPACITY!$G$6,0,7*(K$2-$E$2)) -> 21.241748 | L5: =OFFSET(CAPACITY!$G$6,0,7*(L$2-$E$2)) -> 8.995678 | M5: =OFFSET(CAPACITY!$G$6,0,7*(M$2-$E$2)) -> 18.395459 | ... AT5: =OFFSET(CAPACITY!$G$6,0,7*(AT$2-$E$2)) -> 7.9063577 | AU5: =OFFSET(CAPACITY!$G$6,0,7*(AU$2+52-$E$2)) -> 12.281209 | AV5: =OFFSET(CAPACITY!$G$6,0,7*(AV$2+52-$E$2)) -> 14.705825 | AW5: =OFFSET(CAPACITY!$G$6,0,7*(AW$2+52-$E$2)) -> 20.082148 | AX5: =OFFSET(CAPACITY!$G$6,0,7*(AX$2+52-$E$2)) -> 20.082148 | AY5: =OFFSET(CAPACITY!$G$6,0,7*(AY$2+52-$E$2)) -> 18.852271 | AZ5: =OFFSET(CAPACITY!$G$6,0,7*(AZ$2+52-$E$2)) -> 19.027967 | BA5: =OFFSET(CAPACITY!$G$6,0,7*(BA$2+52-$E$2)) -> 17.270999 | BB5: =OFFSET(CAPACITY!$G$6,0,7*(BB$2+52-$E$2)) -> 15.074789 | ... CT5: =OFFSET(CAPACITY!$G$6,0,7*(CT$2+52-$E$2)) -> 4.9195114
C6: MASH | E6: =CAPACITY!G8 -> 8.1375 | F6: =OFFSET(CAPACITY!$G$8,0,7*(F$2-$E$2)) -> 8.1375 | G6: =OFFSET(CAPACITY!$G$8,0,7*(G$2-$E$2)) -> 8.1375 | H6: =OFFSET(CAPACITY!$G$8,0,7*(H$2-$E$2)) -> 6.3875 | I6: =OFFSET(CAPACITY!$G$8,0,7*(I$2-$E$2)) -> 8.1375 | J6: =OFFSET(CAPACITY!$G$8,0,7*(J$2-$E$2)) -> 8.1375 | K6: =OFFSET(CAPACITY!$G$8,0,7*(K$2-$E$2)) -> 8.1375 | L6: =OFFSET(CAPACITY!$G$8,0,7*(L$2-$E$2)) -> 5.25 | M6: =OFFSET(CAPACITY!$G$8,0,7*(M$2-$E$2)) -> 8.1375 | ... AT6: =OFFSET(CAPACITY!$G$8,0,7*(AT$2-$E$2)) -> 2.205 | AU6: =OFFSET(CAPACITY!$G$8,0,7*(AU$2+52-$E$2)) -> 3.4825 | AV6: =OFFSET(CAPACITY!$G$8,0,7*(AV$2+52-$E$2)) -> 6.0375 | AW6: =OFFSET(CAPACITY!$G$8,0,7*(AW$2+52-$E$2)) -> 7.91 | AX6: =OFFSET(CAPACITY!$G$8,0,7*(AX$2+52-$E$2)) -> 7.21 | AY6: =OFFSET(CAPACITY!$G$8,0,7*(AY$2+52-$E$2)) -> 6.86 | AZ6: =OFFSET(CAPACITY!$G$8,0,7*(AZ$2+52-$E$2)) -> 6.7375 | BA6: =OFFSET(CAPACITY!$G$8,0,7*(BA$2+52-$E$2)) -> 6.16 | BB6: =OFFSET(CAPACITY!$G$8,0,7*(BB$2+52-$E$2)) -> 7.56 | ... CT6: =OFFSET(CAPACITY!$G$8,0,7*(CT$2+52-$E$2)) -> 3.15
C7: MAGENTO | E7: =CAPACITY!G10 -> 23.2875 | F7: =OFFSET(CAPACITY!$G$10,0,7*(F$2-$E$2)) -> 23.2875 | G7: =OFFSET(CAPACITY!$G$10,0,7*(G$2-$E$2)) -> 23.2875 | H7: =OFFSET(CAPACITY!$G$10,0,7*(H$2-$E$2)) -> 22.5375 | I7: =OFFSET(CAPACITY!$G$10,0,7*(I$2-$E$2)) -> 23.2875 | J7: =OFFSET(CAPACITY!$G$10,0,7*(J$2-$E$2)) -> 23.2875 | K7: =OFFSET(CAPACITY!$G$10,0,7*(K$2-$E$2)) -> 23.2875 | L7: =OFFSET(CAPACITY!$G$10,0,7*(L$2-$E$2)) -> 20.25 | M7: =OFFSET(CAPACITY!$G$10,0,7*(M$2-$E$2)) -> 24.1575 | ... AT7: =OFFSET(CAPACITY!$G$10,0,7*(AT$2-$E$2)) -> 12.1125 | AU7: =OFFSET(CAPACITY!$G$10,0,7*(AU$2+52-$E$2)) -> 15.6675 | AV7: =OFFSET(CAPACITY!$G$10,0,7*(AV$2+52-$E$2)) -> 19.18875 | AW7: =OFFSET(CAPACITY!$G$10,0,7*(AW$2+52-$E$2)) -> 24.1575 | AX7: =OFFSET(CAPACITY!$G$10,0,7*(AX$2+52-$E$2)) -> 24.1575 | AY7: =OFFSET(CAPACITY!$G$10,0,7*(AY$2+52-$E$2)) -> 24.1575 | AZ7: =OFFSET(CAPACITY!$G$10,0,7*(AZ$2+52-$E$2)) -> 24.1575 | BA7: =OFFSET(CAPACITY!$G$10,0,7*(BA$2+52-$E$2)) -> 24.1575 | BB7: =OFFSET(CAPACITY!$G$10,0,7*(BB$2+52-$E$2)) -> 24.1575 | ... CT7: =OFFSET(CAPACITY!$G$10,0,7*(CT$2+52-$E$2)) -> 7.5
B8: PROJECTS & FUNCTIONALITIES CAPACITY UTILISATION | C8: ALF | E8: =E3-SUMIF($C$13:$C$536,$C8,E13:E536) -> 15.342 | F8: =F3-SUMIF($C$13:$C$536,$C8,F13:F536) -> 15.342 | G8: =G3-SUMIF($C$13:$C$536,$C8,G13:G536) -> 15.342 | H8: =H3-SUMIF($C$13:$C$536,$C8,H13:H536) -> 9.462 | I8: =I3-SUMIF($C$13:$C$536,$C8,I13:I536) -> 15.342 | J8: =J3-SUMIF($C$13:$C$536,$C8,J13:J536) -> 10.342 | K8: =K3-SUMIF($C$13:$C$536,$C8,K13:K536) -> -4.658 | L8: =L3-SUMIF($C$13:$C$536,$C8,L13:L536) -> -8.972 | ... CT8: =CT3-SUMIF($C$13:$C$536,$C8,CT13:CT536) -> 9.66
C9: WAREX | E9: =E4-SUMIF($C$13:$C$536,$C9,E13:E536) -> 10.388559 | F9: =F4-SUMIF($C$13:$C$536,$C9,F13:F536) -> 10.388559 | G9: =G4-SUMIF($C$13:$C$536,$C9,G13:G536) -> 10.388559 | H9: =H4-SUMIF($C$13:$C$536,$C9,H13:H536) -> 0.15445992 | I9: =I4-SUMIF($C$13:$C$536,$C9,I13:I536) -> 2.3885585 | J9: =J4-SUMIF($C$13:$C$536,$C9,J13:J536) -> 2.0694016 | K9: =K4-SUMIF($C$13:$C$536,$C9,K13:K536) -> -3.6114415 | L9: =L4-SUMIF($C$13:$C$536,$C9,L13:L536) -> -4.0850583 | ... CT9: =CT4-SUMIF($C$13:$C$536,$C9,CT13:CT536) -> 7.3406097
C10: OPTIMUS | E10: =E5-SUMIF($C$13:$C$536,$C10,E13:E536) -> 21.241748 | F10: =F5-SUMIF($C$13:$C$536,$C10,F13:F536) -> 21.241748 | G10: =G5-SUMIF($C$13:$C$536,$C10,G13:G536) -> 21.241748 | H10: =H5-SUMIF($C$13:$C$536,$C10,H13:H536) -> 16.67363 | I10: =I5-SUMIF($C$13:$C$536,$C10,I13:I536) -> 21.241748 | J10: =J5-SUMIF($C$13:$C$536,$C10,J13:J536) -> 21.241748 | K10: =K5-SUMIF($C$13:$C$536,$C10,K13:K536) -> 21.241748 | L10: =L5-SUMIF($C$13:$C$536,$C10,L13:L536) -> 8.995678 | ... CT10: =CT5-SUMIF($C$13:$C$536,$C10,CT13:CT536) -> 4.9195114
C11: MASH | E11: =E6-SUMIF($C$13:$C$536,$C11,E13:E536) -> 7.6375 | F11: =F6-SUMIF($C$13:$C$536,$C11,F13:F536) -> 7.6375 | G11: =G6-SUMIF($C$13:$C$536,$C11,G13:G536) -> 7.6375 | H11: =H6-SUMIF($C$13:$C$536,$C11,H13:H536) -> 4.8875 | I11: =I6-SUMIF($C$13:$C$536,$C11,I13:I536) -> 5.6375 | J11: =J6-SUMIF($C$13:$C$536,$C11,J13:J536) -> 3.6375 | K11: =K6-SUMIF($C$13:$C$536,$C11,K13:K536) -> 0.6375 | L11: =L6-SUMIF($C$13:$C$536,$C11,L13:L536) -> -2.25 | ... CT11: =CT6-SUMIF($C$13:$C$536,$C11,CT13:CT536) -> 3.15
C12: MAGENTO | E12: =E7-SUMIF($C$13:$C$536,$C12,E13:E536) -> 23.2875 | F12: =F7-SUMIF($C$13:$C$536,$C12,F13:F536) -> 23.2875 | G12: =G7-SUMIF($C$13:$C$536,$C12,G13:G536) -> 23.2875 | H12: =H7-SUMIF($C$13:$C$536,$C12,H13:H536) -> 22.5375 | I12: =I7-SUMIF($C$13:$C$536,$C12,I13:I536) -> 23.2875 | J12: =J7-SUMIF($C$13:$C$536,$C12,J13:J536) -> 11.2875 | K12: =K7-SUMIF($C$13:$C$536,$C12,K13:K536) -> 0.2875 | L12: =L7-SUMIF($C$13:$C$536,$C12,L13:L536) -> 2.25 | ... CT12: =CT7-SUMIF($C$13:$C$536,$C12,CT13:CT536) -> 7.5
B13: DŁUG FUNKCJONALNY ALF | C13: ALF | D13: =SUM(E13:CT13) -> 660 | E13: 12 | F13: 12 | G13: 12 | H13: 12 | I13: 12 | J13: 12 | K13: 12 | L13: 12 | M13: 12 | N13: 12 | O13: 12 | P13: 12 | Q13: 12 | R13: 12 | S13: 12 | T13: 12 | U13: 12 | V13: 12 | W13: 12 | X13: 12 | Y13: 12 | Z13: 12 | AA13: 12 | AB13: 12 | AC13: 12 | AD13: 12 | AE13: 12 | AF13: 12 | AG13: 12 | AH13: 12 | AI13: 12 | AJ13: 12 | AK13: 12 | AL13: 12 | AM13: 12 | AN13: 12 | AO13: 12 | AP13: 12 | AQ13: 12 | AR13: 12 | AS13: 12 | AV13: 12 | AW13: 12 | AX13: 12 | AY13: 12 | AZ13: 12 | BA13: 12 | BB13: 12 | BC13: 12 | BD13: 12 | BE13: 12 | BF13: 12 | BG13: 12 | BH13: 12 | BI13: 12
C14: WAREX | D14: =SUM(E14:CT14) -> 0
C15: OPTIMUS | D15: =SUM(E15:CT15) -> 0
C16: MASH | D16: =SUM(E16:CT16) -> 27.5 | E16: 0.5 | F16: 0.5 | G16: 0.5 | H16: 0.5 | I16: 0.5 | J16: 0.5 | K16: 0.5 | L16: 0.5 | M16: 0.5 | N16: 0.5 | O16: 0.5 | P16: 0.5 | Q16: 0.5 | R16: 0.5 | S16: 0.5 | T16: 0.5 | U16: 0.5 | V16: 0.5 | W16: 0.5 | X16: 0.5 | Y16: 0.5 | Z16: 0.5 | AA16: 0.5 | AB16: 0.5 | AC16: 0.5 | AD16: 0.5 | AE16: 0.5 | AF16: 0.5 | AG16: 0.5 | AH16: 0.5 | AI16: 0.5 | AJ16: 0.5 | AK16: 0.5 | AL16: 0.5 | AM16: 0.5 | AN16: 0.5 | AO16: 0.5 | AP16: 0.5 | AQ16: 0.5 | AR16: 0.5 | AS16: 0.5 | AV16: 0.5 | AW16: 0.5 | AX16: 0.5 | AY16: 0.5 | AZ16: 0.5 | BA16: 0.5 | BB16: 0.5 | BC16: 0.5 | BD16: 0.5 | BE16: 0.5 | BF16: 0.5 | BG16: 0.5 | BH16: 0.5 | BI16: 0.5
C17: MAGENTO | D17: =SUM(E17:CT17) -> 0
A18: 0 | B18: Project - Portal B2B 1(1.5) | C18: ALF | D18: =SUM(E18:CT18) -> 2 | K18: 2
C19: WAREX | D19: =SUM(E19:CT19) -> 0
C20: OPTIMUS | D20: =SUM(E20:CT20) -> 0
C21: MASH | D21: =SUM(E21:CT21) -> 2 | J21: 1 | M21: 1
C22: MAGENTO | D22: =SUM(E22:CT22) -> 27 | J22: 6 | K22: 3 | L22: 3 | M22: 3 | N22: 2 | R22: 5 | S22: 5
A23: 0 | B23: Project - Multibrand for iMad | C23: ALF | D23: =SUM(E23:CT23) -> 2 | K23: 2
C24: WAREX | D24: =SUM(E24:CT24) -> 0
C25: OPTIMUS | D25: =SUM(E25:CT25) -> 0
C26: MASH | D26: =SUM(E26:CT26) -> 1 | K26: 1
C27: MAGENTO | D27: =SUM(E27:CT27) -> 35 | K27: 5 | L27: 5 | M27: 5 | Q27: 5 | R27: 5 | S27: 5 | T27: 5
A28: 0 | B28: Project - Malezja Faza 1A | C28: ALF | D28: =SUM(E28:CT28) -> 8.5 | K28: 1 | L28: 1 | M28: 0.5 | O28: 1 | P28: 3 | Q28: 2
C29: WAREX | D29: =SUM(E29:CT29) -> 1 | M29: 0.5 | N29: 0.5
C30: OPTIMUS | D30: =SUM(E30:CT30) -> 8 | P30: 0.5 | Q30: 0.5 | R30: 5 | S30: 2
C31: MASH | D31: =SUM(E31:CT31) -> 25 | H31: 1 | I31: 2 | J31: 3 | K31: 3 | L31: 2 | M31: 3 | N31: 1 | P31: 0.5 | Q31: 1 | R31: 0.5 | S31: 1 | T31: 2 | U31: 1 | AB31: 2 | AC31: 2
C32: MAGENTO | D32: =SUM(E32:CT32) -> 98 | J32: 6 | K32: 15 | L32: 10 | M32: 5 | N32: 15 | O32: 15 | P32: 10 | Q32: 5 | R32: 4 | S32: 4 | T32: 3 | AD32: 3 | AE32: 3
A33: 0 | B33: MM Open Days: Faza1 - 22/05 | C33: ALF | D33: =SUM(E33:CT33) -> 25 | K33: 5 | L33: 5 | M33: 5 | N33: 5 | O33: 5
C34: WAREX | D34: =SUM(E34:CT34) -> 2 | N34: 2
C35: OPTIMUS | D35: =SUM(E35:CT35) -> 0
C36: MASH | D36: =SUM(E36:CT36) -> 15 | K36: 3 | L36: 5 | M36: 3 | N36: 2 | O36: 2
C37: MAGENTO | D37: =SUM(E37:CT37) -> 10 | N37: 5 | O37: 5
A38: 0 | B38: MM Open Days: Faza2 - 03/06 | C38: ALF | D38: =SUM(E38:CT38) -> 0
C39: WAREX | D39: =SUM(E39:CT39) -> 0
C40: OPTIMUS | D40: =SUM(E40:CT40) -> 0
C41: MASH | D41: =SUM(E41:CT41) -> 0
C42: MAGENTO | D42: =SUM(E42:CT42) -> 4 | P42: 4
A43: 0 | B43: Open Days tMobile - 23/06 + Genetal Open Days Tasks | C43: ALF | D43: =SUM(E43:CT43) -> 0
C44: WAREX | D44: =SUM(E44:CT44) -> 0
C45: OPTIMUS | D45: =SUM(E45:CT45) -> 0
C46: MASH | D46: =SUM(E46:CT46) -> 0
C47: MAGENTO | D47: =SUM(E47:CT47) -> 12 | Q47: 4 | R47: 3 | S47: 5
A48: 0 | B48: PLAY New Assortment Groups | C48: ALF | D48: =SUM(E48:CT48) -> 0
C49: WAREX | D49: =SUM(E49:CT49) -> 44 | H49: 3 | I49: 3 | J49: 3 | K49: 8 | L49: 3 | M49: 12 | N49: 8 | O49: 2 | Q49: 1 | R49: 1
C50: OPTIMUS | D50: =SUM(E50:CT50) -> 29 | P50: 5 | Q50: 10 | R50: 10 | S50: 3 | T50: 1
C51: MASH | D51: =SUM(E51:CT51) -> 0
C52: MAGENTO | D52: =SUM(E52:CT52) -> 0
A53: 0 | B53: Inicjatywa PLK karta usług (B2B Enterprise + Frontend) | C53: ALF | D53: =SUM(E53:CT53) -> 0
C54: WAREX | D54: =SUM(E54:CT54) -> 105 | H54: 5 | I54: 5 | J54: 5 | K54: 6 | L54: 3 | M54: 8 | N54: 8 | O54: 9 | P54: 9 | Q54: 4 | R54: 4 | S54: 8 | T54: 4 | U54: 5 | V54: 3 | W54: 4 | X54: 4 | Y54: 3 | Z54: 2 | AA54: 3 | AB54: 1 | AC54: 2
C55: OPTIMUS | D55: =SUM(E55:CT55) -> 22 | U55: 1 | AA55: 1 | AB55: 8 | AC55: 7 | AD55: 2 | AE55: 3
C56: MASH | D56: =SUM(E56:CT56) -> 0
C57: MAGENTO | D57: =SUM(E57:CT57) -> 0
A58: 0 | B58: JET (zmiana leasingu na najem do 27 maja) | C58: ALF | D58: =SUM(E58:CT58) -> 10 | N58: 2 | O58: 5 | Q58: 3
C59: WAREX | D59: =SUM(E59:CT59) -> 0
C60: OPTIMUS | D60: =SUM(E60:CT60) -> 0
C61: MASH | D61: =SUM(E61:CT61) -> 0
C62: MAGENTO | D62: =SUM(E62:CT62) -> 0
A63: 0 | B63: ALLPSI | C63: ALF | D63: =SUM(E63:CT63) -> 36 | N63: 2 | O63: 5 | P63: 5 | Q63: 6 | R63: 5 | S63: 4 | T63: 2 | U63: 2 | V63: 2 | W63: 3
C64: WAREX | D64: =SUM(E64:CT64) -> 0
C65: OPTIMUS | D65: =SUM(E65:CT65) -> 0
C66: MASH | D66: =SUM(E66:CT66) -> 10 | M66: 1 | N66: 3 | O66: 1 | P66: 1 | Q66: 1 | R66: 1 | S66: 1 | T66: 1
C67: MAGENTO | D67: =SUM(E67:CT67) -> 0
A68: 0 | B68: PHOX (iMad Now) | C68: ALF | D68: =SUM(E68:CT68) -> 0
C69: WAREX | D69: =SUM(E69:CT69) -> 0
C70: OPTIMUS | D70: =SUM(E70:CT70) -> 0
C71: MASH | D71: =SUM(E71:CT71) -> 0
C72: MAGENTO | D72: 0
A73: 0 | B73: (BIK) Antyfraud CFD | C73: ALF | D73: =SUM(E73:CT73) -> 0
C74: WAREX | D74: =SUM(E74:CT74) -> 0
C75: OPTIMUS | D75: =SUM(E75:CT75) -> 0
C76: MASH | D76: =SUM(E76:CT76) -> 22 | M76: 1 | N76: 1 | O76: 1 | P76: 0.5 | Q76: 1 | R76: 1 | S76: 3 | T76: 3 | U76: 2 | V76: 2 | W76: 2 | X76: 0.5 | Y76: 0.5 | Z76: 0.5 | AA76: 1 | AB76: 1 | AC76: 1
C77: MAGENTO | D77: =SUM(E77:CT77) -> 37 | R77: 2 | S77: 5 | T77: 3 | U77: 3 | V77: 3 | W77: 3 | X77: 5 | Y77: 5 | Z77: 2 | AA77: 2 | AB77: 2 | AC77: 2
A78: 0 | B78: Inicjatywa API PLAY | C78: ALF | D78: =SUM(E78:CT78) -> 0
C79: WAREX | D79: =SUM(E79:CT79) -> 0
C80: OPTIMUS | D80: =SUM(E80:CT80) -> 72 | T80: 1 | U80: 2 | V80: 2 | W80: 2 | X80: 2 | Y80: 5 | Z80: 10 | AA80: 3 | AB80: 5 | AC80: 5 | AD80: 3 | AE80: 3 | AF80: 3 | AG80: 3 | AH80: 3 | AI80: 1 | AJ80: 2 | AK80: 5 | AL80: 2 | AM80: 2 | AN80: 2 | AO80: 2 | AP80: 1 | AQ80: 1 | AR80: 1 | AS80: 1
C81: MASH | D81: =SUM(E81:CT81) -> 0
C82: MAGENTO | D82: =SUM(E82:CT82) -> 0
A83: 0 | B83: Decision Cube | C83: ALF | D83: =SUM(E83:CT83) -> 117 | U83: 5 | V83: 5 | W83: 5 | X83: 5 | Y83: 5 | Z83: 5 | AA83: 5 | AB83: 5 | AC83: 5 | AD83: 3 | AE83: 5 | AF83: 6 | AG83: 6 | AH83: 5 | AI83: 5 | AJ83: 3 | AK83: 3 | AL83: 3 | AM83: 3 | AN83: 3 | AO83: 3 | AP83: 3 | AQ83: 3 | AR83: 3 | AS83: 3 | AV83: 3 | AW83: 3 | AX83: 3 | AY83: 3
C84: WAREX | D84: =SUM(E84:CT84) -> 0
C85: OPTIMUS | D85: =SUM(E85:CT85) -> 0
C86: MASH | D86: =SUM(E86:CT86) -> 0
C87: MAGENTO | D87: =SUM(E87:CT87) -> 0
A88: 0 | B88: Dynamic Pricing | C88: ALF | D88: =SUM(E88:CT88) -> 30 | AH88: 2 | AI88: 3 | AJ88: 3 | AK88: 5 | AL88: 5 | AM88: 5 | AN88: 5 | AO88: 1 | AP88: 1
C89: WAREX | D89: =SUM(E89:CT89) -> 0
C90: OPTIMUS | D90: =SUM(E90:CT90) -> 0
C91: MASH | D91: =SUM(E91:CT91) -> 10 | AI91: 2 | AJ91: 2 | AK91: 1 | AL91: 1 | AM91: 1 | AN91: 1 | AO91: 1 | AP91: 1
C92: MAGENTO | D92: =SUM(E92:CT92) -> 0
A93: 0 | B93: Paperless | C93: ALF | D93: =SUM(E93:CT93) -> 14 | AM93: 2 | AN93: 2 | AO93: 2 | AP93: 2 | AQ93: 2 | AR93: 2 | AS93: 2
C94: WAREX | D94: =SUM(E94:CT94) -> 0
C95: OPTIMUS | D95: =SUM(E95:CT95) -> 0
C96: MASH | D96: =SUM(E96:CT96) -> 0
C97: MAGENTO | D97: =SUM(E97:CT97) -> 0
B98: Upgrade | C98: ALF | D98: =SUM(E98:CT98) -> 38 | AQ98: 5 | AR98: 5 | AS98: 5 | AV98: 3 | AW98: 5 | AX98: 5 | AY98: 5 | AZ98: 5
C99: WAREX | D99: =SUM(E99:CT99) -> 0
C100: OPTIMUS | D100: =SUM(E100:CT100) -> 0
...

Sheet WORKLOAD_TEAMS (7)
A1: PRIORYTET | B1: DATE | C1: DATE | D1: TOTALS | E1: =TEXT(DATE(2024,1,1)+(E2-1)*7-WEEKDAY(DATE(2024,1,1),2)+1,"dd.mm")&"-"&TEXT(DATE(2024,1,1)+(E2-1)*7-WEEKDAY(DATE(2024,1,1),2)+7,"dd.mm") -> 11.03-17.03 | F1: =TEXT(DATE(2024,1,1)+(F2-1)*7-WEEKDAY(DATE(2024,1,1),2)+1,"dd.mm")&"-"&TEXT(DATE(2024,1,1)+(F2-1)*7-WEEKDAY(DATE(2024,1,1),2)+7,"dd.mm") -> 18.03-24.03 | G1: =TEXT(DATE(2024,1,1)+(G2-1)*7-WEEKDAY(DATE(2024,1,1),2)+1,"dd.mm")&"-"&TEXT(DATE(2024,1,1)+(G2-1)*7-WEEKDAY(DATE(2024,1,1),2)+7,"dd.mm") -> 25.03-31.03 | H1: =TEXT(DATE(2024,1,1)+(H2-1)*7-WEEKDAY(DATE(2024,1,1),2)+1,"dd.mm")&"-"&TEXT(DATE(2024,1,1)+(H2-1)*7-WEEKDAY(DATE(2024,1,1),2)+7,"dd.mm") -> 01.04-07.04 | I1: =TEXT(DATE(2024,1,1)+(I2-1)*7-WEEKDAY(DATE(2024,1,1),2)+1,"dd.mm")&"-"&TEXT(DATE(2024,1,1)+(I2-1)*7-WEEKDAY(DATE(2024,1,1),2)+7,"dd.mm") -> 08.04-14.04 | J1: =TEXT(DATE(2024,1,1)+(J2-1)*7-WEEKDAY(DATE(2024,1,1),2)+1,"dd.mm")&"-"&TEXT(DATE(2024,1,1)+(J2-1)*7-WEEKDAY(DATE(2024,1,1),2)+7,"dd.mm") -> 15.04-21.04 | K1: =TEXT(DATE(2024,1,1)+(K2-1)*7-WEEKDAY(DATE(2024,1,1),2)+1,"dd.mm")&"-"&TEXT(DATE(2024,1,1)+(K2-1)*7-WEEKDAY(DATE(2024,1,1),2)+7,"dd.mm") -> 22.04-28.04 | L1: =TEXT(DATE(2024,1,1)+(L2-1)*7-WEEKDAY(DATE(2024,1,1),2)+1,"dd.mm")&"-"&TEXT(DATE(2024,1,1)+(L2-1)*7-WEEKDAY(DATE(2024,1,1),2)+7,"dd.mm") -> 29.04-05.05 | ... AT1: =TEXT(DATE(2024,1,1)+(AT2-1)*7-WEEKDAY(DATE(2024,1,1),2)+1,"dd.mm")&"-"&TEXT(DATE(2024,1,1)+(AT2-1)*7-WEEKDAY(DATE(2024,1,1),2)+7,"dd.mm") -> 23.12-29.12 | AU1: =TEXT(DATE(2025,1,1)+(AU2-1)*7-WEEKDAY(DATE(2025,1,1),2)+1,"dd.mm")&"-"&TEXT(DATE(2025,1,1)+(AU2-1)*7-WEEKDAY(DATE(2025,1,1),2)+7,"dd.mm") -> 30.12-05.01 | AV1: =TEXT(DATE(2025,1,1)+(AV2-1)*7-WEEKDAY(DATE(2025,1,1),2)+1,"dd.mm")&"-"&TEXT(DATE(2025,1,1)+(AV2-1)*7-WEEKDAY(DATE(2025,1,1),2)+7,"dd.mm") -> 06.01-12.01 | AW1: =TEXT(DATE(2025,1,1)+(AW2-1)*7-WEEKDAY(DATE(2025,1,1),2)+1,"dd.mm")&"-"&TEXT(DATE(2025,1,1)+(AW2-1)*7-WEEKDAY(DATE(2025,1,1),2)+7,"dd.mm") -> 13.01-19.01 | AX1: =TEXT(DATE(2025,1,1)+(AX2-1)*7-WEEKDAY(DATE(2025,1,1),2)+1,"dd.mm")&"-"&TEXT(DATE(2025,1,1)+(AX2-1)*7-WEEKDAY(DATE(2025,1,1),2)+7,"dd.mm") -> 20.01-26.01 | AY1: =TEXT(DATE(2025,1,1)+(AY2-1)*7-WEEKDAY(DATE(2025,1,1),2)+1,"dd.mm")&"-"&TEXT(DATE(2025,1,1)+(AY2-1)*7-WEEKDAY(DATE(2025,1,1),2)+7,"dd.mm") -> 27.01-02.02 | AZ1: =TEXT(DATE(2025,1,1)+(AZ2-1)*7-WEEKDAY(DATE(2025,1,1),2)+1,"dd.mm")&"-"&TEXT(DATE(2025,1,1)+(AZ2-1)*7-WEEKDAY(DATE(2025,1,1),2)+7,"dd.mm") -> 03.02-09.02 | BA1: =TEXT(DATE(2025,1,1)+(BA2-1)*7-WEEKDAY(DATE(2025,1,1),2)+1,"dd.mm")&"-"&TEXT(DATE(2025,1,1)+(BA2-1)*7-WEEKDAY(DATE(2025,1,1),2)+7,"dd.mm") -> 10.02-16.02 | BB1: =TEXT(DATE(2025,1,1)+(BB2-1)*7-WEEKDAY(DATE(2025,1,1),2)+1,"dd.mm")&"-"&TEXT(DATE(2025,1,1)+(BB2-1)*7-WEEKDAY(DATE(2025,1,1),2)+7,"dd.mm") -> 17.02-23.02 | ... CT1: =TEXT(DATE(2025,1,1)+(CT2-1)*7-WEEKDAY(DATE(2025,1,1),2)+1,"dd.mm")&"-"&TEXT(DATE(2025,1,1)+(CT2-1)*7-WEEKDAY(DATE(2025,1,1),2)+7,"dd.mm") -> 22.12-28.12
C2: WEEK | E2: 11 | F2: 12 | G2: 13 | H2: 14 | I2: 15 | J2: 16 | K2: 17 | L2: 18 | M2: 19 | N2: 20 | O2: 21 | P2: 22 | Q2: 23 | R2: 24 | S2: 25 | T2: 26 | U2: 27 | V2: 28 | W2: 29 | X2: 30 | Y2: 31 | Z2: 32 | AA2: 33 | AB2: 34 | AC2: 35 | AD2: 36 | AE2: 37 | AF2: 38 | AG2: 39 | AH2: 40 | AI2: 41 | AJ2: 42 | AK2: 43 | AL2: 44 | AM2: 45 | AN2: 46 | AO2: 47 | AP2: 48 | AQ2: 49 | AR2: 50 | AS2: 51 | AT2: 52 | AU2: 1 | AV2: 2 | AW2: 3 | AX2: 4 | AY2: 5 | AZ2: 6 | BA2: 7 | BB2: 8 | BC2: 9 | BD2: 10 | BE2: 11 | BF2: 12 | BG2: 13 | BH2: 14 | BI2: 15 | BJ2: 16 | BK2: 17 | BL2: 18 | BM2: 19 | BN2: 20 | BO2: 21 | BP2: 22 | BQ2: 23 | BR2: 24 | BS2: 25 | BT2: 26 | BU2: 27 | BV2: 28 | BW2: 29 | BX2: 30 | BY2: 31 | BZ2: 32 | CA2: 33 | CB2: 34 | CC2: 35 | CD2: 36 | CE2: 37 | CF2: 38 | CG2: 39 | CH2: 40 | CI2: 41 | CJ2: 42 | CK2: 43 | CL2: 44 | CM2: 45 | CN2: 46 | CO2: 47 | CP2: 48 | CQ2: 49 | CR2: 50 | CS2: 51 | CT2: 52
B3: PROJECTS & FUNCTIONALITIES CAPACITY | C3: ALF | E3: =CAPACITY!G2 -> 27.342 | F3: =OFFSET(CAPACITY!$G$2,0,7*(F$2-$E$2)) -> 27.342 | G3: =OFFSET(CAPACITY!$G$2,0,7*(G$2-$E$2)) -> 27.342 | H3: =OFFSET(CAPACITY!$G$2,0,7*(H$2-$E$2)) -> 21.462 | I3: =OFFSET(CAPACITY!$G$2,0,7*(I$2-$E$2)) -> 27.342 | J3: =OFFSET(CAPACITY!$G$2,0,7*(J$2-$E$2)) -> 27.342 | K3: =OFFSET(CAPACITY!$G$2,0,7*(K$2-$E$2)) -> 27.342 | L3: =OFFSET(CAPACITY!$G$2,0,7*(L$2-$E$2)) -> 14.028 | M3: =OFFSET(CAPACITY!$G$2,0,7*(M$2-$E$2)) -> 28.371 | ... AT3: =OFFSET(CAPACITY!$G$2,0,7*(AT$2-$E$2)) -> 12.39 | AU3: =OFFSET(CAPACITY!$G$2,0,7*(AU$2+52-$E$2)) -> 17.346 | AV3: =OFFSET(CAPACITY!$G$2,0,7*(AV$2+52-$E$2)) -> 23.247 | AW3: =OFFSET(CAPACITY!$G$2,0,7*(AW$2+52-$E$2)) -> 28.728 | AX3: =OFFSET(CAPACITY!$G$2,0,7*(AX$2+52-$E$2)) -> 28.728 | AY3: =OFFSET(CAPACITY!$G$2,0,7*(AY$2+52-$E$2)) -> 26.439 | AZ3: =OFFSET(CAPACITY!$G$2,0,7*(AZ$2+52-$E$2)) -> 28.455 | BA3: =OFFSET(CAPACITY!$G$2,0,7*(BA$2+52-$E$2)) -> 27.342 | BB3: =OFFSET(CAPACITY!$G$2,0,7*(BB$2+52-$E$2)) -> 28.581 | ... CT3: =OFFSET(CAPACITY!$G$2,0,7*(CT$2+52-$E$2)) -> 9.66
C4: WAREX | E4: =CAPACITY!G4 -> 10.388559 | F4: =OFFSET(CAPACITY!$G$4,0,7*(F$2-$E$2)) -> 10.388559 | G4: =OFFSET(CAPACITY!$G$4,0,7*(G$2-$E$2)) -> 10.388559 | H4: =OFFSET(CAPACITY!$G$4,0,7*(H$2-$E$2)) -> 8.1544599 | I4: =OFFSET(CAPACITY!$G$4,0,7*(I$2-$E$2)) -> 10.388559 | J4: =OFFSET(CAPACITY!$G$4,0,7*(J$2-$E$2)) -> 10.069402 | K4: =OFFSET(CAPACITY!$G$4,0,7*(K$2-$E$2)) -> 10.388559 | L4: =OFFSET(CAPACITY!$G$4,0,7*(L$2-$E$2)) -> 1.9149417 | M4: =OFFSET(CAPACITY!$G$4,0,7*(M$2-$E$2)) -> 9.4310877 | ... AT4: =OFFSET(CAPACITY!$G$4,0,7*(AT$2-$E$2)) -> 9.4151298 | AU4: =OFFSET(CAPACITY!$G$4,0,7*(AU$2+52-$E$2)) -> 13.181182 | AV4: =OFFSET(CAPACITY!$G$4,0,7*(AV$2+52-$E$2)) -> 17.665337 | AW4: =OFFSET(CAPACITY!$G$4,0,7*(AW$2+52-$E$2)) -> 21.830335 | AX4: =OFFSET(CAPACITY!$G$4,0,7*(AX$2+52-$E$2)) -> 21.830335 | AY4: =OFFSET(CAPACITY!$G$4,0,7*(AY$2+52-$E$2)) -> 20.09093 | AZ4: =OFFSET(CAPACITY!$G$4,0,7*(AZ$2+52-$E$2)) -> 21.622883 | BA4: =OFFSET(CAPACITY!$G$4,0,7*(BA$2+52-$E$2)) -> 20.777117 | BB4: =OFFSET(CAPACITY!$G$4,0,7*(BB$2+52-$E$2)) -> 21.71863 | ... CT4: =OFFSET(CAPACITY!$G$4,0,7*(CT$2+52-$E$2)) -> 7.3406097
C5: OPTIMUS | E5: =CAPACITY!G6 -> 21.241748 | F5: =OFFSET(CAPACITY!$G$6,0,7*(F$2-$E$2)) -> 21.241748 | G5: =OFFSET(CAPACITY!$G$6,0,7*(G$2-$E$2)) -> 21.241748 | H5: =OFFSET(CAPACITY!$G$6,0,7*(H$2-$E$2)) -> 16.67363 | I5: =OFFSET(CAPACITY!$G$6,0,7*(I$2-$E$2)) -> 21.241748 | J5: =OFFSET(CAPACITY!$G$6,0,7*(J$2-$E$2)) -> 21.241748 | K5: =OFFSET(CAPACITY!$G$6,0,7*(K$2-$E$2)) -> 21.241748 | L5: =OFFSET(CAPACITY!$G$6,0,7*(L$2-$E$2)) -> 8.995678 | M5: =OFFSET(CAPACITY!$G$6,0,7*(M$2-$E$2)) -> 18.395459 | ... AT5: =OFFSET(CAPACITY!$G$6,0,7*(AT$2-$E$2)) -> 7.9063577 | AU5: =OFFSET(CAPACITY!$G$6,0,7*(AU$2+52-$E$2)) -> 12.281209 | AV5: =OFFSET(CAPACITY!$G$6,0,7*(AV$2+52-$E$2)) -> 14.705825 | AW5: =OFFSET(CAPACITY!$G$6,0,7*(AW$2+52-$E$2)) -> 20.082148 | AX5: =OFFSET(CAPACITY!$G$6,0,7*(AX$2+52-$E$2)) -> 20.082148 | AY5: =OFFSET(CAPACITY!$G$6,0,7*(AY$2+52-$E$2)) -> 18.852271 | AZ5: =OFFSET(CAPACITY!$G$6,0,7*(AZ$2+52-$E$2)) -> 19.027967 | BA5: =OFFSET(CAPACITY!$G$6,0,7*(BA$2+52-$E$2)) -> 17.270999 | BB5: =OFFSET(CAPACITY!$G$6,0,7*(BB$2+52-$E$2)) -> 15.074789 | ... CT5: =OFFSET(CAPACITY!$G$6,0,7*(CT$2+52-$E$2)) -> 4.9195114
C6: MASH | E6: =CAPACITY!G8 -> 8.1375 | F6: =OFFSET(CAPACITY!$G$8,0,7*(F$2-$E$2)) -> 8.1375 | G6: =OFFSET(CAPACITY!$G$8,0,7*(G$2-$E$2)) -> 8.1375 | H6: =OFFSET(CAPACITY!$G$8,0,7*(H$2-$E$2)) -> 6.3875 | I6: =OFFSET(CAPACITY!$G$8,0,7*(I$2-$E$2)) -> 8.1375 | J6: =OFFSET(CAPACITY!$G$8,0,7*(J$2-$E$2)) -> 8.1375 | K6: =OFFSET(CAPACITY!$G$8,0,7*(K$2-$E$2)) -> 8.1375 | L6: =OFFSET(CAPACITY!$G$8,0,7*(L$2-$E$2)) -> 5.25 | M6: =OFFSET(CAPACITY!$G$8,0,7*(M$2-$E$2)) -> 8.1375 | ... AT6: =OFFSET(CAPACITY!$G$8,0,7*(AT$2-$E$2)) -> 2.205 | AU6: =OFFSET(CAPACITY!$G$8,0,7*(AU$2+52-$E$2)) -> 3.4825 | AV6: =OFFSET(CAPACITY!$G$8,0,7*(AV$2+52-$E$2)) -> 6.0375 | AW6: =OFFSET(CAPACITY!$G$8,0,7*(AW$2+52-$E$2)) -> 7.91 | AX6: =OFFSET(CAPACITY!$G$8,0,7*(AX$2+52-$E$2)) -> 7.21 | AY6: =OFFSET(CAPACITY!$G$8,0,7*(AY$2+52-$E$2)) -> 6.86 | AZ6: =OFFSET(CAPACITY!$G$8,0,7*(AZ$2+52-$E$2)) -> 6.7375 | BA6: =OFFSET(CAPACITY!$G$8,0,7*(BA$2+52-$E$2)) -> 6.16 | BB6: =OFFSET(CAPACITY!$G$8,0,7*(BB$2+52-$E$2)) -> 7.56 | ... CT6: =OFFSET(CAPACITY!$G$8,0,7*(CT$2+52-$E$2)) -> 3.15
C7: MAGENTO | E7: =CAPACITY!G10 -> 23.2875 | F7: =OFFSET(CAPACITY!$G$10,0,7*(F$2-$E$2)) -> 23.2875 | G7: =OFFSET(CAPACITY!$G$10,0,7*(G$2-$E$2)) -> 23.2875 | H7: =OFFSET(CAPACITY!$G$10,0,7*(H$2-$E$2)) -> 22.5375 | I7: =OFFSET(CAPACITY!$G$10,0,7*(I$2-$E$2)) -> 23.2875 | J7: =OFFSET(CAPACITY!$G$10,0,7*(J$2-$E$2)) -> 23.2875 | K7: =OFFSET(CAPACITY!$G$10,0,7*(K$2-$E$2)) -> 23.2875 | L7: =OFFSET(CAPACITY!$G$10,0,7*(L$2-$E$2)) -> 20.25 | M7: =OFFSET(CAPACITY!$G$10,0,7*(M$2-$E$2)) -> 24.1575 | ... AT7: =OFFSET(CAPACITY!$G$10,0,7*(AT$2-$E$2)) -> 12.1125 | AU7: =OFFSET(CAPACITY!$G$10,0,7*(AU$2+52-$E$2)) -> 15.6675 | AV7: =OFFSET(CAPACITY!$G$10,0,7*(AV$2+52-$E$2)) -> 19.18875 | AW7: =OFFSET(CAPACITY!$G$10,0,7*(AW$2+52-$E$2)) -> 24.1575 | AX7: =OFFSET(CAPACITY!$G$10,0,7*(AX$2+52-$E$2)) -> 24.1575 | AY7: =OFFSET(CAPACITY!$G$10,0,7*(AY$2+52-$E$2)) -> 24.1575 | AZ7: =OFFSET(CAPACITY!$G$10,0,7*(AZ$2+52-$E$2)) -> 24.1575 | BA7: =OFFSET(CAPACITY!$G$10,0,7*(BA$2+52-$E$2)) -> 24.1575 | BB7: =OFFSET(CAPACITY!$G$10,0,7*(BB$2+52-$E$2)) -> 24.1575 | ... CT7: =OFFSET(CAPACITY!$G$10,0,7*(CT$2+52-$E$2)) -> 7.5
B8: PROJECTS & FUNCTIONALITIES CAPACITY UTILISATION | C8: ALF | E8: =E3-SUMIF($C$14:$C$462,$C8,E14:E462) -> 15.342 | F8: =F3-SUMIF($C$14:$C$462,$C8,F14:F462) -> 15.342 | G8: =G3-SUMIF($C$14:$C$462,$C8,G14:G462) -> 15.342 | H8: =H3-SUMIF($C$14:$C$462,$C8,H14:H462) -> 9.462 | I8: =I3-SUMIF($C$14:$C$462,$C8,I14:I462) -> 15.342 | J8: =J3-SUMIF($C$14:$C$462,$C8,J14:J462) -> 10.342 | K8: =K3-SUMIF($C$14:$C$462,$C8,K14:K462) -> -4.658 | L8: =L3-SUMIF($C$14:$C$462,$C8,L14:L462) -> -8.972 | ... CT8: =CT3-SUMIF($C$14:$C$462,$C8,CT14:CT462) -> -2.34
C9: WAREX | E9: =E4-SUMIF($C$14:$C$462,$C9,E14:E462) -> 10.388559 | F9: =F4-SUMIF($C$14:$C$462,$C9,F14:F462) -> 10.388559 | G9: =G4-SUMIF($C$14:$C$462,$C9,G14:G462) -> 10.388559 | H9: =H4-SUMIF($C$14:$C$462,$C9,H14:H462) -> 0.15445992 | I9: =I4-SUMIF($C$14:$C$462,$C9,I14:I462) -> 2.3885585 | J9: =J4-SUMIF($C$14:$C$462,$C9,J14:J462) -> 2.0694016 | K9: =K4-SUMIF($C$14:$C$462,$C9,K14:K462) -> -3.6114415 | L9: =L4-SUMIF($C$14:$C$462,$C9,L14:L462) -> -4.0850583 | ... CT9: =CT4-SUMIF($C$14:$C$462,$C9,CT14:CT462) -> 7.3406097
C10: OPTIMUS | E10: =E5-SUMIF($C$14:$C$462,$C10,E14:E462) -> 21.241748 | F10: =F5-SUMIF($C$14:$C$462,$C10,F14:F462) -> 21.241748 | G10: =G5-SUMIF($C$14:$C$462,$C10,G14:G462) -> 21.241748 | H10: =H5-SUMIF($C$14:$C$462,$C10,H14:H462) -> 16.67363 | I10: =I5-SUMIF($C$14:$C$462,$C10,I14:I462) -> 21.241748 | J10: =J5-SUMIF($C$14:$C$462,$C10,J14:J462) -> 21.241748 | K10: =K5-SUMIF($C$14:$C$462,$C10,K14:K462) -> 21.241748 | L10: =L5-SUMIF($C$14:$C$462,$C10,L14:L462) -> 8.995678 | ... CT10: =CT5-SUMIF($C$14:$C$462,$C10,CT14:CT462) -> 4.9195114
C11: MASH | E11: =E6-SUMIF($C$14:$C$462,$C11,E14:E462) -> 7.6375 | F11: =F6-SUMIF($C$14:$C$462,$C11,F14:F462) -> 7.6375 | G11: =G6-SUMIF($C$14:$C$462,$C11,G14:G462) -> 7.6375 | H11: =H6-SUMIF($C$14:$C$462,$C11,H14:H462) -> 4.8875 | I11: =I6-SUMIF($C$14:$C$462,$C11,I14:I462) -> 5.6375 | J11: =J6-SUMIF($C$14:$C$462,$C11,J14:J462) -> 3.6375 | K11: =K6-SUMIF($C$14:$C$462,$C11,K14:K462) -> 0.6375 | L11: =L6-SUMIF($C$14:$C$462,$C11,L14:L462) -> -2.25 | ... CT11: =CT6-SUMIF($C$14:$C$462,$C11,CT14:CT462) -> 2.65
C12: MAGENTO | E12: =E7-SUMIF($C$14:$C$462,$C12,E14:E462) -> 23.2875 | F12: =F7-SUMIF($C$14:$C$462,$C12,F14:F462) -> 23.2875 | G12: =G7-SUMIF($C$14:$C$462,$C12,G14:G462) -> 23.2875 | H12: =H7-SUMIF($C$14:$C$462,$C12,H14:H462) -> 22.5375 | I12: =I7-SUMIF($C$14:$C$462,$C12,I14:I462) -> 23.2875 | J12: =J7-SUMIF($C$14:$C$462,$C12,J14:J462) -> 11.2875 | K12: =K7-SUMIF($C$14:$C$462,$C12,K14:K462) -> 0.2875 | L12: =L7-SUMIF($C$14:$C$462,$C12,L14:L462) -> 2.25 | ... CT12: =CT7-SUMIF($C$14:$C$462,$C12,CT14:CT462) -> 7.5
A14: 1 | B14: DŁUG FUNKCJONALNY ALF | C14: ALF | D14: =SUM(E14:CT14) -> 1104 | E14: 12 | F14: 12 | G14: 12 | H14: 12 | I14: 12 | J14: 12 | K14: 12 | L14: 12 | M14: 12 | N14: 12 | O14: 12 | P14: 12 | Q14: 12 | R14: 12 | S14: 12 | T14: 12 | U14: 12 | V14: 12 | W14: 12 | X14: 12 | Y14: 12 | Z14: 12 | AA14: 12 | AB14: 12 | AC14: 12 | AD14: 12 | AE14: 12 | AF14: 12 | AG14: 12 | AH14: 12 | AI14: 12 | AJ14: 12 | AK14: 12 | AL14: 12 | AM14: 12 | AN14: 12 | AO14: 12 | AP14: 12 | AQ14: 12 | AR14: 12 | AS14: 12 | AV14: 12 | AW14: 12 | AX14: 12 | AY14: 12 | AZ14: 12 | BA14: 12 | BB14: 12 | BC14: 12 | BD14: 12 | BE14: 12 | BF14: 12 | BG14: 12 | BH14: 12 | BI14: 12 | BJ14: 12 | BK14: 12 | BL14: 12 | BM14: 12 | BN14: 12 | BO14: 12 | BP14: 12 | BQ14: 12 | BR14: 12 | BS14: 12 | BT14: 12 | BU14: 12 | BV14: 12 | BW14: 12 | BX14: 12 | BY14: 12 | BZ14: 12 | CA14: 12 | CB14: 12 | CC14: 12 | CD14: 12 | CE14: 12 | CF14: 12 | CG14: 12 | CH14: 12 | CI14: 12 | CJ14: 12 | CK14: 12 | CL14: 12 | CM14: 12 | CN14: 12 | CO14: 12 | CP14: 12 | CQ14: 12 | CR14: 12 | CS14: 12 | CT14: 12
C15: WAREX | D15: =SUM(E15:CT15) -> 0
C16: OPTIMUS | D16: =SUM(E16:CT16) -> 0
C17: MASH | D17: =SUM(E17:CT17) -> 46 | E17: 0.5 | F17: 0.5 | G17: 0.5 | H17: 0.5 | I17: 0.5 | J17: 0.5 | K17: 0.5 | L17: 0.5 | M17: 0.5 | N17: 0.5 | O17: 0.5 | P17: 0.5 | Q17: 0.5 | R17: 0.5 | S17: 0.5 | T17: 0.5 | U17: 0.5 | V17: 0.5 | W17: 0.5 | X17: 0.5 | Y17: 0.5 | Z17: 0.5 | AA17: 0.5 | AB17: 0.5 | AC17: 0.5 | AD17: 0.5 | AE17: 0.5 | AF17: 0.5 | AG17: 0.5 | AH17: 0.5 | AI17: 0.5 | AJ17: 0.5 | AK17: 0.5 | AL17: 0.5 | AM17: 0.5 | AN17: 0.5 | AO17: 0.5 | AP17: 0.5 | AQ17: 0.5 | AR17: 0.5 | AS17: 0.5 | AV17: 0.5 | AW17: 0.5 | AX17: 0.5 | AY17: 0.5 | AZ17: 0.5 | BA17: 0.5 | BB17: 0.5 | BC17: 0.5 | BD17: 0.5 | BE17: 0.5 | BF17: 0.5 | BG17: 0.5 | BH17: 0.5 | BI17: 0.5 | BJ17: 0.5 | BK17: 0.5 | BL17: 0.5 | BM17: 0.5 | BN17: 0.5 | BO17: 0.5 | BP17: 0.5 | BQ17: 0.5 | BR17: 0.5 | BS17: 0.5 | BT17: 0.5 | BU17: 0.5 | BV17: 0.5 | BW17: 0.5 | BX17: 0.5 | BY17: 0.5 | BZ17: 0.5 | CA17: 0.5 | CB17: 0.5 | CC17: 0.5 | CD17: 0.5 | CE17: 0.5 | CF17: 0.5 | CG17: 0.5 | CH17: 0.5 | CI17: 0.5 | CJ17: 0.5 | CK17: 0.5 | CL17: 0.5 | CM17: 0.5 | CN17: 0.5 | CO17: 0.5 | CP17: 0.5 | CQ17: 0.5 | CR17: 0.5 | CS17: 0.5 | CT17: 0.5
C18: MAGENTO | D18: =SUM(E18:CT18) -> 0
A19: 3 | B19: Coverwise | C19: ALF | D19: =SUM(E19:CT19) -> 0
C20: WAREX | D20: =SUM(E20:CT20) -> 101 | AZ20: 5 | BA20: 5 | BB20: 5 | BC20: 7 | BD20: 10 | BE20: 10 | BF20: 7 | BG20: 7 | BH20: 5 | BI20: 5 | BJ20: 5 | BK20: 5 | BL20: 5 | BM20: 5 | BN20: 5 | BO20: 5 | BP20: 5
C21: OPTIMUS | D21: =SUM(E21:CT21) -> 160 | AZ21: 5 | BA21: 5 | BB21: 5 | BC21: 5 | BD21: 5 | BE21: 10 | BF21: 10 | BG21: 10 | BH21: 10 | BI21: 10 | BJ21: 10 | BK21: 10 | BL21: 10 | BM21: 10 | BN21: 10 | BO21: 10 | BP21: 10 | BQ21: 5 | BR21: 5 | BS21: 5
C22: MASH | D22: =SUM(E22:CT22) -> 0
C23: MAGENTO | D23: =SUM(E23:CT23) -> 0
A24: 5 | B24: Worten | C24: ALF | D24: =SUM(E24:CT24) -> 80 | BJ24: 5 | BK24: 5 | BL24: 10 | BM24: 10 | BN24: 10 | BO24: 10 | BP24: 10 | BQ24: 10 | BR24: 10
C25: WAREX | D25: =SUM(E25:CT25) -> 24 | BL25: 3 | BM25: 5 | BN25: 5 | BO25: 5 | BP25: 3 | BQ25: 3
C26: OPTIMUS | D26: =SUM(E26:CT26) -> 31 | BM26: 2 | BN26: 2 | BO26: 2 | BP26: 5 | BQ26: 5 | BR26: 10 | BS26: 5
C27: MASH | D27: =SUM(E27:CT27) -> 36 | BI27: 5 | BJ27: 5 | BK27: 5 | BL27: 7 | BM27: 7 | BN27: 7
C28: MAGENTO | D28: =SUM(E28:CT28) -> 95 | BI28: 5 | BJ28: 10 | BK28: 10 | BL28: 10 | BM28: 10 | BN28: 10 | BO28: 10 | BP28: 10 | BQ28: 10 | BR28: 10
A29: 6 | B29: Melon | C29: ALF | D29: =SUM(E29:CT29) -> 37 | BL29: 1 | BM29: 2 | BN29: 2 | BO29: 7 | BP29: 7 | BQ29: 6 | BR29: 6 | BS29: 6
C30: WAREX | D30: =SUM(E30:CT30) -> 0
C31: OPTIMUS | D31: =SUM(E31:CT31) -> 0
C32: MASH | D32: =SUM(E32:CT32) -> 66 | BO32: 5 | BP32: 5 | BQ32: 7 | BR32: 7 | BS32: 7 | BT32: 7 | BU32: 7 | BV32: 7 | BW32: 7 | BX32: 7
C33: MAGENTO | D33: =SUM(E33:CT33) -> 0
A34: 8 | B34: Dynamic Pricing | C34: ALF | D34: =SUM(E34:CT34) -> 36 | AH34: 2 | AI34: 3 | AJ34: 3 | AK34: 5 | AL34: 5 | AM34: 5 | AN34: 5 | AO34: 1 | AP34: 1 | BH34: 1 | BI34: 1 | BJ34: 1 | BK34: 1 | BL34: 1 | BM34: 1
C35: WAREX | D35: =SUM(E35:CT35) -> 0
C36: OPTIMUS | D36: =SUM(E36:CT36) -> 0
C37: MASH | D37: =SUM(E37:CT37) -> 41 | AI37: 2 | AJ37: 2 | AK37: 1 | AL37: 1 | AM37: 1 | AN37: 1 | AO37: 1 | AP37: 1 | BE37: 3 | BF37: 5 | BG37: 7 | BH37: 7 | BI37: 7 | BJ37: 2
C38: MAGENTO | D38: =SUM(E38:CT38) -> 0
A39: 9 | B39: Decision Cube | C39: ALF | D39: =SUM(E39:CT39) -> 117 | U39: 5 | V39: 5 | W39: 5 | X39: 5 | Y39: 5 | Z39: 5 | AA39: 5 | AB39: 5 | AC39: 5 | AD39: 3 | AE39: 5 | AF39: 6 | AG39: 6 | AH39: 5 | AI39: 5 | AJ39: 3 | AK39: 3 | AL39: 3 | AM39: 3 | AN39: 3 | AO39: 3 | AP39: 3 | AQ39: 3 | AR39: 3 | AS39: 3 | AV39: 3 | AW39: 3 | AX39: 3 | AY39: 3
C40: WAREX | D40: =SUM(E40:CT40) -> 0
C41: OPTIMUS | D41: =SUM(E41:CT41) -> 0
C42: MASH | D42: =SUM(E42:CT42) -> 0
C43: MAGENTO | D43: =SUM(E43:CT43) -> 0
A44: 10 | B44: Paperless | C44: ALF | D44: =SUM(E44:CT44) -> 14 | AM44: 2 | AN44: 2 | AO44: 2 | AP44: 2 | AQ44: 2 | AR44: 2 | AS44: 2
C45: WAREX | D45: =SUM(E45:CT45) -> 0
C46: OPTIMUS | D46: =SUM(E46:CT46) -> 0
C47: MASH | D47: =SUM(E47:CT47) -> 0
C48: MAGENTO | D48: =SUM(E48:CT48) -> 0
A49: 11 | B49: Upgrade | C49: ALF | D49: =SUM(E49:CT49) -> 38 | AQ49: 5 | AR49: 5 | AS49: 5 | AV49: 3 | AW49: 5 | AX49: 5 | AY49: 5 | AZ49: 5
C50: WAREX | D50: =SUM(E50:CT50) -> 0
C51: OPTIMUS | D51: =SUM(E51:CT51) -> 0
C52: MASH | D52: =SUM(E52:CT52) -> 0
C53: MAGENTO | D53: =SUM(E53:CT53) -> 0
B54: Mbox for MM (Worten) - 23.07 | C54: ALF | D54: =SUM(E54:CT54) -> 20 | V54: 10 | W54: 8 | X54: 2
C55: WAREX | D55: =SUM(E55:CT55) -> 0
C56: OPTIMUS | D56: =SUM(E56:CT56) -> 0
C57: MASH | D57: =SUM(E57:CT57) -> 0
C58: MAGENTO | D58: =SUM(E58:CT58) -> 20 | V58: 10 | W58: 8 | X58: 2
A59: 22 | B59: Rebranding | C59: ALF | D59: =SUM(E59:CT59) -> 107 | Q59: 6 | R59: 10 | S59: 8 | T59: 8 | U59: 8 | V59: 8 | W59: 5 | X59: 5 | Y59: 9 | AC59: 5 | AD59: 5 | AE59: 5 | AF59: 5 | AG59: 5 | AP59: 5 | AR59: 5 | AS59: 5
C60: WAREX | D60: =SUM(E60:CT60) -> 120 | Q60: 5 | R60: 3 | S60: 5 | T60: 2 | U60: 2 | V60: 2 | W60: 0 | X60: 2 | Y60: 2 | Z60: 1 | AA60: 1 | AB60: 1 | AC60: 2 | AD60: 2 | AE60: 2 | AF60: 2 | AG60: 5 | AJ60: 10 | AK60: 12 | AL60: 13 | AM60: 10 | AN60: 10 | AO60: 3 | AP60: 3 | AQ60: 5 | AR60: 5 | AS60: 10
C61: OPTIMUS | D61: =SUM(E61:CT61) -> 281 | M61: 2 | N61: 6 | O61: 10 | P61: 15 | Q61: 15 | R61: 15 | S61: 5 | T61: 5 | U61: 10 | V61: 10 | W61: 10 | X61: 10 | Y61: 10 | Z61: 10 | AA61: 10 | AB61: 10 | AC61: 10 | AD61: 10 | AE61: 10 | AF61: 10 | AG61: 10 | AH61: 10 | AI61: 10 | AJ61: 10 | AK61: 10 | AL61: 5 | AM61: 5 | AN61: 3 | AO61: 5 | AP61: 5 | AQ61: 5 | AR61: 5 | AS61: 5
C62: MASH | D62: =SUM(E62:CT62) -> 3.5 | P62: 1 | Q62: 1 | R62: 1 | U62: 0.5
C63: MAGENTO | D63: =SUM(E63:CT63) -> 41 | P63: 1 | U63: 5 | V63: 5 | W63: 5 | X63: 5 | Z63: 5 | AA63: 6 | AB63: 9
A64: 1 | B64: Compass | C64: ALF | D64: =SUM(E64:CT64) -> 34 | AJ64: 5 | AK64: 5 | AL64: 5 | AM64: 5 | AN64: 5 | AO64: 4 | AP64: 5
C65: WAREX | D65: =SUM(E65:CT65) -> 0
C66: OPTIMUS | D66: =SUM(E66:CT66) -> 50 | AI66: 2 | AJ66: 2 | AK66: 2 | AL66: 5 | AM66: 3 | AN66: 3 | AO66: 7 | AP66: 7 | AQ66: 7 | AR66: 7 | AS66: 5
C67: MASH | D67: =SUM(E67:CT67) -> 24 | AH67: 3 | AI67: 3 | AJ67: 3 | AK67: 3 | AL67: 3 | AM67: 3 | AN67: 3 | AO67: 3
C68: MAGENTO | D68: =SUM(E68:CT68) -> 0
A69: 2 | B69: Project - HT Rental | C69: ALF | D69: =SUM(E69:CT69) -> 45 | Q69: 5 | R69: 5 | T69: 4 | U69: 4 | V69: 5 | W69: 5 | X69: 5 | Y69: 5 | Z69: 2 | AQ69: 2 | AR69: 3
C70: WAREX | D70: =SUM(E70:CT70) -> 26 | P70: 1 | S70: 2 | T70: 1 | U70: 3 | V70: 4 | W70: 5 | X70: 0 | Y70: 3 | AN70: 2 | AO70: 2 | AR70: 3
C71: OPTIMUS | D71: =SUM(E71:CT71) -> 32 | V71: 5 | W71: 10 | X71: 5 | Y71: 5 | Z71: 5 | AA71: 2
C72: MASH | D72: =SUM(E72:CT72) -> 0
C73: MAGENTO | D73: =SUM(E73:CT73) -> 0
B74: Project - iStyle HU | C74: ALF | D74: =SUM(E74:CT74) -> 37 | N74: 5 | O74: 10 | P74: 11 | Q74: 5 | R74: 4 | S74: 2
C75: WAREX | D75: =SUM(E75:CT75) -> 17 | O75: 2 | P75: 3 | Q75: 6 | R75: 4 | S75: 2
C76: OPTIMUS | D76: =SUM(E76:CT76) -> 22 | S76: 1 | T76: 9 | U76: 5 | V76: 5 | W76: 2
C77: MASH | D77: 8 | N77: 2 | O77: 4 | P77: 1 | Q77: 1 | R77: 0.5
C78: MAGENTO | D78: =SUM(E78:CT78) -> 0
A79: 3 | B79: T-Mobile Rental | C79: ALF | D79: =SUM(E79:CT79) -> 0
C80: WAREX | D80: =SUM(E80:CT80) -> 0
C81: OPTIMUS | D81: =SUM(E81:CT81) -> 0
C82: MASH | D82: =SUM(E82:CT82) -> 0
C83: ALF | D83: =SUM(E83:CT83) -> 0
A84: 4 | B84: Orange (Insurance Exchange) | C84: ALF | D84: =SUM(E84:CT84) -> 0
C85: WAREX | D85: =SUM(E85:CT85) -> 0
C86: OPTIMUS | D86: =SUM(E86:CT86) -> 0
C87: MASH | D87: =SUM(E87:CT87) -> 0
C88: MAGENTO | D88: =SUM(E88:CT88) -> 0
A89: 4 | B89: Orange B2B Enterprise | C89: ALF | D89: =SUM(E89:CT89) -> 0
C90: WAREX | D90: =SUM(E90:CT90) -> 21 | AD90: 5 | AE90: 5 | AF90: 3 | AG90: 4 | AH90: 2 | AI90: 2
C91: OPTIMUS | D91: =SUM(E91:CT91) -> 26 | AF91: 5 | AG91: 5 | AH91: 5 | AI91: 5 | AJ91: 2 | AK91: 2 | AL91: 2
C92: MASH | D92: =SUM(E92:CT92) -> 0
C93: MAGENTO | D93: =SUM(E93:CT93) -> 0
A94: 5 | B94: iMad Changes Phase 1 (iMad Care i iMad Rent) | C94: ALF | D94: =SUM(E94:CT94) -> 16 | AH94: 5 | AI94: 5 | AJ94: 2 | AK94: 2 | AL94: 2
C95: WAREX | D95: =SUM(E95:CT95) -> 47 | AC95: 1 | AD95: 1 | AF95: 2 | AG95: 5 | AK95: 5 | AL95: 5 | AM95: 5 | AN95: 5 | AO95: 5 | AP95: 5 | AQ95: 5 | AR95: 3
C96: OPTIMUS | D96: =SUM(E96:CT96) -> 26 | AN96: 5 | AO96: 5 | AP96: 3 | AQ96: 3 | AR96: 5 | AS96: 5
C97: MASH | D97: =SUM(E97:CT97) -> 0
C98: MAGENTO | D98: =SUM(E98:CT98) -> 20 | AK98: 5 | AL98: 5 | AM98: 5 | AN98: 5
A99: 6 | B99: Project - Multibrand for iMad PHASE 2 (sale) | C99: ALF | D99: =SUM(E99:CT99) -> 0
C100: WAREX | D100: =SUM(E100:CT100) -> 0
C101: OPTIMUS | D101: =SUM(E101:CT101) -> 0
...

Sheet WORKLOAD_TEAMS (8)
A1: PRIORYTET | B1: DATE | C1: DATE | D1: TOTALS | E1: =TEXT(DATE(2024,1,1)+(E2-1)*7-WEEKDAY(DATE(2024,1,1),2)+1,"dd.mm")&"-"&TEXT(DATE(2024,1,1)+(E2-1)*7-WEEKDAY(DATE(2024,1,1),2)+7,"dd.mm") -> 11.03-17.03 | F1: =TEXT(DATE(2024,1,1)+(F2-1)*7-WEEKDAY(DATE(2024,1,1),2)+1,"dd.mm")&"-"&TEXT(DATE(2024,1,1)+(F2-1)*7-WEEKDAY(DATE(2024,1,1),2)+7,"dd.mm") -> 18.03-24.03 | G1: =TEXT(DATE(2024,1,1)+(G2-1)*7-WEEKDAY(DATE(2024,1,1),2)+1,"dd.mm")&"-"&TEXT(DATE(2024,1,1)+(G2-1)*7-WEEKDAY(DATE(2024,1,1),2)+7,"dd.mm") -> 25.03-31.03 | H1: =TEXT(DATE(2024,1,1)+(H2-1)*7-WEEKDAY(DATE(2024,1,1),2)+1,"dd.mm")&"-"&TEXT(DATE(2024,1,1)+(H2-1)*7-WEEKDAY(DATE(2024,1,1),2)+7,"dd.mm") -> 01.04-07.04 | I1: =TEXT(DATE(2024,1,1)+(I2-1)*7-WEEKDAY(DATE(2024,1,1),2)+1,"dd.mm")&"-"&TEXT(DATE(2024,1,1)+(I2-1)*7-WEEKDAY(DATE(2024,1,1),2)+7,"dd.mm") -> 08.04-14.04 | J1: =TEXT(DATE(2024,1,1)+(J2-1)*7-WEEKDAY(DATE(2024,1,1),2)+1,"dd.mm")&"-"&TEXT(DATE(2024,1,1)+(J2-1)*7-WEEKDAY(DATE(2024,1,1),2)+7,"dd.mm") -> 15.04-21.04 | K1: =TEXT(DATE(2024,1,1)+(K2-1)*7-WEEKDAY(DATE(2024,1,1),2)+1,"dd.mm")&"-"&TEXT(DATE(2024,1,1)+(K2-1)*7-WEEKDAY(DATE(2024,1,1),2)+7,"dd.mm") -> 22.04-28.04 | L1: =TEXT(DATE(2024,1,1)+(L2-1)*7-WEEKDAY(DATE(2024,1,1),2)+1,"dd.mm")&"-"&TEXT(DATE(2024,1,1)+(L2-1)*7-WEEKDAY(DATE(2024,1,1),2)+7,"dd.mm") -> 29.04-05.05 | ... AT1: =TEXT(DATE(2024,1,1)+(AT2-1)*7-WEEKDAY(DATE(2024,1,1),2)+1,"dd.mm")&"-"&TEXT(DATE(2024,1,1)+(AT2-1)*7-WEEKDAY(DATE(2024,1,1),2)+7,"dd.mm") -> 23.12-29.12 | AU1: =TEXT(DATE(2025,1,1)+(AU2-1)*7-WEEKDAY(DATE(2025,1,1),2)+1,"dd.mm")&"-"&TEXT(DATE(2025,1,1)+(AU2-1)*7-WEEKDAY(DATE(2025,1,1),2)+7,"dd.mm") -> 30.12-05.01 | AV1: =TEXT(DATE(2025,1,1)+(AV2-1)*7-WEEKDAY(DATE(2025,1,1),2)+1,"dd.mm")&"-"&TEXT(DATE(2025,1,1)+(AV2-1)*7-WEEKDAY(DATE(2025,1,1),2)+7,"dd.mm") -> 06.01-12.01 | AW1: =TEXT(DATE(2025,1,1)+(AW2-1)*7-WEEKDAY(DATE(2025,1,1),2)+1,"dd.mm")&"-"&TEXT(DATE(2025,1,1)+(AW2-1)*7-WEEKDAY(DATE(2025,1,1),2)+7,"dd.mm") -> 13.01-19.01 | AX1: =TEXT(DATE(2025,1,1)+(AX2-1)*7-WEEKDAY(DATE(2025,1,1),2)+1,"dd.mm")&"-"&TEXT(DATE(2025,1,1)+(AX2-1)*7-WEEKDAY(DATE(2025,1,1),2)+7,"dd.mm") -> 20.01-26.01 | AY1: =TEXT(DATE(2025,1,1)+(AY2-1)*7-WEEKDAY(DATE(2025,1,1),2)+1,"dd.mm")&"-"&TEXT(DATE(2025,1,1)+(AY2-1)*7-WEEKDAY(DATE(2025,1,1),2)+7,"dd.mm") -> 27.01-02.02 | AZ1: =TEXT(DATE(2025,1,1)+(AZ2-1)*7-WEEKDAY(DATE(2025,1,1),2)+1,"dd.mm")&"-"&TEXT(DATE(2025,1,1)+(AZ2-1)*7-WEEKDAY(DATE(2025,1,1),2)+7,"dd.mm") -> 03.02-09.02 | BA1: =TEXT(DATE(2025,1,1)+(BA2-1)*7-WEEKDAY(DATE(2025,1,1),2)+1,"dd.mm")&"-"&TEXT(DATE(2025,1,1)+(BA2-1)*7-WEEKDAY(DATE(2025,1,1),2)+7,"dd.mm") -> 10.02-16.02 | BB1: =TEXT(DATE(2025,1,1)+(BB2-1)*7-WEEKDAY(DATE(2025,1,1),2)+1,"dd.mm")&"-"&TEXT(DATE(2025,1,1)+(BB2-1)*7-WEEKDAY(DATE(2025,1,1),2)+7,"dd.mm") -> 17.02-23.02 | ... CT1: =TEXT(DATE(2025,1,1)+(CT2-1)*7-WEEKDAY(DATE(2025,1,1),2)+1,"dd.mm")&"-"&TEXT(DATE(2025,1,1)+(CT2-1)*7-WEEKDAY(DATE(2025,1,1),2)+7,"dd.mm") -> 22.12-28.12
C2: WEEK | E2: 11 | F2: 12 | G2: 13 | H2: 14 | I2: 15 | J2: 16 | K2: 17 | L2: 18 | M2: 19 | N2: 20 | O2: 21 | P2: 22 | Q2: 23 | R2: 24 | S2: 25 | T2: 26 | U2: 27 | V2: 28 | W2: 29 | X2: 30 | Y2: 31 | Z2: 32 | AA2: 33 | AB2: 34 | AC2: 35 | AD2: 36 | AE2: 37 | AF2: 38 | AG2: 39 | AH2: 40 | AI2: 41 | AJ2: 42 | AK2: 43 | AL2: 44 | AM2: 45 | AN2: 46 | AO2: 47 | AP2: 48 | AQ2: 49 | AR2: 50 | AS2: 51 | AT2: 52 | AU2: 1 | AV2: 2 | AW2: 3 | AX2: 4 | AY2: 5 | AZ2: 6 | BA2: 7 | BB2: 8 | BC2: 9 | BD2: 10 | BE2: 11 | BF2: 12 | BG2: 13 | BH2: 14 | BI2: 15 | BJ2: 16 | BK2: 17 | BL2: 18 | BM2: 19 | BN2: 20 | BO2: 21 | BP2: 22 | BQ2: 23 | BR2: 24 | BS2: 25 | BT2: 26 | BU2: 27 | BV2: 28 | BW2: 29 | BX2: 30 | BY2: 31 | BZ2: 32 | CA2: 33 | CB2: 34 | CC2: 35 | CD2: 36 | CE2: 37 | CF2: 38 | CG2: 39 | CH2: 40 | CI2: 41 | CJ2: 42 | CK2: 43 | CL2: 44 | CM2: 45 | CN2: 46 | CO2: 47 | CP2: 48 | CQ2: 49 | CR2: 50 | CS2: 51 | CT2: 52
B3: PROJECTS & FUNCTIONALITIES CAPACITY | C3: ALF | E3: =CAPACITY!G2 -> 27.342 | F3: =OFFSET(CAPACITY!$G$2,0,7*(F$2-$E$2)) -> 27.342 | G3: =OFFSET(CAPACITY!$G$2,0,7*(G$2-$E$2)) -> 27.342 | H3: =OFFSET(CAPACITY!$G$2,0,7*(H$2-$E$2)) -> 21.462 | I3: =OFFSET(CAPACITY!$G$2,0,7*(I$2-$E$2)) -> 27.342 | J3: =OFFSET(CAPACITY!$G$2,0,7*(J$2-$E$2)) -> 27.342 | K3: =OFFSET(CAPACITY!$G$2,0,7*(K$2-$E$2)) -> 27.342 | L3: =OFFSET(CAPACITY!$G$2,0,7*(L$2-$E$2)) -> 14.028 | M3: =OFFSET(CAPACITY!$G$2,0,7*(M$2-$E$2)) -> 28.371 | ... AT3: =OFFSET(CAPACITY!$G$2,0,7*(AT$2-$E$2)) -> 12.39 | AU3: =OFFSET(CAPACITY!$G$2,0,7*(AU$2+52-$E$2)) -> 17.346 | AV3: =OFFSET(CAPACITY!$G$2,0,7*(AV$2+52-$E$2)) -> 23.247 | AW3: =OFFSET(CAPACITY!$G$2,0,7*(AW$2+52-$E$2)) -> 28.728 | AX3: =OFFSET(CAPACITY!$G$2,0,7*(AX$2+52-$E$2)) -> 28.728 | AY3: =OFFSET(CAPACITY!$G$2,0,7*(AY$2+52-$E$2)) -> 26.439 | AZ3: =OFFSET(CAPACITY!$G$2,0,7*(AZ$2+52-$E$2)) -> 28.455 | BA3: =OFFSET(CAPACITY!$G$2,0,7*(BA$2+52-$E$2)) -> 27.342 | BB3: =OFFSET(CAPACITY!$G$2,0,7*(BB$2+52-$E$2)) -> 28.581 | ... CT3: =OFFSET(CAPACITY!$G$2,0,7*(CT$2+52-$E$2)) -> 9.66
C4: WAREX | E4: =CAPACITY!G4 -> 10.388559 | F4: =OFFSET(CAPACITY!$G$4,0,7*(F$2-$E$2)) -> 10.388559 | G4: =OFFSET(CAPACITY!$G$4,0,7*(G$2-$E$2)) -> 10.388559 | H4: =OFFSET(CAPACITY!$G$4,0,7*(H$2-$E$2)) -> 8.1544599 | I4: =OFFSET(CAPACITY!$G$4,0,7*(I$2-$E$2)) -> 10.388559 | J4: =OFFSET(CAPACITY!$G$4,0,7*(J$2-$E$2)) -> 10.069402 | K4: =OFFSET(CAPACITY!$G$4,0,7*(K$2-$E$2)) -> 10.388559 | L4: =OFFSET(CAPACITY!$G$4,0,7*(L$2-$E$2)) -> 1.9149417 | M4: =OFFSET(CAPACITY!$G$4,0,7*(M$2-$E$2)) -> 9.4310877 | ... AT4: =OFFSET(CAPACITY!$G$4,0,7*(AT$2-$E$2)) -> 9.4151298 | AU4: =OFFSET(CAPACITY!$G$4,0,7*(AU$2+52-$E$2)) -> 13.181182 | AV4: =OFFSET(CAPACITY!$G$4,0,7*(AV$2+52-$E$2)) -> 17.665337 | AW4: =OFFSET(CAPACITY!$G$4,0,7*(AW$2+52-$E$2)) -> 21.830335 | AX4: =OFFSET(CAPACITY!$G$4,0,7*(AX$2+52-$E$2)) -> 21.830335 | AY4: =OFFSET(CAPACITY!$G$4,0,7*(AY$2+52-$E$2)) -> 20.09093 | AZ4: =OFFSET(CAPACITY!$G$4,0,7*(AZ$2+52-$E$2)) -> 21.622883 | BA4: =OFFSET(CAPACITY!$G$4,0,7*(BA$2+52-$E$2)) -> 20.777117 | BB4: =OFFSET(CAPACITY!$G$4,0,7*(BB$2+52-$E$2)) -> 21.71863 | ... CT4: =OFFSET(CAPACITY!$G$4,0,7*(CT$2+52-$E$2)) -> 7.3406097
C5: OPTIMUS | E5: =CAPACITY!G6 -> 21.241748 | F5: =OFFSET(CAPACITY!$G$6,0,7*(F$2-$E$2)) -> 21.241748 | G5: =OFFSET(CAPACITY!$G$6,0,7*(G$2-$E$2)) -> 21.241748 | H5: =OFFSET(CAPACITY!$G$6,0,7*(H$2-$E$2)) -> 16.67363 | I5: =OFFSET(CAPACITY!$G$6,0,7*(I$2-$E$2)) -> 21.241748 | J5: =OFFSET(CAPACITY!$G$6,0,7*(J$2-$E$2)) -> 21.241748 | K5: =OFFSET(CAPACITY!$G$6,0,7*(K$2-$E$2)) -> 21.241748 | L5: =OFFSET(CAPACITY!$G$6,0,7*(L$2-$E$2)) -> 8.995678 | M5: =OFFSET(CAPACITY!$G$6,0,7*(M$2-$E$2)) -> 18.395459 | ... AT5: =OFFSET(CAPACITY!$G$6,0,7*(AT$2-$E$2)) -> 7.9063577 | AU5: =OFFSET(CAPACITY!$G$6,0,7*(AU$2+52-$E$2)) -> 12.281209 | AV5: =OFFSET(CAPACITY!$G$6,0,7*(AV$2+52-$E$2)) -> 14.705825 | AW5: =OFFSET(CAPACITY!$G$6,0,7*(AW$2+52-$E$2)) -> 20.082148 | AX5: =OFFSET(CAPACITY!$G$6,0,7*(AX$2+52-$E$2)) -> 20.082148 | AY5: =OFFSET(CAPACITY!$G$6,0,7*(AY$2+52-$E$2)) -> 18.852271 | AZ5: =OFFSET(CAPACITY!$G$6,0,7*(AZ$2+52-$E$2)) -> 19.027967 | BA5: =OFFSET(CAPACITY!$G$6,0,7*(BA$2+52-$E$2)) -> 17.270999 | BB5: =OFFSET(CAPACITY!$G$6,0,7*(BB$2+52-$E$2)) -> 15.074789 | ... CT5: =OFFSET(CAPACITY!$G$6,0,7*(CT$2+52-$E$2)) -> 4.9195114
C6: MASH | E6: =CAPACITY!G8 -> 8.1375 | F6: =OFFSET(CAPACITY!$G$8,0,7*(F$2-$E$2)) -> 8.1375 | G6: =OFFSET(CAPACITY!$G$8,0,7*(G$2-$E$2)) -> 8.1375 | H6: =OFFSET(CAPACITY!$G$8,0,7*(H$2-$E$2)) -> 6.3875 | I6: =OFFSET(CAPACITY!$G$8,0,7*(I$2-$E$2)) -> 8.1375 | J6: =OFFSET(CAPACITY!$G$8,0,7*(J$2-$E$2)) -> 8.1375 | K6: =OFFSET(CAPACITY!$G$8,0,7*(K$2-$E$2)) -> 8.1375 | L6: =OFFSET(CAPACITY!$G$8,0,7*(L$2-$E$2)) -> 5.25 | M6: =OFFSET(CAPACITY!$G$8,0,7*(M$2-$E$2)) -> 8.1375 | ... AT6: =OFFSET(CAPACITY!$G$8,0,7*(AT$2-$E$2)) -> 2.205 | AU6: =OFFSET(CAPACITY!$G$8,0,7*(AU$2+52-$E$2)) -> 3.4825 | AV6: =OFFSET(CAPACITY!$G$8,0,7*(AV$2+52-$E$2)) -> 6.0375 | AW6: =OFFSET(CAPACITY!$G$8,0,7*(AW$2+52-$E$2)) -> 7.91 | AX6: =OFFSET(CAPACITY!$G$8,0,7*(AX$2+52-$E$2)) -> 7.21 | AY6: =OFFSET(CAPACITY!$G$8,0,7*(AY$2+52-$E$2)) -> 6.86 | AZ6: =OFFSET(CAPACITY!$G$8,0,7*(AZ$2+52-$E$2)) -> 6.7375 | BA6: =OFFSET(CAPACITY!$G$8,0,7*(BA$2+52-$E$2)) -> 6.16 | BB6: =OFFSET(CAPACITY!$G$8,0,7*(BB$2+52-$E$2)) -> 7.56 | ... CT6: =OFFSET(CAPACITY!$G$8,0,7*(CT$2+52-$E$2)) -> 3.15
C7: MAGENTO | E7: =CAPACITY!G10 -> 23.2875 | F7: =OFFSET(CAPACITY!$G$10,0,7*(F$2-$E$2)) -> 23.2875 | G7: =OFFSET(CAPACITY!$G$10,0,7*(G$2-$E$2)) -> 23.2875 | H7: =OFFSET(CAPACITY!$G$10,0,7*(H$2-$E$2)) -> 22.5375 | I7: =OFFSET(CAPACITY!$G$10,0,7*(I$2-$E$2)) -> 23.2875 | J7: =OFFSET(CAPACITY!$G$10,0,7*(J$2-$E$2)) -> 23.2875 | K7: =OFFSET(CAPACITY!$G$10,0,7*(K$2-$E$2)) -> 23.2875 | L7: =OFFSET(CAPACITY!$G$10,0,7*(L$2-$E$2)) -> 20.25 | M7: =OFFSET(CAPACITY!$G$10,0,7*(M$2-$E$2)) -> 24.1575 | ... AT7: =OFFSET(CAPACITY!$G$10,0,7*(AT$2-$E$2)) -> 12.1125 | AU7: =OFFSET(CAPACITY!$G$10,0,7*(AU$2+52-$E$2)) -> 15.6675 | AV7: =OFFSET(CAPACITY!$G$10,0,7*(AV$2+52-$E$2)) -> 19.18875 | AW7: =OFFSET(CAPACITY!$G$10,0,7*(AW$2+52-$E$2)) -> 24.1575 | AX7: =OFFSET(CAPACITY!$G$10,0,7*(AX$2+52-$E$2)) -> 24.1575 | AY7: =OFFSET(CAPACITY!$G$10,0,7*(AY$2+52-$E$2)) -> 24.1575 | AZ7: =OFFSET(CAPACITY!$G$10,0,7*(AZ$2+52-$E$2)) -> 24.1575 | BA7: =OFFSET(CAPACITY!$G$10,0,7*(BA$2+52-$E$2)) -> 24.1575 | BB7: =OFFSET(CAPACITY!$G$10,0,7*(BB$2+52-$E$2)) -> 24.1575 | ... CT7: =OFFSET(CAPACITY!$G$10,0,7*(CT$2+52-$E$2)) -> 7.5
B8: PROJECTS & FUNCTIONALITIES CAPACITY UTILISATION | C8: ALF | E8: =E3-SUMIF($C$14:$C$502,$C8,E14:E502) -> 15.342 | F8: =F3-SUMIF($C$14:$C$502,$C8,F14:F502) -> 15.342 | G8: =G3-SUMIF($C$14:$C$502,$C8,G14:G502) -> 15.342 | H8: =H3-SUMIF($C$14:$C$502,$C8,H14:H502) -> 9.462 | I8: =I3-SUMIF($C$14:$C$502,$C8,I14:I502) -> 15.342 | J8: =J3-SUMIF($C$14:$C$502,$C8,J14:J502) -> 10.342 | K8: =K3-SUMIF($C$14:$C$502,$C8,K14:K502) -> -4.658 | L8: =L3-SUMIF($C$14:$C$502,$C8,L14:L502) -> -8.972 | ... CT8: =CT3-SUMIF($C$14:$C$502,$C8,CT14:CT502) -> -2.34
C9: WAREX | E9: =E4-SUMIF($C$14:$C$502,$C9,E14:E502) -> 10.388559 | F9: =F4-SUMIF($C$14:$C$502,$C9,F14:F502) -> 10.388559 | G9: =G4-SUMIF($C$14:$C$502,$C9,G14:G502) -> 10.388559 | H9: =H4-SUMIF($C$14:$C$502,$C9,H14:H502) -> 0.15445992 | I9: =I4-SUMIF($C$14:$C$502,$C9,I14:I502) -> 2.3885585 | J9: =J4-SUMIF($C$14:$C$502,$C9,J14:J502) -> 2.0694016 | K9: =K4-SUMIF($C$14:$C$502,$C9,K14:K502) -> -3.6114415 | L9: =L4-SUMIF($C$14:$C$502,$C9,L14:L502) -> -4.0850583 | ... CT9: =CT4-SUMIF($C$14:$C$502,$C9,CT14:CT502) -> 7.3406097
C10: OPTIMUS | E10: =E5-SUMIF($C$14:$C$502,$C10,E14:E502) -> 21.241748 | F10: =F5-SUMIF($C$14:$C$502,$C10,F14:F502) -> 21.241748 | G10: =G5-SUMIF($C$14:$C$502,$C10,G14:G502) -> 21.241748 | H10: =H5-SUMIF($C$14:$C$502,$C10,H14:H502) -> 16.67363 | I10: =I5-SUMIF($C$14:$C$502,$C10,I14:I502) -> 21.241748 | J10: =J5-SUMIF($C$14:$C$502,$C10,J14:J502) -> 21.241748 | K10: =K5-SUMIF($C$14:$C$502,$C10,K14:K502) -> 21.241748 | L10: =L5-SUMIF($C$14:$C$502,$C10,L14:L502) -> 8.995678 | ... CT10: =CT5-SUMIF($C$14:$C$502,$C10,CT14:CT502) -> 4.9195114
C11: MASH | E11: =E6-SUMIF($C$14:$C$502,$C11,E14:E502) -> 7.6375 | F11: =F6-SUMIF($C$14:$C$502,$C11,F14:F502) -> 7.6375 | G11: =G6-SUMIF($C$14:$C$502,$C11,G14:G502) -> 7.6375 | H11: =H6-SUMIF($C$14:$C$502,$C11,H14:H502) -> 4.8875 | I11: =I6-SUMIF($C$14:$C$502,$C11,I14:I502) -> 5.6375 | J11: =J6-SUMIF($C$14:$C$502,$C11,J14:J502) -> 3.6375 | K11: =K6-SUMIF($C$14:$C$502,$C11,K14:K502) -> 0.6375 | L11: =L6-SUMIF($C$14:$C$502,$C11,L14:L502) -> -2.25 | ... CT11: =CT6-SUMIF($C$14:$C$502,$C11,CT14:CT502) -> 2.65
C12: MAGENTO | E12: =E7-SUMIF($C$14:$C$502,$C12,E14:E502) -> 23.2875 | F12: =F7-SUMIF($C$14:$C$502,$C12,F14:F502) -> 23.2875 | G12: =G7-SUMIF($C$14:$C$502,$C12,G14:G502) -> 23.2875 | H12: =H7-SUMIF($C$14:$C$502,$C12,H14:H502) -> 22.5375 | I12: =I7-SUMIF($C$14:$C$502,$C12,I14:I502) -> 23.2875 | J12: =J7-SUMIF($C$14:$C$502,$C12,J14:J502) -> 11.2875 | K12: =K7-SUMIF($C$14:$C$502,$C12,K14:K502) -> 0.2875 | L12: =L7-SUMIF($C$14:$C$502,$C12,L14:L502) -> 2.25 | ... CT12: =CT7-SUMIF($C$14:$C$502,$C12,CT14:CT502) -> 7.5
A14: 2 | B14: DŁUG FUNKCJONALNY ALF | C14: ALF | D14: =SUM(E14:CT14) -> 1104 | E14: 12 | F14: 12 | G14: 12 | H14: 12 | I14: 12 | J14: 12 | K14: 12 | L14: 12 | M14: 12 | N14: 12 | O14: 12 | P14: 12 | Q14: 12 | R14: 12 | S14: 12 | T14: 12 | U14: 12 | V14: 12 | W14: 12 | X14: 12 | Y14: 12 | Z14: 12 | AA14: 12 | AB14: 12 | AC14: 12 | AD14: 12 | AE14: 12 | AF14: 12 | AG14: 12 | AH14: 12 | AI14: 12 | AJ14: 12 | AK14: 12 | AL14: 12 | AM14: 12 | AN14: 12 | AO14: 12 | AP14: 12 | AQ14: 12 | AR14: 12 | AS14: 12 | AV14: 12 | AW14: 12 | AX14: 12 | AY14: 12 | AZ14: 12 | BA14: 12 | BB14: 12 | BC14: 12 | BD14: 12 | BE14: 12 | BF14: 12 | BG14: 12 | BH14: 12 | BI14: 12 | BJ14: 12 | BK14: 12 | BL14: 12 | BM14: 12 | BN14: 12 | BO14: 12 | BP14: 12 | BQ14: 12 | BR14: 12 | BS14: 12 | BT14: 12 | BU14: 12 | BV14: 12 | BW14: 12 | BX14: 12 | BY14: 12 | BZ14: 12 | CA14: 12 | CB14: 12 | CC14: 12 | CD14: 12 | CE14: 12 | CF14: 12 | CG14: 12 | CH14: 12 | CI14: 12 | CJ14: 12 | CK14: 12 | CL14: 12 | CM14: 12 | CN14: 12 | CO14: 12 | CP14: 12 | CQ14: 12 | CR14: 12 | CS14: 12 | CT14: 12
C15: WAREX | D15: =SUM(E15:CT15) -> 0
C16: OPTIMUS | D16: =SUM(E16:CT16) -> 0
C17: MASH | D17: =SUM(E17:CT17) -> 46 | E17: 0.5 | F17: 0.5 | G17: 0.5 | H17: 0.5 | I17: 0.5 | J17: 0.5 | K17: 0.5 | L17: 0.5 | M17: 0.5 | N17: 0.5 | O17: 0.5 | P17: 0.5 | Q17: 0.5 | R17: 0.5 | S17: 0.5 | T17: 0.5 | U17: 0.5 | V17: 0.5 | W17: 0.5 | X17: 0.5 | Y17: 0.5 | Z17: 0.5 | AA17: 0.5 | AB17: 0.5 | AC17: 0.5 | AD17: 0.5 | AE17: 0.5 | AF17: 0.5 | AG17: 0.5 | AH17: 0.5 | AI17: 0.5 | AJ17: 0.5 | AK17: 0.5 | AL17: 0.5 | AM17: 0.5 | AN17: 0.5 | AO17: 0.5 | AP17: 0.5 | AQ17: 0.5 | AR17: 0.5 | AS17: 0.5 | AV17: 0.5 | AW17: 0.5 | AX17: 0.5 | AY17: 0.5 | AZ17: 0.5 | BA17: 0.5 | BB17: 0.5 | BC17: 0.5 | BD17: 0.5 | BE17: 0.5 | BF17: 0.5 | BG17: 0.5 | BH17: 0.5 | BI17: 0.5 | BJ17: 0.5 | BK17: 0.5 | BL17: 0.5 | BM17: 0.5 | BN17: 0.5 | BO17: 0.5 | BP17: 0.5 | BQ17: 0.5 | BR17: 0.5 | BS17: 0.5 | BT17: 0.5 | BU17: 0.5 | BV17: 0.5 | BW17: 0.5 | BX17: 0.5 | BY17: 0.5 | BZ17: 0.5 | CA17: 0.5 | CB17: 0.5 | CC17: 0.5 | CD17: 0.5 | CE17: 0.5 | CF17: 0.5 | CG17: 0.5 | CH17: 0.5 | CI17: 0.5 | CJ17: 0.5 | CK17: 0.5 | CL17: 0.5 | CM17: 0.5 | CN17: 0.5 | CO17: 0.5 | CP17: 0.5 | CQ17: 0.5 | CR17: 0.5 | CS17: 0.5 | CT17: 0.5
C18: MAGENTO | D18: =SUM(E18:CT18) -> 0
A19: 3 | B19: Coverwise | C19: ALF | D19: =SUM(E19:CT19) -> 0
C20: WAREX | D20: =SUM(E20:CT20) -> 158 | AZ20: 5 | BA20: 5 | BB20: 5 | BC20: 7 | BD20: 10 | BE20: 10 | BF20: 7 | BG20: 7 | BH20: 5 | BI20: 5 | BJ20: 5 | BK20: 5 | BL20: 5 | BM20: 5 | BN20: 5 | BO20: 5 | BP20: 5 | BR20: 3 | BS20: 3 | BT20: 3 | BU20: 3 | BV20: 3 | BW20: 3 | BX20: 3 | BY20: 3 | BZ20: 3 | CA20: 3 | CB20: 3 | CC20: 3 | CD20: 3 | CE20: 3 | CF20: 3 | CG20: 3 | CH20: 3 | CI20: 3 | CJ20: 3
C21: OPTIMUS | D21: =SUM(E21:CT21) -> 197 | AZ21: 5 | BA21: 5 | BB21: 5 | BC21: 5 | BD21: 5 | BE21: 10 | BF21: 10 | BG21: 10 | BH21: 10 | BI21: 10 | BJ21: 10 | BK21: 10 | BL21: 10 | BM21: 10 | BN21: 10 | BO21: 10 | BP21: 10 | BQ21: 5 | BR21: 5 | BS21: 5 | BT21: 5 | BU21: 5 | BV21: 5 | BW21: 5 | BX21: 5 | BY21: 3 | BZ21: 3 | CA21: 3 | CB21: 3
C22: MASH | D22: =SUM(E22:CT22) -> 0
C23: MAGENTO | D23: =SUM(E23:CT23) -> 0
A24: 6 | B24: Melon | C24: ALF | D24: =SUM(E24:CT24) -> 37 | BL24: 1 | BM24: 2 | BN24: 2 | BO24: 7 | BP24: 7 | BQ24: 6 | BR24: 6 | BS24: 6
C25: WAREX | D25: =SUM(E25:CT25) -> 0
C26: OPTIMUS | D26: =SUM(E26:CT26) -> 0
C27: MASH | D27: =SUM(E27:CT27) -> 66 | BO27: 5 | BP27: 5 | BQ27: 7 | BR27: 7 | BS27: 7 | BT27: 7 | BU27: 7 | BV27: 7 | BW27: 7 | BX27: 7
C28: MAGENTO | D28: =SUM(E28:CT28) -> 0
A29: 6 | B29: T-Mobile New Variants | C29: ALF | D29: =SUM(E29:CT29) -> 0
C30: WAREX | D30: =SUM(E30:CT30) -> 26 | BO30: 5 | BP30: 7 | BQ30: 7 | BR30: 5 | BS30: 2
C31: OPTIMUS | D31: =SUM(E31:CT31) -> 18 | BQ31: 7 | BR31: 3 | BS31: 3 | BT31: 3 | BU31: 2
C32: MASH | D32: =SUM(E32:CT32) -> 0
C33: MAGENTO | D33: =SUM(E33:CT33) -> 0
A34: 8 | B34: PLK Service Care Pack Update 2025 | C34: ALF | D34: =SUM(E34:CT34) -> 0
C35: WAREX | D35: =SUM(E35:CT35) -> 22 | BX35: 4 | BY35: 5 | BZ35: 5 | CA35: 5 | CB35: 3
C36: OPTIMUS | D36: =SUM(E36:CT36) -> 50 | CC36: 5 | CD36: 5 | CE36: 5 | CF36: 5 | CG36: 5 | CH36: 5 | CI36: 5 | CJ36: 5 | CK36: 5 | CL36: 5
C37: WAREX | D37: =SUM(E37:CT37) -> 24 | CC37: 4 | CD37: 4 | CE37: 4 | CF37: 4 | CG37: 4 | CH37: 4
C38: OPTIMUS | D38: =SUM(E38:CT38) -> 8 | CE38: 4 | CF38: 4
A39: 7 | B39: PKO BP - New protection services for PKO BP | C39: ALF | D39: =SUM(E39:CT39) -> 0
C40: WAREX | D40: =SUM(E40:CT40) -> 74 | BZ40: 4 | CA40: 4 | CB40: 4 | CC40: 4 | CD40: 4 | CE40: 3 | CF40: 5 | CG40: 5 | CH40: 5 | CI40: 5 | CJ40: 5 | CK40: 5 | CL40: 5 | CM40: 5 | CN40: 5 | CO40: 3 | CP40: 3
C41: OPTIMUS | D41: =SUM(E41:CT41) -> 0
C42: MASH | D42: =SUM(E42:CT42) -> 0
C43: MAGENTO | D43: =SUM(E43:CT43) -> 0
A44: 8 | B44: Orange B2B Enterprise | C44: ALF | D44: =SUM(E44:CT44) -> 0
C45: WAREX | D45: =SUM(E45:CT45) -> 21 | AD45: 5 | AE45: 5 | AF45: 3 | AG45: 4 | AH45: 2 | AI45: 2
C46: OPTIMUS | D46: =SUM(E46:CT46) -> 26 | AF46: 5 | AG46: 5 | AH46: 5 | AI46: 5 | AJ46: 2 | AK46: 2 | AL46: 2
C47: MASH | D47: =SUM(E47:CT47) -> 0
C48: MAGENTO | D48: =SUM(E48:CT48) -> 0
A49: 9 | B49: Worten (including Unified API changes) | C49: ALF | D49: =SUM(E49:CT49) -> 80 | BJ49: 5 | BK49: 5 | BL49: 10 | BM49: 10 | BN49: 10 | BO49: 10 | BP49: 10 | BQ49: 10 | BR49: 10
C50: WAREX | D50: =SUM(E50:CT50) -> 54 | BL50: 3 | BM50: 3 | BN50: 3 | BO50: 3 | BP50: 3 | BQ50: 3 | BR50: 3 | BS50: 3 | BT50: 3 | BU50: 3 | BV50: 3 | BW50: 3 | BX50: 3 | BY50: 3 | BZ50: 3 | CA50: 3 | CB50: 3 | CC50: 3
C51: OPTIMUS | D51: =SUM(E51:CT51) -> 82 | BM51: 2 | BN51: 2 | BO51: 2 | BP51: 5 | BQ51: 5 | BR51: 10 | BS51: 5 | BU51: 3 | BV51: 3 | BW51: 5 | BX51: 5 | BY51: 5 | BZ51: 5 | CA51: 5 | CB51: 5 | CC51: 5 | CD51: 5 | CE51: 5
C52: MASH | D52: =SUM(E52:CT52) -> 36 | BI52: 5 | BJ52: 5 | BK52: 5 | BL52: 7 | BM52: 7 | BN52: 7
C53: MAGENTO | D53: =SUM(E53:CT53) -> 95 | BI53: 5 | BJ53: 10 | BK53: 10 | BL53: 10 | BM53: 10 | BN53: 10 | BO53: 10 | BP53: 10 | BQ53: 10 | BR53: 10
A54: 10 | B54: MM Spain (rental + TBC) | C54: ALF | D54: =SUM(E54:CT54) -> 55 | CG54: 10 | CH54: 10 | CI54: 10 | CJ54: 10 | CK54: 10 | CL54: 5
C55: WAREX | D55: =SUM(E55:CT55) -> 0 | CO55: ? | CP55: ?
C56: OPTIMUS | D56: =SUM(E56:CT56) -> 0
C57: MASH | D57: =SUM(E57:CT57) -> 20 | CI57: 5 | CJ57: 5 | CK57: 5 | CL57: 5
C58: MAGENTO | D58: =SUM(E58:CT58) -> 30 | CG58: 5 | CH58: 5 | CI58: 5 | CJ58: 5 | CK58: 5 | CL58: 5
A59: 11 | B59: Warranty for Orange Slovakia​ | C59: ALF | D59: =SUM(E59:CT59) -> 0
C60: WAREX | D60: =SUM(E60:CT60) -> 0
C61: OPTIMUS | D61: =SUM(E61:CT61) -> 0
C62: MASH | D62: =SUM(E62:CT62) -> 0
C63: MAGENTO | D63: =SUM(E63:CT63) -> 0
A64: 12 | B64: B2B – Protection Product Changes | C64: ALF | D64: =SUM(E64:CT64) -> 0
C65: WAREX | D65: =SUM(E65:CT65) -> 34 | BW65: 5 | BX65: 5 | BY65: 5 | BZ65: 5 | CA65: 3 | CB65: 3 | CC65: 3 | CD65: 3 | CE65: 2
C66: WAREX | D66: =SUM(E66:CT66) -> 28 | CD66: 3 | CE66: 5 | CF66: 5 | CG66: 5 | CH66: 5 | CI66: 3 | CJ66: 2
C67: MASH | D67: =SUM(E67:CT67) -> 0
C68: MAGENTO | D68: =SUM(E68:CT68) -> 0
B69: IRIS | C69: ALF | D69: =SUM(E69:CT69) -> 0
C70: WAREX | D70: =SUM(E70:CT70) -> 38 | BN70: 2 | BO70: 2 | BP70: 2 | BQ70: 2 | BR70: 2 | BS70: 2 | BT70: 2 | BU70: 2 | BV70: 2 | BW70: 2 | BX70: 2 | BY70: 2 | BZ70: 2 | CA70: 2 | CB70: 2 | CC70: 2 | CD70: 2 | CE70: 2 | CF70: 2
C71: OPTIMUS | D71: =SUM(E71:CT71) -> 0
C72: MASH | D72: =SUM(E72:CT72) -> 0
C73: MAGENTO | D73: =SUM(E73:CT73) -> 0
A74: 8 | B74: Dynamic Pricing | C74: ALF | D74: =SUM(E74:CT74) -> 36 | AH74: 2 | AI74: 3 | AJ74: 3 | AK74: 5 | AL74: 5 | AM74: 5 | AN74: 5 | AO74: 1 | AP74: 1 | BH74: 1 | BI74: 1 | BJ74: 1 | BK74: 1 | BL74: 1 | BM74: 1
C75: WAREX | D75: =SUM(E75:CT75) -> 0
C76: OPTIMUS | D76: =SUM(E76:CT76) -> 0
C77: MASH | D77: =SUM(E77:CT77) -> 41 | AI77: 2 | AJ77: 2 | AK77: 1 | AL77: 1 | AM77: 1 | AN77: 1 | AO77: 1 | AP77: 1 | BE77: 3 | BF77: 5 | BG77: 7 | BH77: 7 | BI77: 7 | BJ77: 2
C78: MAGENTO | D78: =SUM(E78:CT78) -> 0
A79: 9 | B79: Decision Cube | C79: ALF | D79: =SUM(E79:CT79) -> 117 | U79: 5 | V79: 5 | W79: 5 | X79: 5 | Y79: 5 | Z79: 5 | AA79: 5 | AB79: 5 | AC79: 5 | AD79: 3 | AE79: 5 | AF79: 6 | AG79: 6 | AH79: 5 | AI79: 5 | AJ79: 3 | AK79: 3 | AL79: 3 | AM79: 3 | AN79: 3 | AO79: 3 | AP79: 3 | AQ79: 3 | AR79: 3 | AS79: 3 | AV79: 3 | AW79: 3 | AX79: 3 | AY79: 3
C80: WAREX | D80: =SUM(E80:CT80) -> 0
C81: OPTIMUS | D81: =SUM(E81:CT81) -> 0
C82: MASH | D82: =SUM(E82:CT82) -> 0
C83: MAGENTO | D83: =SUM(E83:CT83) -> 0
A84: 10 | B84: Paperless | C84: ALF | D84: =SUM(E84:CT84) -> 14 | AM84: 2 | AN84: 2 | AO84: 2 | AP84: 2 | AQ84: 2 | AR84: 2 | AS84: 2
C85: WAREX | D85: =SUM(E85:CT85) -> 0
C86: OPTIMUS | D86: =SUM(E86:CT86) -> 0
C87: MASH | D87: =SUM(E87:CT87) -> 0
C88: MAGENTO | D88: =SUM(E88:CT88) -> 0
A89: 11 | B89: Upgrade | C89: ALF | D89: =SUM(E89:CT89) -> 38 | AQ89: 5 | AR89: 5 | AS89: 5 | AV89: 3 | AW89: 5 | AX89: 5 | AY89: 5 | AZ89: 5
C90: WAREX | D90: =SUM(E90:CT90) -> 0
C91: OPTIMUS | D91: =SUM(E91:CT91) -> 0
C92: MASH | D92: =SUM(E92:CT92) -> 0
C93: MAGENTO | D93: =SUM(E93:CT93) -> 0
B94: Mbox for MM (Worten) - 23.07 | C94: ALF | D94: =SUM(E94:CT94) -> 20 | V94: 10 | W94: 8 | X94: 2
C95: WAREX | D95: =SUM(E95:CT95) -> 0
C96: OPTIMUS | D96: =SUM(E96:CT96) -> 0
C97: MASH | D97: =SUM(E97:CT97) -> 0
C98: MAGENTO | D98: =SUM(E98:CT98) -> 20 | V98: 10 | W98: 8 | X98: 2
A99: 22 | B99: Rebranding | C99: ALF | D99: =SUM(E99:CT99) -> 107 | Q99: 6 | R99: 10 | S99: 8 | T99: 8 | U99: 8 | V99: 8 | W99: 5 | X99: 5 | Y99: 9 | AC99: 5 | AD99: 5 | AE99: 5 | AF99: 5 | AG99: 5 | AP99: 5 | AR99: 5 | AS99: 5
C100: WAREX | D100: =SUM(E100:CT100) -> 120 | Q100: 5 | R100: 3 | S100: 5 | T100: 2 | U100: 2 | V100: 2 | W100: 0 | X100: 2 | Y100: 2 | Z100: 1 | AA100: 1 | AB100: 1 | AC100: 2 | AD100: 2 | AE100: 2 | AF100: 2 | AG100: 5 | AJ100: 10 | AK100: 12 | AL100: 13 | AM100: 10 | AN100: 10 | AO100: 3 | AP100: 3 | AQ100: 5 | AR100: 5 | AS100: 10
C101: OPTIMUS | D101: =SUM(E101:CT101) -> 281 | M101: 2 | N101: 6 | O101: 10 | P101: 15 | Q101: 15 | R101: 15 | S101: 5 | T101: 5 | U101: 10 | V101: 10 | W101: 10 | X101: 10 | Y101: 10 | Z101: 10 | AA101: 10 | AB101: 10 | AC101: 10 | AD101: 10 | AE101: 10 | AF101: 10 | AG101: 10 | AH101: 10 | AI101: 10 | AJ101: 10 | AK101: 10 | AL101: 5 | AM101: 5 | AN101: 3 | AO101: 5 | AP101: 5 | AQ101: 5 | AR101: 5 | AS101: 5
...

Sheet CAPACITY
E1: ALF | F1: ALL | G1: {=SUM((G13:K83)*(--($E$13:$E$83=$E$1)))} -> 51.15 | N1: {=SUM((N13:R83)*(--($E$13:$E$83=$E$1)))} -> 51.15 | U1: {=SUM((U13:Y83)*(--($E$13:$E$83=$E$1)))} -> 51.15 | AB1: {=SUM((AB13:AF83)*(--($E$13:$E$83=$E$1)))} -> 40.15 | AI1: {=SUM((AI13:AM83)*(--($E$13:$E$83=$E$1)))} -> 51.15 | AP1: {=SUM((AP13:AT83)*(--($E$13:$E$83=$E$1)))} -> 51.15 | AW1: {=SUM((AW13:BA83)*(--($E$13:$E$83=$E$1)))} -> 51.15 | BD1: {=SUM((BD13:BH83)*(--($E$13:$E$83=$E$1)))} -> 26.4 | BK1: {=SUM((BK13:BO83)*(--($E$13:$E$83=$E$1)))} -> 53.6 | BR1: {=SUM((BR13:BV83)*(--($E$13:$E$83=$E$1)))} -> 53.6 | BY1: {=SUM((BY13:CC83)*(--($E$13:$E$83=$E$1)))} -> 54.6 | CF1: {=SUM((CF13:CJ83)*(--($E$13:$E$83=$E$1)))} -> 33.3 | CM1: {=SUM((CM13:CQ83)*(--($E$13:$E$83=$E$1)))} -> 54.6 | CT1: {=SUM((CT13:CX83)*(--($E$13:$E$83=$E$1)))} -> 53.3 | DA1: {=SUM((DA13:DE83)*(--($E$13:$E$83=$E$1)))} -> 47.65 | DH1: {=SUM((DH13:DL83)*(--($E$13:$E$83=$E$1)))} -> 51.5 | DO1: {=SUM((DO13:DS83)*(--($E$13:$E$83=$E$1)))} -> 42.5 | DV1: {=SUM((DV13:DZ83)*(--($E$13:$E$83=$E$1)))} -> 42.8 | EC1: {=SUM((EC13:EG83)*(--($E$13:$E$83=$E$1)))} -> 49.8 | EJ1: {=SUM((EJ13:EN83)*(--($E$13:$E$83=$E$1)))} -> 46.65 | EQ1: {=SUM((EQ13:EU83)*(--($E$13:$E$83=$E$1)))} -> 55.8 | EX1: {=SUM((EX13:FB83)*(--($E$13:$E$83=$E$1)))} -> 55.45 | FE1: {=SUM((FE13:FI83)*(--($E$13:$E$83=$E$1)))} -> 33.55 | FL1: {=SUM((FL13:FP83)*(--($E$13:$E$83=$E$1)))} -> 54.45 | FS1: {=SUM((FS13:FW83)*(--($E$13:$E$83=$E$1)))} -> 59.1 | FZ1: {=SUM((FZ13:GD83)*(--($E$13:$E$83=$E$1)))} -> 54.8 | GG1: {=SUM((GG13:GK83)*(--($E$13:$E$83=$E$1)))} -> 54.8 | GN1: {=SUM((GN13:GR83)*(--($E$13:$E$83=$E$1)))} -> 55.1 | GU1: {=SUM((GU13:GY83)*(--($E$13:$E$83=$E$1)))} -> 59.1 | HB1: {=SUM((HB13:HF83)*(--($E$13:$E$83=$E$1)))} -> 39.35 | HI1: {=SUM((HI13:HM83)*(--($E$13:$E$83=$E$1)))} -> 57.1 | HP1: {=SUM((HP13:HT83)*(--($E$13:$E$83=$E$1)))} -> 56.45 | HW1: {=SUM((HW13:IA83)*(--($E$13:$E$83=$E$1)))} -> 55.1 | ID1: {=SUM((ID13:IH83)*(--($E$13:$E$83=$E$1)))} -> 49.8 | IK1: {=SUM((IK13:IO83)*(--($E$13:$E$83=$E$1)))} -> 59.1 | IR1: {=SUM((IR13:IV83)*(--($E$13:$E$83=$E$1)))} -> 42.1 | IY1: {=SUM((IY13:JC83)*(--($E$13:$E$83=$E$1)))} -> 59.1 | JF1: {=SUM((JF13:JJ83)*(--($E$13:$E$83=$E$1)))} -> 55.1 | JM1: {=SUM((JM13:JQ83)*(--($E$13:$E$83=$E$1)))} -> 52.8 | JT1: {=SUM((JT13:JX83)*(--($E$13:$E$83=$E$1)))} -> 58.45 | KA1: {=SUM((KA13:KE83)*(--($E$13:$E$83=$E$1)))} -> 56.1 | KH1: {=SUM((KH13:KL83)*(--($E$13:$E$83=$E$1)))} -> 22.2 | KO1: {=SUM((KO13:KS83)*(--($E$13:$E$83=$E$1)))} -> 33.35 | KV1: {=SUM((KV13:KZ83)*(--($E$13:$E$83=$E$1)))} -> 44.4 | LC1: {=SUM((LC13:LG83)*(--($E$13:$E$83=$E$1)))} -> 54.45 | LJ1: {=SUM((LJ13:LN83)*(--($E$13:$E$83=$E$1)))} -> 54.45 | LQ1: {=SUM((LQ13:LU83)*(--($E$13:$E$83=$E$1)))} -> 49 | LX1: {=SUM((LX13:MB83)*(--($E$13:$E$83=$E$1)))} -> 54.45 | ME1: {=SUM((ME13:MI83)*(--($E$13:$E$83=$E$1)))} -> 55.8 | ML1: {=SUM((ML13:MP83)*(--($E$13:$E$83=$E$1)))} -> 54.1 | MS1: {=SUM((MS13:MW83)*(--($E$13:$E$83=$E$1)))} -> 57.4 | MZ1: {=SUM((MZ13:ND83)*(--($E$13:$E$83=$E$1)))} -> 60.3 | NG1: {=SUM((NG13:NK83)*(--($E$13:$E$83=$E$1)))} -> 64.8 | NN1: {=SUM((NN13:NR83)*(--($E$13:$E$83=$E$1)))} -> 62.85 | NU1: {=SUM((NU13:NY83)*(--($E$13:$E$83=$E$1)))} -> 61.85 | OB1: {=SUM((OB13:OF83)*(--($E$13:$E$83=$E$1)))} -> 72.16 | OI1: {=SUM((OI13:OM83)*(--($E$13:$E$83=$E$1)))} -> 59.15 | OP1: {=SUM((OP13:OT83)*(--($E$13:$E$83=$E$1)))} -> 61.8 | OW1: {=SUM((OW13:PA83)*(--($E$13:$E$83=$E$1)))} -> 46.05 | PD1: {=SUM((PD13:PH83)*(--($E$13:$E$83=$E$1)))} -> 35.1 | PK1: {=SUM((PK13:PO83)*(--($E$13:$E$83=$E$1)))} -> 63.5 | PR1: {=SUM((PR13:PV83)*(--($E$13:$E$83=$E$1)))} -> 57.2 | PY1: {=SUM((PY13:QC83)*(--($E$13:$E$83=$E$1)))} -> 59.85 | QF1: {=SUM((QF13:QJ83)*(--($E$13:$E$83=$E$1)))} -> 62.8 | QM1: {=SUM((QM13:QQ83)*(--($E$13:$E$83=$E$1)))} -> 61.85 | QT1: {=SUM((QT13:QX83)*(--($E$13:$E$83=$E$1)))} -> 64.4 | RA1: {=SUM((RA13:RE83)*(--($E$13:$E$83=$E$1)))} -> 47.25 | RH1: {=SUM((RH13:RL83)*(--($E$13:$E$83=$E$1)))} -> 64.45 | RO1: {=SUM((RO13:RS83)*(--($E$13:$E$83=$E$1)))} -> 67.05 | RV1: {=SUM((RV13:RZ83)*(--($E$13:$E$83=$E$1)))} -> 63.4 | SC1: {=SUM((SC13:SG83)*(--($E$13:$E$83=$E$1)))} -> 53.45 | SJ1: {=SUM((SJ13:SN83)*(--($E$13:$E$83=$E$1)))} -> 50.18 | SQ1: {=SUM((SQ13:SU83)*(--($E$13:$E$83=$E$1)))} -> 50.12 | SX1: {=SUM((SX13:TB83)*(--($E$13:$E$83=$E$1)))} -> 51.1 | TE1: {=SUM((TE13:TI83)*(--($E$13:$E$83=$E$1)))} -> 44 | TL1: {=SUM((TL13:TP83)*(--($E$13:$E$83=$E$1)))} -> 66.4 | TS1: {=SUM((TS13:TW83)*(--($E$13:$E$83=$E$1)))} -> 63.5 | TZ1: {=SUM((TZ13:UD83)*(--($E$13:$E$83=$E$1)))} -> 63.71 | UG1: {=SUM((UG13:UK83)*(--($E$13:$E$83=$E$1)))} -> 68.05 | UN1: {=SUM((UN13:UR83)*(--($E$13:$E$83=$E$1)))} -> 64.15 | UU1: {=SUM((UU13:UY83)*(--($E$13:$E$83=$E$1)))} -> 59.75 | VB1: {=SUM((VB13:VF83)*(--($E$13:$E$83=$E$1)))} -> 62.05 | VI1: {=SUM((VI13:VM83)*(--($E$13:$E$83=$E$1)))} -> 58.45 | VP1: {=SUM((VP13:VT83)*(--($E$13:$E$83=$E$1)))} -> 63.6 | VW1: {=SUM((VW13:WA83)*(--($E$13:$E$83=$E$1)))} -> 66.25 | WD1: {=SUM((WD13:WH83)*(--($E$13:$E$83=$E$1)))} -> 67.6 | WK1: {=SUM((WK13:WO83)*(--($E$13:$E$83=$E$1)))} -> 66 | WR1: {=SUM((WR13:WV83)*(--($E$13:$E$83=$E$1)))} -> 34.2 | WY1: {=SUM((WY13:XC83)*(--($E$13:$E$83=$E$1)))} -> 68 | XF1: {=SUM((XF13:XJ83)*(--($E$13:$E$83=$E$1)))} -> 67 | XM1: {=SUM((XM13:XQ83)*(--($E$13:$E$83=$E$1)))} -> 65.85 | XT1: {=SUM((XT13:XX83)*(--($E$13:$E$83=$E$1)))} -> 62.85 | YA1: {=SUM((YA13:YE83)*(--($E$13:$E$83=$E$1)))} -> 63.2 | YH1: {=SUM((YH13:YL83)*(--($E$13:$E$83=$E$1)))} -> 17 | YO1: {=SUM((YO13:YS83)*(--($E$13:$E$83=$E$1)))} -> 29.5 | YV1: {=SUM((YV13:YZ83)*(--($E$13:$E$83=$E$1)))} -> 40.55 | ZC1: {=SUM((ZC13:ZG83)*(--($E$13:$E$83=$E$1)))} -> 67.5 | ZJ1: {=SUM((ZJ13:ZN83)*(--($E$13:$E$83=$E$1)))} -> 66.5 | ZQ1: {=SUM((ZQ13:ZU83)*(--($E$13:$E$83=$E$1)))} -> 63.85 | ZX1: {=SUM((ZX13:AAB83)*(--($E$13:$E$83=$E$1)))} -> 69.75 | AAE1: {=SUM((AAE13:AAI83)*(--($E$13:$E$83=$E$1)))} -> 66.75 | AAL1: {=SUM((AAL13:AAP83)*(--($E$13:$E$83=$E$1)))} -> 64.1 | AAS1: {=SUM((AAS13:AAW83)*(--($E$13:$E$83=$E$1)))} -> 64.1 | AAZ1: {=SUM((AAZ13:ABD83)*(--($E$13:$E$83=$E$1)))} -> 60.15 | ABG1: {=SUM((ABG13:ABK83)*(--($E$13:$E$83=$E$1)))} -> 68.8 | ABN1: {=SUM((ABN13:ABR83)*(--($E$13:$E$83=$E$1)))} -> 67.45 | ABU1: {=SUM((ABU13:ABY83)*(--($E$13:$E$83=$E$1)))} -> 62.15 | ACB1: {=SUM((ACB13:ACF83)*(--($E$13:$E$83=$E$1)))} -> 64.45 | ACI1: {=SUM((ACI13:ACM83)*(--($E$13:$E$83=$E$1)))} -> 46.95 | ACP1: {=SUM((ACP13:ACT83)*(--($E$13:$E$83=$E$1)))} -> 63.15 | ACW1: {=SUM((ACW13:ADA83)*(--($E$13:$E$83=$E$1)))} -> 60.3 | ADD1: {=SUM((ADD13:ADH83)*(--($E$13:$E$83=$E$1)))} -> 58.85 | ADK1: {=SUM((ADK13:ADO83)*(--($E$13:$E$83=$E$1)))} -> 51 | ADR1: {=SUM((ADR13:ADV83)*(--($E$13:$E$83=$E$1)))} -> 53 | ADY1: {=SUM((ADY13:AEC83)*(--($E$13:$E$83=$E$1)))} -> 63.95 | AEF1: {=SUM((AEF13:AEJ83)*(--($E$13:$E$83=$E$1)))} -> 68.6 | AEM1: {=SUM((AEM13:AEQ83)*(--($E$13:$E$83=$E$1)))} -> 47 | AET1: {=SUM((AET13:AEX83)*(--($E$13:$E$83=$E$1)))} -> 67.6 | AFA1: {=SUM((AFA13:AFE83)*(--($E$13:$E$83=$E$1)))} -> 67.6 | AFH1: {=SUM((AFH13:AFL83)*(--($E$13:$E$83=$E$1)))} -> 66.75 | AFO1: {=SUM((AFO13:AFS83)*(--($E$13:$E$83=$E$1)))} -> 65.1 | AFV1: {=SUM((AFV13:AFZ83)*(--($E$13:$E$83=$E$1)))} -> 55.8 | AGC1: {=SUM((AGC13:AGG83)*(--($E$13:$E$83=$E$1)))} -> 53.15 | AGJ1: {=SUM((AGJ13:AGN83)*(--($E$13:$E$83=$E$1)))} -> 61.1 | AGQ1: {=SUM((AGQ13:AGU83)*(--($E$13:$E$83=$E$1)))} -> 65.45 | AGX1: {=SUM((AGX13:AHB83)*(--($E$13:$E$83=$E$1)))} -> 65.1 | AHE1: {=SUM((AHE13:AHI83)*(--($E$13:$E$83=$E$1)))} -> 54 | AHL1: {=SUM((AHL13:AHP83)*(--($E$13:$E$83=$E$1)))} -> 63.1 | AHS1: {=SUM((AHS13:AHW83)*(--($E$13:$E$83=$E$1)))} -> 69.75 | AHZ1: {=SUM((AHZ13:AID83)*(--($E$13:$E$83=$E$1)))} -> 69.75 | AIG1: {=SUM((AIG13:AIK83)*(--($E$13:$E$83=$E$1)))} -> 69.75 | AIN1: {=SUM((AIN13:AIR83)*(--($E$13:$E$83=$E$1)))} -> 69.75 | AIU1: {=SUM((AIU13:AIY83)*(--($E$13:$E$83=$E$1)))} -> 67.75 | AJB1: {=SUM((AJB13:AJF83)*(--($E$13:$E$83=$E$1)))} -> 69.1 | AJI1: {=SUM((AJI13:AJM83)*(--($E$13:$E$83=$E$1)))} -> 68.75 | AJP1: {=SUM((AJP13:AJT83)*(--($E$13:$E$83=$E$1)))} -> 69.75 | AJW1: {=SUM((AJW13:AKA83)*(--($E$13:$E$83=$E$1)))} -> 69.75 | AKD1: {=SUM((AKD13:AKH83)*(--($E$13:$E$83=$E$1)))} -> 69.75 | AKK1: {=SUM((AKK13:AKO83)*(--($E$13:$E$83=$E$1)))} -> 69.75 | AKR1: {=SUM((AKR13:AKV83)*(--($E$13:$E$83=$E$1)))} -> 49.1 | AKY1: {=SUM((AKY13:ALC83)*(--($E$13:$E$83=$E$1)))} -> 69.75 | ALF1: {=SUM((ALF13:ALJ83)*(--($E$13:$E$83=$E$1)))} -> 69.75 | ALM1: {=SUM((ALM13:ALQ83)*(--($E$13:$E$83=$E$1)))} -> 69.75 | ALT1: {=SUM((ALT13:ALX83)*(--($E$13:$E$83=$E$1)))} -> 69.75 | AMA1: {=SUM((AMA13:AME83)*(--($E$13:$E$83=$E$1)))} -> 69.75 | AMH1: {=SUM((AMH13:AML83)*(--($E$13:$E$83=$E$1)))} -> 39 | AMO1: {=SUM((AMO13:AMS83)*(--($E$13:$E$83=$E$1)))} -> 42 | AMV1: {=SUM((AMV13:AMZ83)*(--($E$13:$E$83=$E$1)))} -> 54.75 | ANC1: {=SUM((ANC13:ANG83)*(--($E$13:$E$83=$E$1)))} -> 69.75 | ANJ1: {=SUM((ANJ13:ANN83)*(--($E$13:$E$83=$E$1)))} -> 69.75 | ANQ1: {=SUM((ANQ13:ANU83)*(--($E$13:$E$83=$E$1)))} -> 69.75 | ANX1: {=SUM((ANX13:AOB83)*(--($E$13:$E$83=$E$1)))} -> 69.75 | AOE1: {=SUM((AOE13:AOI83)*(--($E$13:$E$83=$E$1)))} -> 69.75 | AOL1: {=SUM((AOL13:AOP83)*(--($E$13:$E$83=$E$1)))} -> 69.75
E2: ALF | F2: PROJECTS | G2: 27.342 | N2: 27.342 | U2: 27.342 | AB2: 21.462 | AI2: 27.342 | AP2: 27.342 | AW2: 27.342 | BD2: 14.028 | BK2: 28.371 | BR2: 28.098 | BY2: 28.518 | CF2: 18.312 | CM2: 28.371 | CT2: 28.245 | DA2: 25.872 | DH2: 25.536 | DO2: 23.709 | DV2: 23.835 | EC2: 26.775 | EJ2: 25.452 | EQ2: 29.295 | EX2: 26.922 | FE2: 17.157 | FL2: 28.728 | FS2: 30.681 | FZ2: 26.922 | GG2: 26.922 | GN2: 27.048 | GU2: 28.728 | HB2: 22.386 | HI2: 29.841 | HP2: 29.568 | HW2: 29.001 | ID2: 25.956 | IK2: 30.681 | IR2: 22.281 | IY2: 30.681 | JF2: 29.001 | JM2: 27.342 | JT2: 30.408 | KA2: 29.421 | KH2: 12.39 | KO2: 17.346 | KV2: 23.247 | LC2: 28.728 | LJ2: 28.728 | LQ2: 26.439 | LX2: 28.455 | ME2: 27.342 | ML2: 28.581 | MS2: 29.967 | MZ2: 31.185 | NG2: 33.075 | NN2: 32.256 | NU2: 31.836 | OB2: 36.1662 | OI2: 30.702 | OP2: 31.815 | OW2: 23.94 | PD2: 18.102 | PK2: 30.576 | PR2: 29.883 | PY2: 30.723 | QF2: 32.235 | QM2: 31.836 | QT2: 32.214 | RA2: 22.911 | RH2: 32.928 | RO2: 33.327 | RV2: 31.794 | SC2: 28.308 | SJ2: 24.9816 | SQ2: 26.6364 | SX2: 26.901 | TE2: 23.52 | TL2: 31.794 | TS2: 30.576 | TZ2: 32.6172 | UG2: 33.747 | UN2: 32.109 | UU2: 29.001 | VB2: 29.967 | VI2: 30.408 | VP2: 32.571 | VW2: 33.684 | WD2: 33.831 | WK2: 33.579 | WR2: 17.703 | WY2: 34.419 | XF2: 33.999 | XM2: 33.516 | XT2: 31.836 | YA2: 32.403 | YH2: 9.66 | YO2: 16.443 | YV2: 18.144 | ZC2: 30.303 | ZJ2: 29.883 | ZQ2: 30.723 | ZX2: =ZX1*PARAMS!$F$3 -> 39.06 | AAE2: =AAE1*PARAMS!$F$3 -> 37.38 | AAL2: =AAL1*PARAMS!$F$3 -> 35.896 | AAS2: =AAS1*PARAMS!$F$3 -> 35.896 | AAZ2: =AAZ1*PARAMS!$F$3 -> 33.684 | ABG2: =ABG1*PARAMS!$F$3 -> 38.528 | ABN2: =ABN1*PARAMS!$F$3 -> 37.772 | ABU2: =ABU1*PARAMS!$F$3 -> 34.804 | ACB2: =ACB1*PARAMS!$F$3 -> 36.092 | ACI2: =ACI1*PARAMS!$F$3 -> 26.292 | ACP2: =ACP1*PARAMS!$F$3 -> 35.364 | ACW2: =ACW1*PARAMS!$F$3 -> 33.768 | ADD2: =ADD1*PARAMS!$F$3 -> 32.956 | ADK2: =ADK1*PARAMS!$F$3 -> 28.56 | ADR2: =ADR1*PARAMS!$F$3 -> 29.68 | ADY2: =ADY1*PARAMS!$F$3 -> 35.812 | AEF2: =AEF1*PARAMS!$F$3 -> 38.416 | AEM2: =AEM1*PARAMS!$F$3 -> 26.32 | AET2: =AET1*PARAMS!$F$3 -> 37.856 | AFA2: =AFA1*PARAMS!$F$3 -> 37.856 | AFH2: =AFH1*PARAMS!$F$3 -> 37.38 | AFO2: =AFO1*PARAMS!$F$3 -> 36.456 | AFV2: =AFV1*PARAMS!$F$3 -> 31.248 | AGC2: =AGC1*PARAMS!$F$3 -> 29.764 | AGJ2: =AGJ1*PARAMS!$F$3 -> 34.216 | AGQ2: =AGQ1*PARAMS!$F$3 -> 36.652 | AGX2: =AGX1*PARAMS!$F$3 -> 36.456 | AHE2: =AHE1*PARAMS!$F$3 -> 30.24 | AHL2: =AHL1*PARAMS!$F$3 -> 35.336 | AHS2: =AHS1*PARAMS!$F$3 -> 39.06 | AHZ2: =AHZ1*PARAMS!$F$3 -> 39.06 | AIG2: =AIG1*PARAMS!$F$3 -> 39.06 | AIN2: =AIN1*PARAMS!$F$3 -> 39.06 | AIU2: =AIU1*PARAMS!$F$3 -> 37.94 | AJB2: =AJB1*PARAMS!$F$3 -> 38.696 | AJI2: =AJI1*PARAMS!$F$3 -> 38.5 | AJP2: =AJP1*PARAMS!$F$3 -> 39.06 | AJW2: =AJW1*PARAMS!$F$3 -> 39.06 | AKD2: =AKD1*PARAMS!$F$3 -> 39.06 | AKK2: =AKK1*PARAMS!$F$3 -> 39.06 | AKR2: =AKR1*PARAMS!$F$3 -> 27.496 | AKY2: =AKY1*PARAMS!$F$3 -> 39.06 | ALF2: =ALF1*PARAMS!$F$3 -> 39.06 | ALM2: =ALM1*PARAMS!$F$3 -> 39.06 | ALT2: =ALT1*PARAMS!$F$3 -> 39.06 | AMA2: =AMA1*PARAMS!$F$3 -> 39.06 | AMH2: =AMH1*PARAMS!$F$3 -> 21.84 | AMO2: =AMO1*PARAMS!$F$3 -> 23.52 | AMV2: =AMV1*PARAMS!$F$3 -> 30.66 | ANC2: =ANC1*PARAMS!$F$3 -> 39.06 | ANJ2: =ANJ1*PARAMS!$F$3 -> 39.06 | ANQ2: =ANQ1*PARAMS!$F$3 -> 39.06 | ANX2: =ANX1*PARAMS!$F$3 -> 39.06 | AOE2: =AOE1*PARAMS!$F$3 -> 39.06 | AOL2: =AOL1*PARAMS!$F$3 -> 39.06
